Workbook

Sheet Menu
D2: SINAPI
D3: Sistema Nacional de Pesquisa de Custos e Índices da Construção Civil
B5: =HYPERLINK("#Busca!$B$8","Pesquisa") -> 0 | D5: Permite a pesquisa de insumos ou composições, por termos não consecutivos, com filtro "contém" e "não contém"
B7: =HYPERLINK("#'ISD'!$F$11","Insumos Não Desonerado") -> 0 | D7: Relatório de preços de insumos sem desoneração para as 27 UF. Inclui link para as fichas de especificação técnica dos insumos.
B9: =HYPERLINK("#'ICD'!$F$11","Insumos Desonerado") -> 0 | D9: Relatório de preços de insumos com desoneração para as 27 UF. Inclui link para as fichas de especificação técnica dos insumos.
B11: =HYPERLINK("#'ISE'!$F$11","Insumos Sem Encargos") -> 0 | D11: Relatório de preços de insumos sem encargos sociais para as 27 UF. Inclui link para as fichas de especificação técnica dos insumos.
B13: =HYPERLINK("#'CSD'!$E$11","Composições Não Desonerado") -> 0 | D13: Relatório de custos de composição sem desoneração para as 27 UF. Inclui links para os cadernos técnicos, links para o analítico da composição, composições com custo e sem custo.
B15: =HYPERLINK("#'CCD'!$E$11","Composições Desonerado") -> 0 | D15: Relatório de custos de composição com desoneração para as 27 UF. Inclui links para os cadernos técnicos, links para o analítico da composição, composições com custo e sem custo.
B17: =HYPERLINK("#'CSE'!$E$11","Composições Sem Encargos") -> 0 | D17: Relatório de custos de composição sem encargos sociais para as 27 UF. Inclui links para os cadernos técnicos, links para o analítico da composição, composições com custo e sem custo.
B19: =HYPERLINK("#Analítico!$A$11","Analítico") -> 0 | D19: Relatório analítico das composições.
B21: =HYPERLINK("#'Analítico com Custo'!$C$8","Analítico com Custo") -> 0 | D21: Permite a consulta do analítico com custos para uma composição, UF e regime de desoneração selecionados.

Sheet Busca
A1: SINAPI - Sistema Nacional de Pesquisa de Custos e Índices da Construção Civil
A2: PESQUISA POR TERMOS NAS DESCRIÇÕES
B4: Instruções:
B5: Preencher a pesquisa com palavras separadas por espaço. Acentuação das palavras afeta a pesquisa. Ordem das palavras ou maiúscula/minúscula não afeta a pesquisa. O campo "Pesquisar em" deve ser preenchido com "insumos" ou "composições". O campo "Contém" é obrigatório. Funciona somente em versões do Excel que tenham disponíveis as fórmulas FILTRO, CLASSIFICAR, DIVIDIRTEXTO, BYROW e LAMBDA
A7: Pesquisar em: | B7: composições
A8: Contém*: | B8: paviment execução asf
A9: Não Contém:
B10: =COUNTIF($B$12:$B$15000,"<>")&" RESULTADOS" -> 0
A11: =IF($B$7="insumos","Cód. Insumo",IF($B$7="composições","Cód. Composição","")) -> 0 | B11: Descrição | C11: Unidade
A12: {=IF($B$7="composições",_xlfn._xlws.SORT(_xlfn._xlws.FILTER('CSD'!B11:D15000,_xlfn.BYROW('CSD'!C11:C15000,_xlfn.LAMBDA(_xlpm.linha,AND(AND(ISNUMBER(SEARCH(_xlfn.TEXTSPLIT(($B$8)," "),_xlpm.linha))),NOT(OR(ISNUMBER(SEARCH(_xlfn.TEXTSPLIT(($B$9)," "),_xlpm.linha)))))))),2,1),IF($B$7="insumos",_xlfn._xlws.SORT(_xlfn._xlws.FILTER('ISD'!B11:D15000,_xlfn.BYROW('ISD'!C11:C15000,_xlfn.LAMBDA(_xlpm.linha,AND(AND(ISNUMBER(SEARCH(_xlfn.TEXTSPLIT(($B$8)," "),_xlpm.linha))),NOT(OR(ISNUMBER(SEARCH(_xlfn.TEXTSPLIT(($B$9)," "),_xlpm.linha)))))))),2,1),""))} -> 0

Sheet ISD
A1: SINAPI - Sistema Nacional de Pesquisa de Custos e Índices da Construção Civil
A2: RELATÓRIO DE PREÇOS DE INSUMOS - ENGARGOS SOCIAIS SEM DESONERAÇÃO
A3: Mês de Referência: | B3: 01/2026 | E3: Encargos sociais sobre a mão de obra:
A4: Data de emissão: | B4: 23/03/2026 | E4: (SEM DESONERAÇÃO) | F4: AC | G4: AL | H4: AM | I4: AP | J4: BA | K4: CE | L4: DF | M4: ES | N4: GO | O4: MA | P4: MG | Q4: MS | R4: MT | S4: PA | T4: PB | U4: PE | V4: PI | W4: PR | X4: RJ | Y4: RN | Z4: RO | AA4: RR | AB4: RS | AC4: SC | AD4: SE | AE4: SP | AF4: TO
E5: Localidade | F5: RIO BRANCO | G5: MACEIO | H5: MANAUS | I5: MACAPA | J5: SALVADOR | K5: FORTALEZA | L5: BRASILIA | M5: VITORIA | N5: GOIANIA | O5: SAO LUIS | P5: BELO HORIZONTE | Q5: CAMPO GRANDE | R5: CUIABA | S5: BELEM | T5: JOAO PESSOA | U5: RECIFE | V5: TERESINA | W5: CURITIBA | X5: RIO DE JANEIRO | Y5: NATAL | Z5: PORTO VELHO | AA5: BOA VISTA | AB5: PORTO ALEGRE | AC5: FLORIANOPOLIS | AD5: ARACAJU | AE5: SAO PAULO | AF5: PALMAS
A6: Origem de preço: | B6: C = COLETADO | C6: CR = COEFICIENTE DE REPRESENTATIVIDADE | E6: Horista | F6: 1.1261 | G6: 1.1612 | H6: 1.1416 | I6: 1.1518 | J6: 1.1773 | K6: 1.1561 | L6: 1.1008 | M6: 1.183 | N6: 1.0772 | O6: 1.1411 | P6: 1.1623 | Q6: 1.1571 | R6: 1.0533 | S6: 1.1942 | T6: 1.1819 | U6: 1.1463 | V6: 1.1378 | W6: 1.1628 | X6: 1.1249 | Y6: 1.1683 | Z6: 1.1571 | AA6: 1.1479 | AB6: 1.1195 | AC6: 1.1447 | AD6: 1.1151 | AE6: 1.1501 | AF6: 1.1523
A7: Preço em branco para determinado estado significa que não houve coleta mínima de preços no mês de referência | E7: Mensalista | F7: 0.6903 | G7: 0.7125 | H7: 0.708 | I7: 0.7006 | J7: 0.7285 | K7: 0.7246 | L7: 0.6994 | M7: 0.7385 | N7: 0.6928 | O7: 0.713 | P7: 0.7383 | Q7: 0.7157 | R7: 0.6783 | S7: 0.727 | T7: 0.7266 | U7: 0.7067 | V7: 0.7159 | W7: 0.7242 | X7: 0.6966 | Y7: 0.7229 | Z7: 0.7065 | AA7: 0.7035 | AB7: 0.6929 | AC7: 0.7103 | AD7: 0.6972 | AE7: 0.7118 | AF7: 0.7198
A9: Acessar Fichas de Especificação Técnico dos Insumos | E9: Preços Medianos (R$):
A10: Classificação | B10: Código do Insumo | C10: Descrição do Insumo | D10: Unidade | E10: Origem de Preço | F10: AC | G10: AL | H10: AM | I10: AP | J10: BA | K10: CE | L10: DF | M10: ES | N10: GO | O10: MA | P10: MG | Q10: MS | R10: MT | S10: PA | T10: PB | U10: PE | V10: PI | W10: PR | X10: RJ | Y10: RN | Z10: RO | AA10: RR | AB10: RS | AC10: SC | AD10: SE | AE10: SP | AF10: TO
A57: MATERIAL | B57: 1 | C57: ACETILENO - RECARGA DE GAS PARA CILINDRO (NAO INCLUI TROCA/MANUTENCAO DO CILINDRO) | D57: KG | E57: C | G57: 133.33 | J57: 157.78 | K57: 101.13 | M57: 105 | N57: 97.77 | P57: 80 | Q57: 100 | R57: 119.64 | W57: 140 | AB57: 110.5 | AE57: 110
A184: ENCARGOS COMPLEMENTARES | B184: 37370 | C184: ALIMENTACAO - HORISTA (COLETADO CAIXA - ENCARGOS COMPLEMENTARES) | D184: H | E184: C | F184: 3.4 | G184: 2.68 | H184: 5.58 | I184: 0.66 | J184: 5 | K184: 4.15 | L184: 4.29 | M184: 7.63 | N184: 3.61 | O184: 2.2 | P184: 2.41 | Q184: 1.73 | R184: 2.9 | S184: 5.15 | T184: 1.82 | U184: 3.06 | V184: 2.49 | W184: 5.96 | X184: 4.78 | Y184: 4.93 | Z184: 3.76 | AA184: 3.52 | AB184: 1.82 | AC184: 0.01 | AD184: 2.96 | AE184: 4.48 | AF184: 2.39
A317: MATERIAL | B317: 34353 | C317: ARGAMASSA COLANTE AC II | D317: KG | E317: CR | F317: 2.42 | G317: 1.86 | H317: 2.38 | I317: 2.1 | J317: 1.58 | K317: 2.17 | L317: 1.19 | M317: 1.35 | N317: 1.49 | O317: 1.91 | P317: 1.26 | Q317: 1.76 | R317: 2.32 | S317: 1.67 | T317: 1.49 | U317: 1.86 | V317: 1.35 | W317: 1.41 | X317: 1.3 | Y317: 1.82 | Z317: 1.99 | AA317: 3.09 | AB317: 1.49 | AC317: 1.3 | AD317: 1.73 | AE317: 1.49 | AF317: 1.39
A320: MATERIAL | B320: 371 | C320: ARGAMASSA INDUSTRIALIZADA MULTIUSO, PARA REVESTIMENTO INTERNO E EXTERNO E ASSENTAMENTO DE BLOCOS DIVERSOS | D320: KG | E320: CR | F320: 1.42 | G320: 1.09 | H320: 1.39 | I320: 1.23 | J320: 0.92 | K320: 1.27 | L320: 0.69 | M320: 0.79 | N320: 0.87 | O320: 1.12 | P320: 0.74 | Q320: 1.03 | R320: 1.36 | S320: 0.98 | T320: 0.87 | U320: 1.09 | V320: 0.79 | W320: 0.83 | X320: 0.76 | Y320: 1.07 | Z320: 1.16 | AA320: 1.81 | AB320: 0.87 | AC320: 0.76 | AD320: 1.01 | AE320: 0.87 | AF320: 0.81
A1932: ENCARGOS COMPLEMENTARES | B1932: 43489 | C1932: EPI - FAMILIA PEDREIRO - HORISTA (ENCARGOS COMPLEMENTARES - COLETADO CAIXA) | D1932: H | E1932: C | F1932: 1.46 | G1932: 1.45 | H1932: 1.46 | I1932: 1.74 | J1932: 1.41 | K1932: 1.5 | L1932: 1.26 | M1932: 1.28 | N1932: 1.13 | O1932: 1.32 | P1932: 1.43 | Q1932: 1.43 | R1932: 1.72 | S1932: 1.76 | T1932: 1.68 | U1932: 1.47 | V1932: 1.81 | W1932: 1.64 | X1932: 1.71 | Y1932: 1.25 | Z1932: 1.56 | AA1932: 1.85 | AB1932: 1.62 | AC1932: 1.55 | AD1932: 1.28 | AE1932: 1.47 | AF1932: 1.6
A1936: ENCARGOS COMPLEMENTARES | B1936: 43491 | C1936: EPI - FAMILIA SERVENTE - HORISTA (ENCARGOS COMPLEMENTARES - COLETADO CAIXA) | D1936: H | E1936: C | F1936: 1.53 | G1936: 1.52 | H1936: 1.53 | I1936: 1.82 | J1936: 1.48 | K1936: 1.57 | L1936: 1.32 | M1936: 1.34 | N1936: 1.18 | O1936: 1.38 | P1936: 1.5 | Q1936: 1.5 | R1936: 1.8 | S1936: 1.85 | T1936: 1.75 | U1936: 1.54 | V1936: 1.89 | W1936: 1.71 | X1936: 1.79 | Y1936: 1.31 | Z1936: 1.63 | AA1936: 1.94 | AB1936: 1.7 | AC1936: 1.62 | AD1936: 1.34 | AE1936: 1.54 | AF1936: 1.67
A1993: ENCARGOS COMPLEMENTARES | B1993: 37372 | C1993: EXAMES - HORISTA (COLETADO CAIXA - ENCARGOS COMPLEMENTARES) | D1993: H | E1993: C | F1993: 1.32 | G1993: 1.4 | H1993: 1.29 | I1993: 1.3 | J1993: 1.49 | K1993: 1.48 | L1993: 1.31 | M1993: 1.62 | N1993: 1.58 | O1993: 1.36 | P1993: 1.57 | Q1993: 1.67 | R1993: 1.62 | S1993: 1.51 | T1993: 1.56 | U1993: 1.24 | V1993: 1.42 | W1993: 1.58 | X1993: 1.25 | Y1993: 1.55 | Z1993: 1.52 | AA1993: 1.36 | AB1993: 1.36 | AC1993: 1.65 | AD1993: 1.39 | AE1993: 1.43 | AF1993: 1.59
A2052: ENCARGOS COMPLEMENTARES | B2052: 43465 | C2052: FERRAMENTAS - FAMILIA PEDREIRO - HORISTA (ENCARGOS COMPLEMENTARES - COLETADO CAIXA) | D2052: H | E2052: C | F2052: 0.7 | G2052: 0.6 | H2052: 0.57 | I2052: 0.65 | J2052: 0.59 | K2052: 0.6 | L2052: 0.71 | M2052: 0.68 | N2052: 0.62 | O2052: 0.73 | P2052: 0.8 | Q2052: 0.81 | R2052: 0.74 | S2052: 0.65 | T2052: 0.63 | U2052: 0.6 | V2052: 0.9 | W2052: 0.6 | X2052: 0.64 | Y2052: 0.66 | Z2052: 0.74 | AA2052: 0.63 | AB2052: 0.71 | AC2052: 0.72 | AD2052: 0.61 | AE2052: 0.73 | AF2052: 0.83
A2056: ENCARGOS COMPLEMENTARES | B2056: 43467 | C2056: FERRAMENTAS - FAMILIA SERVENTE - HORISTA (ENCARGOS COMPLEMENTARES - COLETADO CAIXA) | D2056: H | E2056: C | F2056: 0.6 | G2056: 0.48 | H2056: 0.57 | I2056: 0.61 | J2056: 0.47 | K2056: 0.57 | L2056: 0.58 | M2056: 0.57 | N2056: 0.56 | O2056: 0.58 | P2056: 0.67 | Q2056: 0.49 | R2056: 0.6 | S2056: 0.56 | T2056: 0.58 | U2056: 0.5 | V2056: 1 | W2056: 0.42 | X2056: 0.56 | Y2056: 0.62 | Z2056: 0.63 | AA2056: 0.64 | AB2056: 0.57 | AC2056: 0.6 | AD2056: 0.49 | AE2056: 0.57 | AF2056: 0.69
A3133: MATERIAL | B3133: 2 | C3133: OXIGENIO - RECARGA DE GAS PARA CILINDRO (NAO INCLUI TROCA/MANUTENCAO DO CILINDRO) | D3133: M3 | E3133: CR | G3133: 29.22 | J3133: 34.58 | K3133: 22.16 | M3133: 23.01 | N3133: 21.42 | P3133: 17.53 | Q3133: 21.91 | R3133: 26.22 | W3133: 30.68 | AB3133: 24.21 | AE3133: 24.1
A3258: MAO DE OBRA | B3258: 4750 | C3258: PEDREIRO (HORISTA) | D3258: H | E3258: C | F3258: 23.38 | G3258: 20.27 | H3258: 21.67 | I3258: 21.32 | J3258: 24.29 | K3258: 21.86 | L3258: 23.15 | M3258: 22.09 | N3258: 24.01 | O3258: 21.28 | P3258: 25.86 | Q3258: 21.26 | R3258: 22.29 | S3258: 21.92 | T3258: 21.6 | U3258: 22.53 | V3258: 21.8 | W3258: 28.95 | X3258: 30.32 | Y3258: 19.83 | Z3258: 22.99 | AA3258: 25.53 | AB3258: 22.76 | AC3258: 30.56 | AD3258: 20.45 | AE3258: 26.03 | AF3258: 21.3
A3358: MATERIAL | B3358: 36178 | C3358: PISO TATIL / PODOTATIL, LADRILHO HIDRAULICO/CONCRETO, *40 X 40* CM, E= 2,5* CM, PADRAO TATIL ALERTA OU DIRECIONAL, COR NATURAL | D3358: UN | E3358: CR | F3358: 28.02 | G3358: 14.34 | H3358: 22.95 | I3358: 20.85 | J3358: 15.44 | K3358: 14.34 | L3358: 19.44 | M3358: 16.55 | N3358: 17.83 | O3358: 15.44 | P3358: 15.54 | Q3358: 17.29 | R3358: 22.03 | S3358: 15.88 | T3358: 12.8 | U3358: 13.46 | V3358: 13.57 | W3358: 12.62 | X3358: 15.88 | Y3358: 15.56 | Z3358: 21.4 | AA3358: 28.68 | AB3358: 14.17 | AC3358: 12.81 | AD3358: 16.55 | AE3358: 18.3 | AF3358: 20.85
A3730: MATERIAL | B3730: 34357 | C3730: REJUNTE CIMENTICIO, QUALQUER COR | D3730: KG | E3730: CR | F3730: 7.63 | G3730: 5.87 | H3730: 7.51 | I3730: 6.63 | J3730: 4.99 | K3730: 6.87 | L3730: 3.75 | M3730: 4.28 | N3730: 4.69 | O3730: 6.04 | P3730: 3.99 | Q3730: 5.57 | R3730: 7.34 | S3730: 5.28 | T3730: 4.69 | U3730: 5.87 | V3730: 4.28 | W3730: 4.46 | X3730: 4.11 | Y3730: 5.75 | Z3730: 6.28 | AA3730: 9.74 | AB3730: 4.69 | AC3730: 4.11 | AD3730: 5.46 | AE3730: 4.69 | AF3730: 4.4
A3804: ENCARGOS COMPLEMENTARES | B3804: 37373 | C3804: SEGURO - HORISTA (COLETADO CAIXA - ENCARGOS COMPLEMENTARES) | D3804: H | E3804: C | F3804: 0.11 | G3804: 0.11 | H3804: 0.11 | I3804: 0.01 | J3804: 0.11 | K3804: 0.11 | L3804: 0.11 | M3804: 0.11 | N3804: 0.1 | O3804: 0.11 | P3804: 0.11 | Q3804: 0.11 | R3804: 0.1 | S3804: 0.11 | T3804: 0.01 | U3804: 0.11 | V3804: 0.11 | W3804: 0.06 | X3804: 0.11 | Y3804: 0.11 | Z3804: 0.01 | AA3804: 0.01 | AB3804: 0.11 | AC3804: 0.11 | AD3804: 0.11 | AE3804: 0.11 | AF3804: 0.11
A3825: MAO DE OBRA | B3825: 6110 | C3825: SERRALHEIRO (HORISTA) | D3825: H | E3825: CR | F3825: 23.38 | G3825: 22.28 | H3825: 26.94 | I3825: 21.32 | J3825: 24.29 | K3825: 21.86 | L3825: 23.15 | M3825: 25.99 | N3825: 24.01 | O3825: 21.28 | P3825: 25.86 | Q3825: 21.76 | R3825: 22.29 | S3825: 21.92 | T3825: 21.6 | U3825: 22.53 | V3825: 21.8 | W3825: 28.95 | X3825: 30.32 | Y3825: 19.83 | Z3825: 22.99 | AA3825: 25.53 | AB3825: 22.76 | AC3825: 30.56 | AD3825: 20.45 | AE3825: 26.72 | AF3825: 21.3
A3828: MAO DE OBRA | B3828: 6111 | C3828: SERVENTE DE OBRAS (HORISTA) | D3828: H | E3828: C | F3828: 16.28 | G3828: 15.92 | H3828: 16.01 | I3828: 15.85 | J3828: 16.04 | K3828: 15.89 | L3828: 15.65 | M3828: 16.69 | N3828: 15.3 | O3828: 15.77 | P3828: 17.36 | Q3828: 15.89 | R3828: 16.61 | S3828: 16.17 | T3828: 16.45 | U3828: 16.95 | V3828: 15.94 | W3828: 20.46 | X3828: 21.46 | Y3828: 15.98 | Z3828: 18.72 | AA3828: 15.95 | AB3828: 17.88 | AC3828: 21.06 | AD3828: 15.58 | AE3828: 21.5 | AF3828: 15.86
A4369: ENCARGOS COMPLEMENTARES | B4369: 37371 | C4369: TRANSPORTE - HORISTA (COLETADO CAIXA - ENCARGOS COMPLEMENTARES) | D4369: H | E4369: C | F4369: 0.27 | G4369: 0.48 | H4369: 1.67 | I4369: 0.38 | J4369: 0.88 | K4369: 1.09 | L4369: 1.52 | M4369: 0.66 | N4369: 0.55 | O4369: 0.51 | P4369: 0.9 | Q4369: 1.04 | R4369: 0.7 | S4369: 1.19 | T4369: 0.78 | U4369: 0.5 | V4369: 0.48 | W4369: 0.79 | X4369: 1.72 | Y4369: 0.73 | Z4369: 0.08 | AA4369: 0.85 | AB4369: 1.02 | AC4369: 0.98 | AD4369: 0.63 | AE4369: 1.07 | AF4369: 0.7

Sheet ICD
A1: SINAPI - Sistema Nacional de Pesquisa de Custos e Índices da Construção Civil
A2: RELATÓRIO DE PREÇOS DE INSUMOS - ENCARGOS SOCIAIS COM DESONERAÇÃO
A3: Mês de Referência: | B3: 01/2026 | E3: Encargos sociais sobre a mão de obra:
A4: Data de emissão: | B4: 23/03/2026 | E4: (COM DESONERAÇÃO) | F4: AC | G4: AL | H4: AM | I4: AP | J4: BA | K4: CE | L4: DF | M4: ES | N4: GO | O4: MA | P4: MG | Q4: MS | R4: MT | S4: PA | T4: PB | U4: PE | V4: PI | W4: PR | X4: RJ | Y4: RN | Z4: RO | AA4: RR | AB4: RS | AC4: SC | AD4: SE | AE4: SP | AF4: TO
E5: Localidade | F5: RIO BRANCO | G5: MACEIO | H5: MANAUS | I5: MACAPA | J5: SALVADOR | K5: FORTALEZA | L5: BRASILIA | M5: VITORIA | N5: GOIANIA | O5: SAO LUIS | P5: BELO HORIZONTE | Q5: CAMPO GRANDE | R5: CUIABA | S5: BELEM | T5: JOAO PESSOA | U5: RECIFE | V5: TERESINA | W5: CURITIBA | X5: RIO DE JANEIRO | Y5: NATAL | Z5: PORTO VELHO | AA5: BOA VISTA | AB5: PORTO ALEGRE | AC5: FLORIANOPOLIS | AD5: ARACAJU | AE5: SAO PAULO | AF5: PALMAS
A6: Origem de preço: | B6: C = COLETADO | C6: CR = COEFICIENTE DE REPRESENTATIVIDADE | E6: Horista | F6: 0.9688 | G6: 1.0013 | H6: 0.9835 | I6: 0.9923 | J6: 1.017 | K6: 0.9971 | L6: 0.9463 | M6: 1.0222 | N6: 0.9322 | O6: 0.9831 | P6: 1.0033 | Q6: 0.9956 | R6: 0.9089 | S6: 1.0326 | T6: 1.0206 | U6: 0.9883 | V6: 0.9796 | W6: 1.0025 | X6: 0.9688 | Y6: 1.0077 | Z6: 0.9961 | AA6: 0.9885 | AB6: 0.9612 | AC6: 0.9838 | AD6: 0.9588 | AE6: 0.9909 | AF6: 0.9923
A7: Preço em branco para determinado estado significa que não houve coleta mínima de preços no mês de referência | E7: Mensalista | F7: 0.5653 | G7: 0.5859 | H7: 0.582 | I7: 0.5746 | J7: 0.6013 | K7: 0.5974 | L7: 0.5745 | M7: 0.6106 | N7: 0.5747 | O7: 0.5866 | P7: 0.6106 | Q7: 0.5874 | R7: 0.5603 | S7: 0.5998 | T7: 0.5991 | U7: 0.581 | V7: 0.5891 | W7: 0.5965 | X7: 0.572 | Y7: 0.5955 | Z7: 0.5792 | AA7: 0.5772 | AB7: 0.5667 | AC7: 0.5822 | AD7: 0.5718 | AE7: 0.5851 | AF7: 0.592
A9: Acessar Fichas de Especificação Técnico dos Insumos | E9: Preços Medianos (R$):
A10: Classificação | B10: Código do Insumo | C10: Descrição do Insumo | D10: Unidade | E10: Origem de Preço | F10: AC | G10: AL | H10: AM | I10: AP | J10: BA | K10: CE | L10: DF | M10: ES | N10: GO | O10: MA | P10: MG | Q10: MS | R10: MT | S10: PA | T10: PB | U10: PE | V10: PI | W10: PR | X10: RJ | Y10: RN | Z10: RO | AA10: RR | AB10: RS | AC10: SC | AD10: SE | AE10: SP | AF10: TO
A57: MATERIAL | B57: 1 | C57: ACETILENO - RECARGA DE GAS PARA CILINDRO (NAO INCLUI TROCA/MANUTENCAO DO CILINDRO) | D57: KG | E57: C | G57: 133.33 | J57: 157.78 | K57: 101.13 | M57: 105 | N57: 97.77 | P57: 80 | Q57: 100 | R57: 119.64 | W57: 140 | AB57: 110.5 | AE57: 110
A184: ENCARGOS COMPLEMENTARES | B184: 37370 | C184: ALIMENTACAO - HORISTA (COLETADO CAIXA - ENCARGOS COMPLEMENTARES) | D184: H | E184: C | F184: 3.4 | G184: 2.68 | H184: 5.58 | I184: 0.66 | J184: 5 | K184: 4.15 | L184: 4.29 | M184: 7.63 | N184: 3.61 | O184: 2.2 | P184: 2.41 | Q184: 1.73 | R184: 2.9 | S184: 5.15 | T184: 1.82 | U184: 3.06 | V184: 2.49 | W184: 5.96 | X184: 4.78 | Y184: 4.93 | Z184: 3.76 | AA184: 3.52 | AB184: 1.82 | AC184: 0.01 | AD184: 2.96 | AE184: 4.48 | AF184: 2.39
A317: MATERIAL | B317: 34353 | C317: ARGAMASSA COLANTE AC II | D317: KG | E317: CR | F317: 2.42 | G317: 1.86 | H317: 2.38 | I317: 2.1 | J317: 1.58 | K317: 2.17 | L317: 1.19 | M317: 1.35 | N317: 1.49 | O317: 1.91 | P317: 1.26 | Q317: 1.76 | R317: 2.32 | S317: 1.67 | T317: 1.49 | U317: 1.86 | V317: 1.35 | W317: 1.41 | X317: 1.3 | Y317: 1.82 | Z317: 1.99 | AA317: 3.09 | AB317: 1.49 | AC317: 1.3 | AD317: 1.73 | AE317: 1.49 | AF317: 1.39
A320: MATERIAL | B320: 371 | C320: ARGAMASSA INDUSTRIALIZADA MULTIUSO, PARA REVESTIMENTO INTERNO E EXTERNO E ASSENTAMENTO DE BLOCOS DIVERSOS | D320: KG | E320: CR | F320: 1.42 | G320: 1.09 | H320: 1.39 | I320: 1.23 | J320: 0.92 | K320: 1.27 | L320: 0.69 | M320: 0.79 | N320: 0.87 | O320: 1.12 | P320: 0.74 | Q320: 1.03 | R320: 1.36 | S320: 0.98 | T320: 0.87 | U320: 1.09 | V320: 0.79 | W320: 0.83 | X320: 0.76 | Y320: 1.07 | Z320: 1.16 | AA320: 1.81 | AB320: 0.87 | AC320: 0.76 | AD320: 1.01 | AE320: 0.87 | AF320: 0.81
A1932: ENCARGOS COMPLEMENTARES | B1932: 43489 | C1932: EPI - FAMILIA PEDREIRO - HORISTA (ENCARGOS COMPLEMENTARES - COLETADO CAIXA) | D1932: H | E1932: C | F1932: 1.46 | G1932: 1.45 | H1932: 1.46 | I1932: 1.74 | J1932: 1.41 | K1932: 1.5 | L1932: 1.26 | M1932: 1.28 | N1932: 1.13 | O1932: 1.32 | P1932: 1.43 | Q1932: 1.43 | R1932: 1.72 | S1932: 1.76 | T1932: 1.68 | U1932: 1.47 | V1932: 1.81 | W1932: 1.64 | X1932: 1.71 | Y1932: 1.25 | Z1932: 1.56 | AA1932: 1.85 | AB1932: 1.62 | AC1932: 1.55 | AD1932: 1.28 | AE1932: 1.47 | AF1932: 1.6
A1936: ENCARGOS COMPLEMENTARES | B1936: 43491 | C1936: EPI - FAMILIA SERVENTE - HORISTA (ENCARGOS COMPLEMENTARES - COLETADO CAIXA) | D1936: H | E1936: C | F1936: 1.53 | G1936: 1.52 | H1936: 1.53 | I1936: 1.82 | J1936: 1.48 | K1936: 1.57 | L1936: 1.32 | M1936: 1.34 | N1936: 1.18 | O1936: 1.38 | P1936: 1.5 | Q1936: 1.5 | R1936: 1.8 | S1936: 1.85 | T1936: 1.75 | U1936: 1.54 | V1936: 1.89 | W1936: 1.71 | X1936: 1.79 | Y1936: 1.31 | Z1936: 1.63 | AA1936: 1.94 | AB1936: 1.7 | AC1936: 1.62 | AD1936: 1.34 | AE1936: 1.54 | AF1936: 1.67
A1993: ENCARGOS COMPLEMENTARES | B1993: 37372 | C1993: EXAMES - HORISTA (COLETADO CAIXA - ENCARGOS COMPLEMENTARES) | D1993: H | E1993: C | F1993: 1.32 | G1993: 1.4 | H1993: 1.29 | I1993: 1.3 | J1993: 1.49 | K1993: 1.48 | L1993: 1.31 | M1993: 1.62 | N1993: 1.58 | O1993: 1.36 | P1993: 1.57 | Q1993: 1.67 | R1993: 1.62 | S1993: 1.51 | T1993: 1.56 | U1993: 1.24 | V1993: 1.42 | W1993: 1.58 | X1993: 1.25 | Y1993: 1.55 | Z1993: 1.52 | AA1993: 1.36 | AB1993: 1.36 | AC1993: 1.65 | AD1993: 1.39 | AE1993: 1.43 | AF1993: 1.59
A2052: ENCARGOS COMPLEMENTARES | B2052: 43465 | C2052: FERRAMENTAS - FAMILIA PEDREIRO - HORISTA (ENCARGOS COMPLEMENTARES - COLETADO CAIXA) | D2052: H | E2052: C | F2052: 0.7 | G2052: 0.6 | H2052: 0.57 | I2052: 0.65 | J2052: 0.59 | K2052: 0.6 | L2052: 0.71 | M2052: 0.68 | N2052: 0.62 | O2052: 0.73 | P2052: 0.8 | Q2052: 0.81 | R2052: 0.74 | S2052: 0.65 | T2052: 0.63 | U2052: 0.6 | V2052: 0.9 | W2052: 0.6 | X2052: 0.64 | Y2052: 0.66 | Z2052: 0.74 | AA2052: 0.63 | AB2052: 0.71 | AC2052: 0.72 | AD2052: 0.61 | AE2052: 0.73 | AF2052: 0.83
A2056: ENCARGOS COMPLEMENTARES | B2056: 43467 | C2056: FERRAMENTAS - FAMILIA SERVENTE - HORISTA (ENCARGOS COMPLEMENTARES - COLETADO CAIXA) | D2056: H | E2056: C | F2056: 0.6 | G2056: 0.48 | H2056: 0.57 | I2056: 0.61 | J2056: 0.47 | K2056: 0.57 | L2056: 0.58 | M2056: 0.57 | N2056: 0.56 | O2056: 0.58 | P2056: 0.67 | Q2056: 0.49 | R2056: 0.6 | S2056: 0.56 | T2056: 0.58 | U2056: 0.5 | V2056: 1 | W2056: 0.42 | X2056: 0.56 | Y2056: 0.62 | Z2056: 0.63 | AA2056: 0.64 | AB2056: 0.57 | AC2056: 0.6 | AD2056: 0.49 | AE2056: 0.57 | AF2056: 0.69
A3133: MATERIAL | B3133: 2 | C3133: OXIGENIO - RECARGA DE GAS PARA CILINDRO (NAO INCLUI TROCA/MANUTENCAO DO CILINDRO) | D3133: M3 | E3133: CR | G3133: 29.22 | J3133: 34.58 | K3133: 22.16 | M3133: 23.01 | N3133: 21.42 | P3133: 17.53 | Q3133: 21.91 | R3133: 26.22 | W3133: 30.68 | AB3133: 24.21 | AE3133: 24.1
A3258: MAO DE OBRA | B3258: 4750 | C3258: PEDREIRO (HORISTA) | D3258: H | E3258: C | F3258: 21.65 | G3258: 18.77 | H3258: 20.07 | I3258: 19.74 | J3258: 22.5 | K3258: 20.25 | L3258: 21.44 | M3258: 20.46 | N3258: 22.33 | O3258: 19.71 | P3258: 23.95 | Q3258: 19.67 | R3258: 20.73 | S3258: 20.3 | T3258: 20 | U3258: 20.87 | V3258: 20.19 | W3258: 26.81 | X3258: 28.09 | Y3258: 18.37 | Z3258: 21.27 | AA3258: 23.64 | AB3258: 21.06 | AC3258: 28.26 | AD3258: 18.94 | AE3258: 24.1 | AF3258: 19.72
A3358: MATERIAL | B3358: 36178 | C3358: PISO TATIL / PODOTATIL, LADRILHO HIDRAULICO/CONCRETO, *40 X 40* CM, E= 2,5* CM, PADRAO TATIL ALERTA OU DIRECIONAL, COR NATURAL | D3358: UN | E3358: CR | F3358: 28.02 | G3358: 14.34 | H3358: 22.95 | I3358: 20.85 | J3358: 15.44 | K3358: 14.34 | L3358: 19.44 | M3358: 16.55 | N3358: 17.83 | O3358: 15.44 | P3358: 15.54 | Q3358: 17.29 | R3358: 22.03 | S3358: 15.88 | T3358: 12.8 | U3358: 13.46 | V3358: 13.57 | W3358: 12.62 | X3358: 15.88 | Y3358: 15.56 | Z3358: 21.4 | AA3358: 28.68 | AB3358: 14.17 | AC3358: 12.81 | AD3358: 16.55 | AE3358: 18.3 | AF3358: 20.85
A3730: MATERIAL | B3730: 34357 | C3730: REJUNTE CIMENTICIO, QUALQUER COR | D3730: KG | E3730: CR | F3730: 7.63 | G3730: 5.87 | H3730: 7.51 | I3730: 6.63 | J3730: 4.99 | K3730: 6.87 | L3730: 3.75 | M3730: 4.28 | N3730: 4.69 | O3730: 6.04 | P3730: 3.99 | Q3730: 5.57 | R3730: 7.34 | S3730: 5.28 | T3730: 4.69 | U3730: 5.87 | V3730: 4.28 | W3730: 4.46 | X3730: 4.11 | Y3730: 5.75 | Z3730: 6.28 | AA3730: 9.74 | AB3730: 4.69 | AC3730: 4.11 | AD3730: 5.46 | AE3730: 4.69 | AF3730: 4.4
A3804: ENCARGOS COMPLEMENTARES | B3804: 37373 | C3804: SEGURO - HORISTA (COLETADO CAIXA - ENCARGOS COMPLEMENTARES) | D3804: H | E3804: C | F3804: 0.11 | G3804: 0.11 | H3804: 0.11 | I3804: 0.01 | J3804: 0.11 | K3804: 0.11 | L3804: 0.11 | M3804: 0.11 | N3804: 0.1 | O3804: 0.11 | P3804: 0.11 | Q3804: 0.11 | R3804: 0.1 | S3804: 0.11 | T3804: 0.01 | U3804: 0.11 | V3804: 0.11 | W3804: 0.06 | X3804: 0.11 | Y3804: 0.11 | Z3804: 0.01 | AA3804: 0.01 | AB3804: 0.11 | AC3804: 0.11 | AD3804: 0.11 | AE3804: 0.11 | AF3804: 0.11
A3825: MAO DE OBRA | B3825: 6110 | C3825: SERRALHEIRO (HORISTA) | D3825: H | E3825: CR | F3825: 21.65 | G3825: 20.63 | H3825: 24.95 | I3825: 19.74 | J3825: 22.5 | K3825: 20.25 | L3825: 21.44 | M3825: 24.08 | N3825: 22.33 | O3825: 19.71 | P3825: 23.95 | Q3825: 20.13 | R3825: 20.73 | S3825: 20.3 | T3825: 20 | U3825: 20.87 | V3825: 20.19 | W3825: 26.81 | X3825: 28.09 | Y3825: 18.37 | Z3825: 21.27 | AA3825: 23.64 | AB3825: 21.06 | AC3825: 28.26 | AD3825: 18.94 | AE3825: 24.74 | AF3825: 19.72
A3828: MAO DE OBRA | B3828: 6111 | C3828: SERVENTE DE OBRAS (HORISTA) | D3828: H | E3828: C | F3828: 15.08 | G3828: 14.74 | H3828: 14.83 | I3828: 14.68 | J3828: 14.86 | K3828: 14.71 | L3828: 14.49 | M3828: 15.46 | N3828: 14.24 | O3828: 14.61 | P3828: 16.08 | Q3828: 14.7 | R3828: 15.44 | S3828: 14.98 | T3828: 15.23 | U3828: 15.7 | V3828: 14.76 | W3828: 18.94 | X3828: 19.88 | Y3828: 14.79 | Z3828: 17.32 | AA3828: 14.77 | AB3828: 16.55 | AC3828: 19.48 | AD3828: 14.43 | AE3828: 19.9 | AF3828: 14.68
A4369: ENCARGOS COMPLEMENTARES | B4369: 37371 | C4369: TRANSPORTE - HORISTA (COLETADO CAIXA - ENCARGOS COMPLEMENTARES) | D4369: H | E4369: C | F4369: 0.27 | G4369: 0.48 | H4369: 1.67 | I4369: 0.38 | J4369: 0.88 | K4369: 1.09 | L4369: 1.52 | M4369: 0.66 | N4369: 0.55 | O4369: 0.51 | P4369: 0.9 | Q4369: 1.04 | R4369: 0.7 | S4369: 1.19 | T4369: 0.78 | U4369: 0.5 | V4369: 0.48 | W4369: 0.79 | X4369: 1.72 | Y4369: 0.73 | Z4369: 0.08 | AA4369: 0.85 | AB4369: 1.02 | AC4369: 0.98 | AD4369: 0.63 | AE4369: 1.07 | AF4369: 0.7

Sheet ISE
A1: SINAPI - Sistema Nacional de Pesquisa de Custos e Índices da Construção Civil
A2: RELATÓRIO DE PREÇOS DE INSUMOS - SEM ENCARGOS SOCIAIS
A3: Mês de Referência: | B3: 01/2026
A4: Data de emissão: | B4: 23/03/2026
A6: Origem de preço: | B6: C = COLETADO | C6: CR = COEFICIENTE DE REPRESENTATIVIDADE
A7: Preço em branco para determinado estado significa que não houve coleta mínima de preços no mês de referência
A9: Acessar Fichas de Especificação Técnico dos Insumos | E9: Preços Medianos (R$):
A10: Classificação | B10: Código do Insumo | C10: Descrição do Insumo | D10: Unidade | E10: Origem de Preço | F10: AC | G10: AL | H10: AM | I10: AP | J10: BA | K10: CE | L10: DF | M10: ES | N10: GO | O10: MA | P10: MG | Q10: MS | R10: MT | S10: PA | T10: PB | U10: PE | V10: PI | W10: PR | X10: RJ | Y10: RN | Z10: RO | AA10: RR | AB10: RS | AC10: SC | AD10: SE | AE10: SP | AF10: TO
A57: MATERIAL | B57: 1 | C57: ACETILENO - RECARGA DE GAS PARA CILINDRO (NAO INCLUI TROCA/MANUTENCAO DO CILINDRO) | D57: KG | E57: C | G57: 133.33 | J57: 157.78 | K57: 101.13 | M57: 105 | N57: 97.77 | P57: 80 | Q57: 100 | R57: 119.64 | W57: 140 | AB57: 110.5 | AE57: 110
A184: ENCARGOS COMPLEMENTARES | B184: 37370 | C184: ALIMENTACAO - HORISTA (COLETADO CAIXA - ENCARGOS COMPLEMENTARES) | D184: H | E184: C | F184: 3.4 | G184: 2.68 | H184: 5.58 | I184: 0.66 | J184: 5 | K184: 4.15 | L184: 4.29 | M184: 7.63 | N184: 3.61 | O184: 2.2 | P184: 2.41 | Q184: 1.73 | R184: 2.9 | S184: 5.15 | T184: 1.82 | U184: 3.06 | V184: 2.49 | W184: 5.96 | X184: 4.78 | Y184: 4.93 | Z184: 3.76 | AA184: 3.52 | AB184: 1.82 | AC184: 0.01 | AD184: 2.96 | AE184: 4.48 | AF184: 2.39
A317: MATERIAL | B317: 34353 | C317: ARGAMASSA COLANTE AC II | D317: KG | E317: CR | F317: 2.42 | G317: 1.86 | H317: 2.38 | I317: 2.1 | J317: 1.58 | K317: 2.17 | L317: 1.19 | M317: 1.35 | N317: 1.49 | O317: 1.91 | P317: 1.26 | Q317: 1.76 | R317: 2.32 | S317: 1.67 | T317: 1.49 | U317: 1.86 | V317: 1.35 | W317: 1.41 | X317: 1.3 | Y317: 1.82 | Z317: 1.99 | AA317: 3.09 | AB317: 1.49 | AC317: 1.3 | AD317: 1.73 | AE317: 1.49 | AF317: 1.39
A320: MATERIAL | B320: 371 | C320: ARGAMASSA INDUSTRIALIZADA MULTIUSO, PARA REVESTIMENTO INTERNO E EXTERNO E ASSENTAMENTO DE BLOCOS DIVERSOS | D320: KG | E320: CR | F320: 1.42 | G320: 1.09 | H320: 1.39 | I320: 1.23 | J320: 0.92 | K320: 1.27 | L320: 0.69 | M320: 0.79 | N320: 0.87 | O320: 1.12 | P320: 0.74 | Q320: 1.03 | R320: 1.36 | S320: 0.98 | T320: 0.87 | U320: 1.09 | V320: 0.79 | W320: 0.83 | X320: 0.76 | Y320: 1.07 | Z320: 1.16 | AA320: 1.81 | AB320: 0.87 | AC320: 0.76 | AD320: 1.01 | AE320: 0.87 | AF320: 0.81
A1932: ENCARGOS COMPLEMENTARES | B1932: 43489 | C1932: EPI - FAMILIA PEDREIRO - HORISTA (ENCARGOS COMPLEMENTARES - COLETADO CAIXA) | D1932: H | E1932: C | F1932: 1.46 | G1932: 1.45 | H1932: 1.46 | I1932: 1.74 | J1932: 1.41 | K1932: 1.5 | L1932: 1.26 | M1932: 1.28 | N1932: 1.13 | O1932: 1.32 | P1932: 1.43 | Q1932: 1.43 | R1932: 1.72 | S1932: 1.76 | T1932: 1.68 | U1932: 1.47 | V1932: 1.81 | W1932: 1.64 | X1932: 1.71 | Y1932: 1.25 | Z1932: 1.56 | AA1932: 1.85 | AB1932: 1.62 | AC1932: 1.55 | AD1932: 1.28 | AE1932: 1.47 | AF1932: 1.6
A1936: ENCARGOS COMPLEMENTARES | B1936: 43491 | C1936: EPI - FAMILIA SERVENTE - HORISTA (ENCARGOS COMPLEMENTARES - COLETADO CAIXA) | D1936: H | E1936: C | F1936: 1.53 | G1936: 1.52 | H1936: 1.53 | I1936: 1.82 | J1936: 1.48 | K1936: 1.57 | L1936: 1.32 | M1936: 1.34 | N1936: 1.18 | O1936: 1.38 | P1936: 1.5 | Q1936: 1.5 | R1936: 1.8 | S1936: 1.85 | T1936: 1.75 | U1936: 1.54 | V1936: 1.89 | W1936: 1.71 | X1936: 1.79 | Y1936: 1.31 | Z1936: 1.63 | AA1936: 1.94 | AB1936: 1.7 | AC1936: 1.62 | AD1936: 1.34 | AE1936: 1.54 | AF1936: 1.67
A1993: ENCARGOS COMPLEMENTARES | B1993: 37372 | C1993: EXAMES - HORISTA (COLETADO CAIXA - ENCARGOS COMPLEMENTARES) | D1993: H | E1993: C | F1993: 1.32 | G1993: 1.4 | H1993: 1.29 | I1993: 1.3 | J1993: 1.49 | K1993: 1.48 | L1993: 1.31 | M1993: 1.62 | N1993: 1.58 | O1993: 1.36 | P1993: 1.57 | Q1993: 1.67 | R1993: 1.62 | S1993: 1.51 | T1993: 1.56 | U1993: 1.24 | V1993: 1.42 | W1993: 1.58 | X1993: 1.25 | Y1993: 1.55 | Z1993: 1.52 | AA1993: 1.36 | AB1993: 1.36 | AC1993: 1.65 | AD1993: 1.39 | AE1993: 1.43 | AF1993: 1.59
A2052: ENCARGOS COMPLEMENTARES | B2052: 43465 | C2052: FERRAMENTAS - FAMILIA PEDREIRO - HORISTA (ENCARGOS COMPLEMENTARES - COLETADO CAIXA) | D2052: H | E2052: C | F2052: 0.7 | G2052: 0.6 | H2052: 0.57 | I2052: 0.65 | J2052: 0.59 | K2052: 0.6 | L2052: 0.71 | M2052: 0.68 | N2052: 0.62 | O2052: 0.73 | P2052: 0.8 | Q2052: 0.81 | R2052: 0.74 | S2052: 0.65 | T2052: 0.63 | U2052: 0.6 | V2052: 0.9 | W2052: 0.6 | X2052: 0.64 | Y2052: 0.66 | Z2052: 0.74 | AA2052: 0.63 | AB2052: 0.71 | AC2052: 0.72 | AD2052: 0.61 | AE2052: 0.73 | AF2052: 0.83
A2056: ENCARGOS COMPLEMENTARES | B2056: 43467 | C2056: FERRAMENTAS - FAMILIA SERVENTE - HORISTA (ENCARGOS COMPLEMENTARES - COLETADO CAIXA) | D2056: H | E2056: C | F2056: 0.6 | G2056: 0.48 | H2056: 0.57 | I2056: 0.61 | J2056: 0.47 | K2056: 0.57 | L2056: 0.58 | M2056: 0.57 | N2056: 0.56 | O2056: 0.58 | P2056: 0.67 | Q2056: 0.49 | R2056: 0.6 | S2056: 0.56 | T2056: 0.58 | U2056: 0.5 | V2056: 1 | W2056: 0.42 | X2056: 0.56 | Y2056: 0.62 | Z2056: 0.63 | AA2056: 0.64 | AB2056: 0.57 | AC2056: 0.6 | AD2056: 0.49 | AE2056: 0.57 | AF2056: 0.69
A3133: MATERIAL | B3133: 2 | C3133: OXIGENIO - RECARGA DE GAS PARA CILINDRO (NAO INCLUI TROCA/MANUTENCAO DO CILINDRO) | D3133: M3 | E3133: CR | G3133: 29.22 | J3133: 34.58 | K3133: 22.16 | M3133: 23.01 | N3133: 21.42 | P3133: 17.53 | Q3133: 21.91 | R3133: 26.22 | W3133: 30.68 | AB3133: 24.21 | AE3133: 24.1
A3258: MAO DE OBRA | B3258: 4750 | C3258: PEDREIRO (HORISTA) | D3258: H | E3258: C | F3258: 11 | G3258: 9.38 | H3258: 10.12 | I3258: 9.91 | J3258: 11.16 | K3258: 10.14 | L3258: 11.02 | M3258: 10.12 | N3258: 11.56 | O3258: 9.94 | P3258: 11.96 | Q3258: 9.86 | R3258: 10.86 | S3258: 9.99 | T3258: 9.9 | U3258: 10.5 | V3258: 10.2 | W3258: 13.39 | X3258: 14.27 | Y3258: 9.15 | Z3258: 10.66 | AA3258: 11.89 | AB3258: 10.74 | AC3258: 14.25 | AD3258: 9.67 | AE3258: 12.11 | AF3258: 9.9
A3358: MATERIAL | B3358: 36178 | C3358: PISO TATIL / PODOTATIL, LADRILHO HIDRAULICO/CONCRETO, *40 X 40* CM, E= 2,5* CM, PADRAO TATIL ALERTA OU DIRECIONAL, COR NATURAL | D3358: UN | E3358: CR | F3358: 28.02 | G3358: 14.34 | H3358: 22.95 | I3358: 20.85 | J3358: 15.44 | K3358: 14.34 | L3358: 19.44 | M3358: 16.55 | N3358: 17.83 | O3358: 15.44 | P3358: 15.54 | Q3358: 17.29 | R3358: 22.03 | S3358: 15.88 | T3358: 12.8 | U3358: 13.46 | V3358: 13.57 | W3358: 12.62 | X3358: 15.88 | Y3358: 15.56 | Z3358: 21.4 | AA3358: 28.68 | AB3358: 14.17 | AC3358: 12.81 | AD3358: 16.55 | AE3358: 18.3 | AF3358: 20.85
A3730: MATERIAL | B3730: 34357 | C3730: REJUNTE CIMENTICIO, QUALQUER COR | D3730: KG | E3730: CR | F3730: 7.63 | G3730: 5.87 | H3730: 7.51 | I3730: 6.63 | J3730: 4.99 | K3730: 6.87 | L3730: 3.75 | M3730: 4.28 | N3730: 4.69 | O3730: 6.04 | P3730: 3.99 | Q3730: 5.57 | R3730: 7.34 | S3730: 5.28 | T3730: 4.69 | U3730: 5.87 | V3730: 4.28 | W3730: 4.46 | X3730: 4.11 | Y3730: 5.75 | Z3730: 6.28 | AA3730: 9.74 | AB3730: 4.69 | AC3730: 4.11 | AD3730: 5.46 | AE3730: 4.69 | AF3730: 4.4
A3804: ENCARGOS COMPLEMENTARES | B3804: 37373 | C3804: SEGURO - HORISTA (COLETADO CAIXA - ENCARGOS COMPLEMENTARES) | D3804: H | E3804: C | F3804: 0.11 | G3804: 0.11 | H3804: 0.11 | I3804: 0.01 | J3804: 0.11 | K3804: 0.11 | L3804: 0.11 | M3804: 0.11 | N3804: 0.1 | O3804: 0.11 | P3804: 0.11 | Q3804: 0.11 | R3804: 0.1 | S3804: 0.11 | T3804: 0.01 | U3804: 0.11 | V3804: 0.11 | W3804: 0.06 | X3804: 0.11 | Y3804: 0.11 | Z3804: 0.01 | AA3804: 0.01 | AB3804: 0.11 | AC3804: 0.11 | AD3804: 0.11 | AE3804: 0.11 | AF3804: 0.11
A3825: MAO DE OBRA | B3825: 6110 | C3825: SERRALHEIRO (HORISTA) | D3825: H | E3825: CR | F3825: 11 | G3825: 10.31 | H3825: 12.58 | I3825: 9.91 | J3825: 11.16 | K3825: 10.14 | L3825: 11.02 | M3825: 11.91 | N3825: 11.56 | O3825: 9.94 | P3825: 11.96 | Q3825: 10.09 | R3825: 10.86 | S3825: 9.99 | T3825: 9.9 | U3825: 10.5 | V3825: 10.2 | W3825: 13.39 | X3825: 14.27 | Y3825: 9.15 | Z3825: 10.66 | AA3825: 11.89 | AB3825: 10.74 | AC3825: 14.25 | AD3825: 9.67 | AE3825: 12.43 | AF3825: 9.9
A3828: MAO DE OBRA | B3828: 6111 | C3828: SERVENTE DE OBRAS (HORISTA) | D3828: H | E3828: C | F3828: 7.66 | G3828: 7.37 | H3828: 7.48 | I3828: 7.37 | J3828: 7.37 | K3828: 7.37 | L3828: 7.45 | M3828: 7.65 | N3828: 7.37 | O3828: 7.37 | P3828: 8.03 | Q3828: 7.37 | R3828: 8.09 | S3828: 7.37 | T3828: 7.54 | U3828: 7.9 | V3828: 7.46 | W3828: 9.46 | X3828: 10.1 | Y3828: 7.37 | Z3828: 8.68 | AA3828: 7.43 | AB3828: 8.44 | AC3828: 9.82 | AD3828: 7.37 | AE3828: 10 | AF3828: 7.37
A4369: ENCARGOS COMPLEMENTARES | B4369: 37371 | C4369: TRANSPORTE - HORISTA (COLETADO CAIXA - ENCARGOS COMPLEMENTARES) | D4369: H | E4369: C | F4369: 0.27 | G4369: 0.48 | H4369: 1.67 | I4369: 0.38 | J4369: 0.88 | K4369: 1.09 | L4369: 1.52 | M4369: 0.66 | N4369: 0.55 | O4369: 0.51 | P4369: 0.9 | Q4369: 1.04 | R4369: 0.7 | S4369: 1.19 | T4369: 0.78 | U4369: 0.5 | V4369: 0.48 | W4369: 0.79 | X4369: 1.72 | Y4369: 0.73 | Z4369: 0.08 | AA4369: 0.85 | AB4369: 1.02 | AC4369: 0.98 | AD4369: 0.63 | AE4369: 1.07 | AF4369: 0.7

Sheet CSD
A1: SINAPI - Sistema Nacional de Pesquisa de Custos e Índices da Construção Civil
A2: RELATÓRIO DE CUSTOS DE COMPOSIÇÕES - ENCARGOS SOCIAIS SEM DESONERAÇÃO
A3: Mês de Referência: | B3: 01/2026 | D3: Encargos sociais sobre a mão de obra:
A4: Data de emissão: | B4: 23/03/2026 | D4: (SEM DESONERAÇÃO) | E4: AC | G4: AL | I4: AM | K4: AP | M4: BA | O4: CE | Q4: DF | S4: ES | U4: GO | W4: MA | Y4: MG | AA4: MS | AC4: MT | AE4: PA | AG4: PB | AI4: PE | AK4: PI | AM4: PR | AO4: RJ | AQ4: RN | AS4: RO | AU4: RR | AW4: RS | AY4: SC | BA4: SE | BC4: SP | BE4: TO
D5: Localidade | E5: RIO BRANCO | G5: MACEIO | I5: MANAUS | K5: MACAPA | M5: SALVADOR | O5: FORTALEZA | Q5: BRASILIA | S5: VITORIA | U5: GOIANIA | W5: SAO LUIS | Y5: BELO HORIZONTE | AA5: CAMPO GRANDE | AC5: CUIABA | AE5: BELEM | AG5: JOAO PESSOA | AI5: RECIFE | AK5: TERESINA | AM5: CURITIBA | AO5: RIO DE JANEIRO | AQ5: NATAL | AS5: PORTO VELHO | AU5: BOA VISTA | AW5: PORTO ALEGRE | AY5: FLORIANOPOLIS | BA5: ARACAJU | BC5: SAO PAULO | BE5: PALMAS
A6: Observação: | B6: %AS (porcentagem Atribuído São Paulo) corresponde a porcentagem do custo total da | D6: Horista | E6: 1.1261 | G6: 1.1612 | I6: 1.1416 | K6: 1.1518 | M6: 1.1773 | O6: 1.1561 | Q6: 1.1008 | S6: 1.183 | U6: 1.0772 | W6: 1.1411 | Y6: 1.1623 | AA6: 1.1571 | AC6: 1.0533 | AE6: 1.1942 | AG6: 1.1819 | AI6: 1.1463 | AK6: 1.1378 | AM6: 1.1628 | AO6: 1.1249 | AQ6: 1.1683 | AS6: 1.1571 | AU6: 1.1479 | AW6: 1.1195 | AY6: 1.1447 | BA6: 1.1151 | BC6: 1.1501 | BE6: 1.1523
B7: composição que foi obtida utilizando preços de insumos de São Paulo por indisponibilidade | D7: Mensalista | E7: 0.6903 | G7: 0.7125 | I7: 0.708 | K7: 0.7006 | M7: 0.7285 | O7: 0.7246 | Q7: 0.6994 | S7: 0.7385 | U7: 0.6928 | W7: 0.713 | Y7: 0.7383 | AA7: 0.7157 | AC7: 0.6783 | AE7: 0.727 | AG7: 0.7266 | AI7: 0.7067 | AK7: 0.7159 | AM7: 0.7242 | AO7: 0.6966 | AQ7: 0.7229 | AS7: 0.7065 | AU7: 0.7035 | AW7: 0.6929 | AY7: 0.7103 | BA7: 0.6972 | BC7: 0.7118 | BE7: 0.7198
B8: dos preços de insumos necessários à composição no estado em questão. Custo zerado (hífen)
B9: indica que pelo menos um dos itens da composição não tem custo/preço. | E9: AC | G9: AL | I9: AM | K9: AP | M9: BA | O9: CE | Q9: DF | S9: ES | U9: GO | W9: MA | Y9: MG | AA9: MS | AC9: MT | AE9: PA | AG9: PB | AI9: PE | AK9: PI | AM9: PR | AO9: RJ | AQ9: RN | AS9: RO | AU9: RR | AW9: RS | AY9: SC | BA9: SE | BC9: SP | BE9: TO
A10: Grupo | B10: Código da Composição | C10: Descrição | D10: Unidade | E10: Custo (R$) | F10: %AS | G10: Custo (R$) | H10: %AS | I10: Custo (R$) | J10: %AS | K10: Custo (R$) | L10: %AS | M10: Custo (R$) | N10: %AS | O10: Custo (R$) | P10: %AS | Q10: Custo (R$) | R10: %AS | S10: Custo (R$) | T10: %AS | U10: Custo (R$) | V10: %AS | W10: Custo (R$) | X10: %AS | Y10: Custo (R$) | Z10: %AS | AA10: Custo (R$) | AB10: %AS | AC10: Custo (R$) | AD10: %AS | AE10: Custo (R$) | AF10: %AS | AG10: Custo (R$) | AH10: %AS | AI10: Custo (R$) | AJ10: %AS | AK10: Custo (R$) | AL10: %AS | AM10: Custo (R$) | AN10: %AS | AO10: Custo (R$) | AP10: %AS | AQ10: Custo (R$) | AR10: %AS | AS10: Custo (R$) | AT10: %AS | AU10: Custo (R$) | AV10: %AS | AW10: Custo (R$) | AX10: %AS | AY10: Custo (R$) | AZ10: %AS | BA10: Custo (R$) | BB10: %AS | BC10: Custo (R$) | BD10: %AS | BE10: Custo (R$) | BF10: %AS
A11: Acessibilidade | B11: =HYPERLINK("#"&CELL("address",OFFSET(Analítico!$B$1,MATCH(104658,Analítico!$B:$B,0)-1,3)),104658) -> 0 | C11: PISO PODOTÁTIL DE ALERTA OU DIRECIONAL, DE CONCRETO, ASSENTADO SOBRE ARGAMASSA. AF_03/2024 | D11: M2 | E11: 253.45 | F11: 0 | G11: 156.56 | H11: 0 | I11: 225.64 | J11: 0 | K11: 197.64 | L11: 0 | M11: 169.1 | N11: 0 | O11: 164.82 | P11: 0 | Q11: 189.38 | R11: 0 | S11: 178.3 | T11: 0 | U11: 178.92 | V11: 0 | W11: 163.59 | X11: 0 | Y11: 165.14 | Z11: 0 | AA11: 175.12 | AB11: 0 | AC11: 214.63 | AD11: 0 | AE11: 173.16 | AF11: 0 | AG11: 144.37 | AH11: 0 | AI11: 154.23 | AJ11: 0 | AK11: 149.09 | AL11: 0 | AM11: 160.31 | AN11: 0 | AO11: 181.78 | AP11: 0 | AQ11: 168.74 | AR11: 0 | AS11: 210.5 | AT11: 0 | AU11: 266.95 | AV11: 0 | AW11: 156.01 | AX11: 0 | AY11: 151.63 | AZ11: 0 | BA11: 169.75 | BB11: 0 | BC11: 194.52 | BD11: 0 | BE11: 195.61 | BF11: 0
A112: Argamassas | B112: =HYPERLINK("#"&CELL("address",OFFSET(Analítico!$B$1,MATCH(87398,Analítico!$B:$B,0)-1,3)),87398) -> 0 | C112: ARGAMASSA INDUSTRIALIZADA MULTIUSO PARA REVESTIMENTOS E ASSENTAMENTO DA ALVENARIA, PREPARO MANUAL. AF_08/2019 | D112: M3 | E112: 2984.07 | F112: 0 | G112: 2348.66 | H112: 0 | I112: 2968.16 | J112: 0 | K112: 2588.58 | L112: 0 | M112: 2063.74 | N112: 0 | O112: 2717.44 | P112: 0 | Q112: 1620.23 | R112: 0 | S112: 1857.83 | T112: 0 | U112: 1936.38 | V112: 0 | W112: 2396.8 | X112: 0 | Y112: 1711.83 | Z112: 0 | AA112: 2233.24 | AB112: 0 | AC112: 2881.12 | AD112: 0 | AE112: 2190.61 | AF112: 0 | AG112: 1937.52 | AH112: 0 | AI112: 2365.4 | AJ112: 0 | AK112: 1790.97 | AL112: 0 | AM112: 1964.15 | AN112: 0 | AO112: 1840.79 | AP112: 0 | AQ112: 2344.1 | AR112: 0 | AS112: 2529.05 | AT112: 0 | AU112: 3730.61 | AV112: 0 | AW112: 1956.9 | AX112: 0 | AY112: 1769.65 | AZ112: 0 | BA112: 2196.32 | BB112: 0 | BC112: 2036.47 | BD112: 0 | BE112: 1824.75 | BF112: 0
A1105: Brises | B1105: =HYPERLINK("#"&CELL("address",OFFSET(Analítico!$B$1,MATCH(104943,Analítico!$B:$B,0)-1,3)),104943) -> 0 | C1105: FORNECIMENTO E INSTALAÇÃO DE CONJUNTO DE BRISE EM REQUADRO DE ALUMÍNIO DESLIZANTE, COM PERFIS INTERNOS TUBULARES FIXOS, COM PINTURA ELETROSTÁTICA BRANCA, ACABAMENTO, 150 CM X 265 CM. AF_03/2024 | D1105: M2 | E1105: 0 | G1105: 0 | I1105: 0 | K1105: 0 | M1105: 0 | O1105: 0 | Q1105: 0 | S1105: 0 | U1105: 0 | W1105: 0 | Y1105: 0 | AA1105: 0 | AC1105: 0 | AE1105: 0 | AG1105: 0 | AI1105: 0 | AK1105: 0 | AM1105: 0 | AO1105: 0 | AQ1105: 0 | AS1105: 0 | AU1105: 0 | AW1105: 0 | AY1105: 0 | BA1105: 0 | BC1105: 0 | BE1105: 0
A1493: Custos Horários Produtivo e Improdutivo dos Equipamentos | B1493: =HYPERLINK("#"&CELL("address",OFFSET(Analítico!$B$1,MATCH(102953,Analítico!$B:$B,0)-1,3)),102953) -> 0 | C1493: BETONEIRA CAPACIDADE NOMINAL DE 250 L, CAPACIDADE DE MISTURA DE 175 L, MOTOR ELÉTRICO MONOFÁSICO POTÊNCIA 1CV - CHI DIURNO. AF_05/2023 | D1493: CHI | E1493: 0 | G1493: 0 | I1493: 0 | K1493: 0 | M1493: 0 | O1493: 0 | Q1493: 0 | S1493: 0 | U1493: 0 | W1493: 0 | Y1493: 0 | AA1493: 0 | AC1493: 0 | AE1493: 0 | AG1493: 0 | AI1493: 0 | AK1493: 0 | AM1493: 0 | AO1493: 0 | AQ1493: 0 | AS1493: 0 | AU1493: 0 | AW1493: 0 | AY1493: 0 | BA1493: 0 | BC1493: 0 | BE1493: 0
A1981: Depreciação, Juros, Impostos e Seguros, Manutenção e Materiais na Operação dos Equipamentos | B1981: =HYPERLINK("#"&CELL("address",OFFSET(Analítico!$B$1,MATCH(92715,Analítico!$B:$B,0)-1,3)),92715) -> 0 | C1981: APARELHO PARA CORTE E SOLDA OXI-ACETILENO SOBRE RODAS, INCLUSIVE CILINDROS E MAÇARICOS - MATERIAIS NA OPERAÇÃO. AF_05/2023 | D1981: H | E1981: 114.72 | F1981: 1 | G1981: 139.08 | H1981: 0 | I1981: 114.72 | J1981: 1 | K1981: 114.72 | L1981: 1 | M1981: 164.59 | N1981: 0 | O1981: 105.48 | P1981: 0 | Q1981: 114.72 | R1981: 1 | S1981: 109.52 | T1981: 0 | U1981: 101.96 | V1981: 0 | W1981: 114.72 | X1981: 1 | Y1981: 83.44 | Z1981: 0 | AA1981: 104.3 | AB1981: 0 | AC1981: 124.8 | AD1981: 0 | AE1981: 114.72 | AF1981: 1 | AG1981: 114.72 | AH1981: 1 | AI1981: 114.72 | AJ1981: 1 | AK1981: 114.72 | AL1981: 1 | AM1981: 146.04 | AN1981: 0 | AO1981: 114.72 | AP1981: 1 | AQ1981: 114.72 | AR1981: 1 | AS1981: 114.72 | AT1981: 1 | AU1981: 114.72 | AV1981: 1 | AW1981: 115.24 | AX1981: 0 | AY1981: 114.72 | AZ1981: 1 | BA1981: 114.72 | BB1981: 1 | BC1981: 114.72 | BD1981: 0 | BE1981: 114.72 | BF1981: 1
A1999: Depreciação, Juros, Impostos e Seguros, Manutenção e Materiais na Operação dos Equipamentos | B1999: =HYPERLINK("#"&CELL("address",OFFSET(Analítico!$B$1,MATCH(102948,Analítico!$B:$B,0)-1,3)),102948) -> 0 | C1999: BETONEIRA CAPACIDADE NOMINAL DE 250 L, CAPACIDADE DE MISTURA DE 175 L, MOTOR ELÉTRICO MONOFÁSICO POTÊNCIA 1CV - DEPRECIAÇÃO. AF_05/2023 | D1999: H | E1999: 0 | G1999: 0 | I1999: 0 | K1999: 0 | M1999: 0 | O1999: 0 | Q1999: 0 | S1999: 0 | U1999: 0 | W1999: 0 | Y1999: 0 | AA1999: 0 | AC1999: 0 | AE1999: 0 | AG1999: 0 | AI1999: 0 | AK1999: 0 | AM1999: 0 | AO1999: 0 | AQ1999: 0 | AS1999: 0 | AU1999: 0 | AW1999: 0 | AY1999: 0 | BA1999: 0 | BC1999: 0 | BE1999: 0
A2000: Depreciação, Juros, Impostos e Seguros, Manutenção e Materiais na Operação dos Equipamentos | B2000: =HYPERLINK("#"&CELL("address",OFFSET(Analítico!$B$1,MATCH(102949,Analítico!$B:$B,0)-1,3)),102949) -> 0 | C2000: BETONEIRA CAPACIDADE NOMINAL DE 250 L, CAPACIDADE DE MISTURA DE 175 L, MOTOR ELÉTRICO MONOFÁSICO POTÊNCIA 1CV - JUROS. AF_05/2023 | D2000: H | E2000: 0 | G2000: 0 | I2000: 0 | K2000: 0 | M2000: 0 | O2000: 0 | Q2000: 0 | S2000: 0 | U2000: 0 | W2000: 0 | Y2000: 0 | AA2000: 0 | AC2000: 0 | AE2000: 0 | AG2000: 0 | AI2000: 0 | AK2000: 0 | AM2000: 0 | AO2000: 0 | AQ2000: 0 | AS2000: 0 | AU2000: 0 | AW2000: 0 | AY2000: 0 | BA2000: 0 | BC2000: 0 | BE2000: 0
A7249: Livro SINAPI: Cálculos e Parâmetros | B7249: =HYPERLINK("#"&CELL("address",OFFSET(Analítico!$B$1,MATCH(95371,Analítico!$B:$B,0)-1,3)),95371) -> 0 | C7249: CURSO DE CAPACITAÇÃO PARA PEDREIRO (ENCARGOS COMPLEMENTARES) - HORISTA | D7249: H | E7249: 0.49 | F7249: 0 | G7249: 0.42 | H7249: 0 | I7249: 0.45 | J7249: 0 | K7249: 0.45 | L7249: 0 | M7249: 0.51 | N7249: 0 | O7249: 0.46 | P7249: 0 | Q7249: 0.49 | R7249: 0 | S7249: 0.46 | T7249: 0 | U7249: 0.5 | V7249: 0 | W7249: 0.45 | X7249: 0 | Y7249: 0.54 | Z7249: 0 | AA7249: 0.45 | AB7249: 0 | AC7249: 0.47 | AD7249: 0 | AE7249: 0.46 | AF7249: 0 | AG7249: 0.45 | AH7249: 0 | AI7249: 0.47 | AJ7249: 0 | AK7249: 0.46 | AL7249: 0 | AM7249: 0.61 | AN7249: 0 | AO7249: 0.64 | AP7249: 0 | AQ7249: 0.42 | AR7249: 0 | AS7249: 0.48 | AT7249: 0 | AU7249: 0.54 | AV7249: 0 | AW7249: 0.48 | AX7249: 0 | AY7249: 0.64 | AZ7249: 0 | BA7249: 0.43 | BB7249: 0 | BC7249: 0.55 | BD7249: 0 | BE7249: 0.45 | BF7249: 0
A7260: Livro SINAPI: Cálculos e Parâmetros | B7260: =HYPERLINK("#"&CELL("address",OFFSET(Analítico!$B$1,MATCH(95377,Analítico!$B:$B,0)-1,3)),95377) -> 0 | C7260: CURSO DE CAPACITAÇÃO PARA SERRALHEIRO (ENCARGOS COMPLEMENTARES) - HORISTA | D7260: H | E7260: 0.26 | F7260: 0 | G7260: 0.25 | H7260: 0 | I7260: 0.31 | J7260: 0 | K7260: 0.24 | L7260: 0 | M7260: 0.28 | N7260: 0 | O7260: 0.25 | P7260: 0 | Q7260: 0.26 | R7260: 0 | S7260: 0.29 | T7260: 0 | U7260: 0.27 | V7260: 0 | W7260: 0.24 | X7260: 0 | Y7260: 0.29 | Z7260: 0 | AA7260: 0.25 | AB7260: 0 | AC7260: 0.25 | AD7260: 0 | AE7260: 0.25 | AF7260: 0 | AG7260: 0.24 | AH7260: 0 | AI7260: 0.25 | AJ7260: 0 | AK7260: 0.25 | AL7260: 0 | AM7260: 0.33 | AN7260: 0 | AO7260: 0.34 | AP7260: 0 | AQ7260: 0.22 | AR7260: 0 | AS7260: 0.26 | AT7260: 0 | AU7260: 0.29 | AV7260: 0 | AW7260: 0.26 | AX7260: 0 | AY7260: 0.35 | AZ7260: 0 | BA7260: 0.23 | BB7260: 0 | BC7260: 0.3 | BD7260: 0 | BE7260: 0.24 | BF7260: 0
A7262: Livro SINAPI: Cálculos e Parâmetros | B7262: =HYPERLINK("#"&CELL("address",OFFSET(Analítico!$B$1,MATCH(95378,Analítico!$B:$B,0)-1,3)),95378) -> 0 | C7262: CURSO DE CAPACITAÇÃO PARA SERVENTE (ENCARGOS COMPLEMENTARES) - HORISTA | D7262: H | E7262: 0.34 | F7262: 0 | G7262: 0.33 | H7262: 0 | I7262: 0.33 | J7262: 0 | K7262: 0.33 | L7262: 0 | M7262: 0.34 | N7262: 0 | O7262: 0.33 | P7262: 0 | Q7262: 0.33 | R7262: 0 | S7262: 0.35 | T7262: 0 | U7262: 0.32 | V7262: 0 | W7262: 0.33 | X7262: 0 | Y7262: 0.36 | Z7262: 0 | AA7262: 0.33 | AB7262: 0 | AC7262: 0.35 | AD7262: 0 | AE7262: 0.34 | AF7262: 0 | AG7262: 0.34 | AH7262: 0 | AI7262: 0.35 | AJ7262: 0 | AK7262: 0.33 | AL7262: 0 | AM7262: 0.43 | AN7262: 0 | AO7262: 0.45 | AP7262: 0 | AQ7262: 0.33 | AR7262: 0 | AS7262: 0.39 | AT7262: 0 | AU7262: 0.33 | AV7262: 0 | AW7262: 0.37 | AX7262: 0 | AY7262: 0.44 | AZ7262: 0 | BA7262: 0.33 | BB7262: 0 | BC7262: 0.45 | BD7262: 0 | BE7262: 0.33 | BF7262: 0
A7377: Livro SINAPI: Cálculos e Parâmetros | B7377: =HYPERLINK("#"&CELL("address",OFFSET(Analítico!$B$1,MATCH(88309,Analítico!$B:$B,0)-1,3)),88309) -> 0 | C7377: PEDREIRO COM ENCARGOS COMPLEMENTARES | D7377: H | E7377: 31.13 | F7377: 0 | G7377: 27.41 | H7377: 0 | I7377: 32.8 | J7377: 0 | K7377: 26.51 | L7377: 0 | M7377: 34.28 | N7377: 0 | O7377: 31.25 | P7377: 0 | Q7377: 32.84 | R7377: 0 | S7377: 34.53 | T7377: 0 | U7377: 32.1 | V7377: 0 | W7377: 27.96 | X7377: 0 | Y7377: 33.62 | Z7377: 0 | AA7377: 28.5 | AB7377: 0 | AC7377: 30.54 | AD7377: 0 | AE7377: 32.75 | AF7377: 0 | AG7377: 28.53 | AH7377: 0 | AI7377: 29.98 | AJ7377: 0 | AK7377: 29.47 | AL7377: 0 | AM7377: 40.19 | AN7377: 0 | AO7377: 41.17 | AP7377: 0 | AQ7377: 29.48 | AR7377: 0 | AS7377: 31.14 | AT7377: 0 | AU7377: 34.29 | AV7377: 0 | AW7377: 29.88 | AX7377: 0 | AY7377: 36.22 | AZ7377: 0 | BA7377: 27.86 | BB7377: 0 | BC7377: 35.87 | BD7377: 0 | BE7377: 28.97 | BF7377: 0
A7388: Livro SINAPI: Cálculos e Parâmetros | B7388: =HYPERLINK("#"&CELL("address",OFFSET(Analítico!$B$1,MATCH(88315,Analítico!$B:$B,0)-1,3)),88315) -> 0 | C7388: SERRALHEIRO COM ENCARGOS COMPLEMENTARES | D7388: H | E7388: 30.9 | F7388: 0 | G7388: 29.25 | H7388: 0 | I7388: 37.93 | J7388: 0 | K7388: 26.3 | L7388: 0 | M7388: 34.05 | N7388: 0 | O7388: 31.04 | P7388: 0 | Q7388: 32.61 | R7388: 0 | S7388: 38.26 | T7388: 0 | U7388: 31.87 | V7388: 0 | W7388: 27.75 | X7388: 0 | Y7388: 33.37 | Z7388: 0 | AA7388: 28.8 | AB7388: 0 | AC7388: 30.32 | AD7388: 0 | AE7388: 32.54 | AF7388: 0 | AG7388: 28.32 | AH7388: 0 | AI7388: 29.76 | AJ7388: 0 | AK7388: 29.26 | AL7388: 0 | AM7388: 39.91 | AN7388: 0 | AO7388: 40.87 | AP7388: 0 | AQ7388: 29.28 | AR7388: 0 | AS7388: 30.92 | AT7388: 0 | AU7388: 34.04 | AV7388: 0 | AW7388: 29.66 | AX7388: 0 | AY7388: 35.93 | AZ7388: 0 | BA7388: 27.66 | BB7388: 0 | BC7388: 36.31 | BD7388: 0 | BE7388: 28.76 | BF7388: 0
A7390: Livro SINAPI: Cálculos e Parâmetros | B7390: =HYPERLINK("#"&CELL("address",OFFSET(Analítico!$B$1,MATCH(88316,Analítico!$B:$B,0)-1,3)),88316) -> 0 | C7390: SERVENTE COM ENCARGOS COMPLEMENTARES | D7390: H | E7390: 23.85 | F7390: 0 | G7390: 22.92 | H7390: 0 | I7390: 27.09 | J7390: 0 | K7390: 20.96 | L7390: 0 | M7390: 25.81 | N7390: 0 | O7390: 25.19 | P7390: 0 | Q7390: 25.11 | R7390: 0 | S7390: 28.97 | T7390: 0 | U7390: 23.2 | V7390: 0 | W7390: 22.24 | X7390: 0 | Y7390: 24.88 | Z7390: 0 | AA7390: 22.76 | AB7390: 0 | AC7390: 24.68 | AD7390: 0 | AE7390: 26.88 | AF7390: 0 | AG7390: 23.29 | AH7390: 0 | AI7390: 24.25 | AJ7390: 0 | AK7390: 23.66 | AL7390: 0 | AM7390: 31.41 | AN7390: 0 | AO7390: 32.12 | AP7390: 0 | AQ7390: 25.56 | AR7390: 0 | AS7390: 26.74 | AT7390: 0 | AU7390: 24.6 | AV7390: 0 | AW7390: 24.83 | AX7390: 0 | AY7390: 26.47 | AZ7390: 0 | BA7390: 22.83 | BB7390: 0 | BC7390: 31.15 | BD7390: 0 | BE7390: 23.34 | BF7390: 0

Sheet CCD
A1: SINAPI - Sistema Nacional de Pesquisa de Custos e Índices da Construção Civil
A2: RELATÓRIO DE CUSTOS DE COMPOSIÇÕES - ENCARGOS SOCIAIS COM DESONERAÇÃO
A3: Mês de Referência: | B3: 01/2026 | D3: Encargos sociais sobre a mão de obra:
A4: Data de emissão: | B4: 23/03/2026 | D4: (COM DESONERAÇÃO) | E4: AC | G4: AL | I4: AM | K4: AP | M4: BA | O4: CE | Q4: DF | S4: ES | U4: GO | W4: MA | Y4: MG | AA4: MS | AC4: MT | AE4: PA | AG4: PB | AI4: PE | AK4: PI | AM4: PR | AO4: RJ | AQ4: RN | AS4: RO | AU4: RR | AW4: RS | AY4: SC | BA4: SE | BC4: SP | BE4: TO
D5: Localidade | E5: RIO BRANCO | G5: MACEIO | I5: MANAUS | K5: MACAPA | M5: SALVADOR | O5: FORTALEZA | Q5: BRASILIA | S5: VITORIA | U5: GOIANIA | W5: SAO LUIS | Y5: BELO HORIZONTE | AA5: CAMPO GRANDE | AC5: CUIABA | AE5: BELEM | AG5: JOAO PESSOA | AI5: RECIFE | AK5: TERESINA | AM5: CURITIBA | AO5: RIO DE JANEIRO | AQ5: NATAL | AS5: PORTO VELHO | AU5: BOA VISTA | AW5: PORTO ALEGRE | AY5: FLORIANOPOLIS | BA5: ARACAJU | BC5: SAO PAULO | BE5: PALMAS
A6: Observação: | B6: %AS (porcentagem Atribuído São Paulo) corresponde a porcentagem do custo total da | D6: Horista | E6: 0.9688 | G6: 1.0013 | I6: 0.9835 | K6: 0.9923 | M6: 1.017 | O6: 0.9971 | Q6: 0.9463 | S6: 1.0222 | U6: 0.9322 | W6: 0.9831 | Y6: 1.0033 | AA6: 0.9956 | AC6: 0.9089 | AE6: 1.0326 | AG6: 1.0206 | AI6: 0.9883 | AK6: 0.9796 | AM6: 1.0025 | AO6: 0.9688 | AQ6: 1.0077 | AS6: 0.9961 | AU6: 0.9885 | AW6: 0.9612 | AY6: 0.9838 | BA6: 0.9588 | BC6: 0.9909 | BE6: 0.9923
B7: composição que foi obtida utilizando preços de insumos de São Paulo por indisponibilidade | D7: Mensalista | E7: 0.5653 | G7: 0.5859 | I7: 0.582 | K7: 0.5746 | M7: 0.6013 | O7: 0.5974 | Q7: 0.5745 | S7: 0.6106 | U7: 0.5747 | W7: 0.5866 | Y7: 0.6106 | AA7: 0.5874 | AC7: 0.5603 | AE7: 0.5998 | AG7: 0.5991 | AI7: 0.581 | AK7: 0.5891 | AM7: 0.5965 | AO7: 0.572 | AQ7: 0.5955 | AS7: 0.5792 | AU7: 0.5772 | AW7: 0.5667 | AY7: 0.5822 | BA7: 0.5718 | BC7: 0.5851 | BE7: 0.592
B8: dos preços de insumos necessários à composição no estado em questão. Custo zerado (hífen)
B9: indica que pelo menos um dos itens da composição não tem custo/preço. | E9: AC | G9: AL | I9: AM | K9: AP | M9: BA | O9: CE | Q9: DF | S9: ES | U9: GO | W9: MA | Y9: MG | AA9: MS | AC9: MT | AE9: PA | AG9: PB | AI9: PE | AK9: PI | AM9: PR | AO9: RJ | AQ9: RN | AS9: RO | AU9: RR | AW9: RS | AY9: SC | BA9: SE | BC9: SP | BE9: TO
A10: Grupo | B10: Código da Composição | C10: Descrição | D10: Unidade | E10: Custo (R$) | F10: %AS | G10: Custo (R$) | H10: %AS | I10: Custo (R$) | J10: %AS | K10: Custo (R$) | L10: %AS | M10: Custo (R$) | N10: %AS | O10: Custo (R$) | P10: %AS | Q10: Custo (R$) | R10: %AS | S10: Custo (R$) | T10: %AS | U10: Custo (R$) | V10: %AS | W10: Custo (R$) | X10: %AS | Y10: Custo (R$) | Z10: %AS | AA10: Custo (R$) | AB10: %AS | AC10: Custo (R$) | AD10: %AS | AE10: Custo (R$) | AF10: %AS | AG10: Custo (R$) | AH10: %AS | AI10: Custo (R$) | AJ10: %AS | AK10: Custo (R$) | AL10: %AS | AM10: Custo (R$) | AN10: %AS | AO10: Custo (R$) | AP10: %AS | AQ10: Custo (R$) | AR10: %AS | AS10: Custo (R$) | AT10: %AS | AU10: Custo (R$) | AV10: %AS | AW10: Custo (R$) | AX10: %AS | AY10: Custo (R$) | AZ10: %AS | BA10: Custo (R$) | BB10: %AS | BC10: Custo (R$) | BD10: %AS | BE10: Custo (R$) | BF10: %AS
A11: Acessibilidade | B11: =HYPERLINK("#"&CELL("address",OFFSET(Analítico!$B$1,MATCH(104658,Analítico!$B:$B,0)-1,3)),104658) -> 0 | C11: PISO PODOTÁTIL DE ALERTA OU DIRECIONAL, DE CONCRETO, ASSENTADO SOBRE ARGAMASSA. AF_03/2024 | D11: M2 | E11: 250.75 | F11: 0 | G11: 154.04 | H11: 0 | I11: 223.07 | J11: 0 | K11: 195.09 | L11: 0 | M11: 166.38 | N11: 0 | O11: 162.24 | P11: 0 | Q11: 186.74 | R11: 0 | S11: 175.63 | T11: 0 | U11: 176.44 | V11: 0 | W11: 161.04 | X11: 0 | Y11: 162.22 | Z11: 0 | AA11: 172.52 | AB11: 0 | AC11: 212.08 | AD11: 0 | AE11: 170.55 | AF11: 0 | AG11: 141.74 | AH11: 0 | AI11: 151.53 | AJ11: 0 | AK11: 146.49 | AL11: 0 | AM11: 156.93 | AN11: 0 | AO11: 178.27 | AP11: 0 | AQ11: 166.23 | AR11: 0 | AS11: 207.56 | AT11: 0 | AU11: 264.17 | AV11: 0 | AW11: 153.18 | AX11: 0 | AY11: 148.07 | AZ11: 0 | BA11: 167.26 | BB11: 0 | BC11: 191.17 | BD11: 0 | BE11: 193.03 | BF11: 0
A112: Argamassas | B112: =HYPERLINK("#"&CELL("address",OFFSET(Analítico!$B$1,MATCH(87398,Analítico!$B:$B,0)-1,3)),87398) -> 0 | C112: ARGAMASSA INDUSTRIALIZADA MULTIUSO PARA REVESTIMENTOS E ASSENTAMENTO DA ALVENARIA, PREPARO MANUAL. AF_08/2019 | D112: M3 | E112: 2968.58 | F112: 0 | G112: 2333.55 | H112: 0 | I112: 2953.05 | J112: 0 | K112: 2573.6 | L112: 0 | M112: 2048.51 | N112: 0 | O112: 2702.33 | P112: 0 | Q112: 1605.25 | R112: 0 | S112: 1841.96 | T112: 0 | U112: 1922.79 | V112: 0 | W112: 2381.81 | X112: 0 | Y112: 1695.47 | Z112: 0 | AA112: 2218.01 | AB112: 0 | AC112: 2866.01 | AD112: 0 | AE112: 2175.25 | AF112: 0 | AG112: 1921.9 | AH112: 0 | AI112: 2349.41 | AJ112: 0 | AK112: 1775.87 | AL112: 0 | AM112: 1944.63 | AN112: 0 | AO112: 1820.52 | AP112: 0 | AQ112: 2328.86 | AR112: 0 | AS112: 2511.05 | AT112: 0 | AU112: 3715.5 | AV112: 0 | AW112: 1939.91 | AX112: 0 | AY112: 1749.38 | AZ112: 0 | BA112: 2181.47 | BB112: 0 | BC112: 2015.95 | BD112: 0 | BE112: 1809.64 | BF112: 0
A1105: Brises | B1105: =HYPERLINK("#"&CELL("address",OFFSET(Analítico!$B$1,MATCH(104943,Analítico!$B:$B,0)-1,3)),104943) -> 0 | C1105: FORNECIMENTO E INSTALAÇÃO DE CONJUNTO DE BRISE EM REQUADRO DE ALUMÍNIO DESLIZANTE, COM PERFIS INTERNOS TUBULARES FIXOS, COM PINTURA ELETROSTÁTICA BRANCA, ACABAMENTO, 150 CM X 265 CM. AF_03/2024 | D1105: M2 | E1105: 0 | G1105: 0 | I1105: 0 | K1105: 0 | M1105: 0 | O1105: 0 | Q1105: 0 | S1105: 0 | U1105: 0 | W1105: 0 | Y1105: 0 | AA1105: 0 | AC1105: 0 | AE1105: 0 | AG1105: 0 | AI1105: 0 | AK1105: 0 | AM1105: 0 | AO1105: 0 | AQ1105: 0 | AS1105: 0 | AU1105: 0 | AW1105: 0 | AY1105: 0 | BA1105: 0 | BC1105: 0 | BE1105: 0
A1493: Custos Horários Produtivo e Improdutivo dos Equipamentos | B1493: =HYPERLINK("#"&CELL("address",OFFSET(Analítico!$B$1,MATCH(102953,Analítico!$B:$B,0)-1,3)),102953) -> 0 | C1493: BETONEIRA CAPACIDADE NOMINAL DE 250 L, CAPACIDADE DE MISTURA DE 175 L, MOTOR ELÉTRICO MONOFÁSICO POTÊNCIA 1CV - CHI DIURNO. AF_05/2023 | D1493: CHI | E1493: 0 | G1493: 0 | I1493: 0 | K1493: 0 | M1493: 0 | O1493: 0 | Q1493: 0 | S1493: 0 | U1493: 0 | W1493: 0 | Y1493: 0 | AA1493: 0 | AC1493: 0 | AE1493: 0 | AG1493: 0 | AI1493: 0 | AK1493: 0 | AM1493: 0 | AO1493: 0 | AQ1493: 0 | AS1493: 0 | AU1493: 0 | AW1493: 0 | AY1493: 0 | BA1493: 0 | BC1493: 0 | BE1493: 0
A1981: Depreciação, Juros, Impostos e Seguros, Manutenção e Materiais na Operação dos Equipamentos | B1981: =HYPERLINK("#"&CELL("address",OFFSET(Analítico!$B$1,MATCH(92715,Analítico!$B:$B,0)-1,3)),92715) -> 0 | C1981: APARELHO PARA CORTE E SOLDA OXI-ACETILENO SOBRE RODAS, INCLUSIVE CILINDROS E MAÇARICOS - MATERIAIS NA OPERAÇÃO. AF_05/2023 | D1981: H | E1981: 114.72 | F1981: 1 | G1981: 139.08 | H1981: 0 | I1981: 114.72 | J1981: 1 | K1981: 114.72 | L1981: 1 | M1981: 164.59 | N1981: 0 | O1981: 105.48 | P1981: 0 | Q1981: 114.72 | R1981: 1 | S1981: 109.52 | T1981: 0 | U1981: 101.96 | V1981: 0 | W1981: 114.72 | X1981: 1 | Y1981: 83.44 | Z1981: 0 | AA1981: 104.3 | AB1981: 0 | AC1981: 124.8 | AD1981: 0 | AE1981: 114.72 | AF1981: 1 | AG1981: 114.72 | AH1981: 1 | AI1981: 114.72 | AJ1981: 1 | AK1981: 114.72 | AL1981: 1 | AM1981: 146.04 | AN1981: 0 | AO1981: 114.72 | AP1981: 1 | AQ1981: 114.72 | AR1981: 1 | AS1981: 114.72 | AT1981: 1 | AU1981: 114.72 | AV1981: 1 | AW1981: 115.24 | AX1981: 0 | AY1981: 114.72 | AZ1981: 1 | BA1981: 114.72 | BB1981: 1 | BC1981: 114.72 | BD1981: 0 | BE1981: 114.72 | BF1981: 1
A1999: Depreciação, Juros, Impostos e Seguros, Manutenção e Materiais na Operação dos Equipamentos | B1999: =HYPERLINK("#"&CELL("address",OFFSET(Analítico!$B$1,MATCH(102948,Analítico!$B:$B,0)-1,3)),102948) -> 0 | C1999: BETONEIRA CAPACIDADE NOMINAL DE 250 L, CAPACIDADE DE MISTURA DE 175 L, MOTOR ELÉTRICO MONOFÁSICO POTÊNCIA 1CV - DEPRECIAÇÃO. AF_05/2023 | D1999: H | E1999: 0 | G1999: 0 | I1999: 0 | K1999: 0 | M1999: 0 | O1999: 0 | Q1999: 0 | S1999: 0 | U1999: 0 | W1999: 0 | Y1999: 0 | AA1999: 0 | AC1999: 0 | AE1999: 0 | AG1999: 0 | AI1999: 0 | AK1999: 0 | AM1999: 0 | AO1999: 0 | AQ1999: 0 | AS1999: 0 | AU1999: 0 | AW1999: 0 | AY1999: 0 | BA1999: 0 | BC1999: 0 | BE1999: 0
A2000: Depreciação, Juros, Impostos e Seguros, Manutenção e Materiais na Operação dos Equipamentos | B2000: =HYPERLINK("#"&CELL("address",OFFSET(Analítico!$B$1,MATCH(102949,Analítico!$B:$B,0)-1,3)),102949) -> 0 | C2000: BETONEIRA CAPACIDADE NOMINAL DE 250 L, CAPACIDADE DE MISTURA DE 175 L, MOTOR ELÉTRICO MONOFÁSICO POTÊNCIA 1CV - JUROS. AF_05/2023 | D2000: H | E2000: 0 | G2000: 0 | I2000: 0 | K2000: 0 | M2000: 0 | O2000: 0 | Q2000: 0 | S2000: 0 | U2000: 0 | W2000: 0 | Y2000: 0 | AA2000: 0 | AC2000: 0 | AE2000: 0 | AG2000: 0 | AI2000: 0 | AK2000: 0 | AM2000: 0 | AO2000: 0 | AQ2000: 0 | AS2000: 0 | AU2000: 0 | AW2000: 0 | AY2000: 0 | BA2000: 0 | BC2000: 0 | BE2000: 0
A7249: Livro SINAPI: Cálculos e Parâmetros | B7249: =HYPERLINK("#"&CELL("address",OFFSET(Analítico!$B$1,MATCH(95371,Analítico!$B:$B,0)-1,3)),95371) -> 0 | C7249: CURSO DE CAPACITAÇÃO PARA PEDREIRO (ENCARGOS COMPLEMENTARES) - HORISTA | D7249: H | E7249: 0.45 | F7249: 0 | G7249: 0.39 | H7249: 0 | I7249: 0.42 | J7249: 0 | K7249: 0.41 | L7249: 0 | M7249: 0.47 | N7249: 0 | O7249: 0.42 | P7249: 0 | Q7249: 0.45 | R7249: 0 | S7249: 0.43 | T7249: 0 | U7249: 0.47 | V7249: 0 | W7249: 0.41 | X7249: 0 | Y7249: 0.5 | Z7249: 0 | AA7249: 0.41 | AB7249: 0 | AC7249: 0.43 | AD7249: 0 | AE7249: 0.43 | AF7249: 0 | AG7249: 0.42 | AH7249: 0 | AI7249: 0.44 | AJ7249: 0 | AK7249: 0.42 | AL7249: 0 | AM7249: 0.56 | AN7249: 0 | AO7249: 0.59 | AP7249: 0 | AQ7249: 0.38 | AR7249: 0 | AS7249: 0.45 | AT7249: 0 | AU7249: 0.5 | AV7249: 0 | AW7249: 0.44 | AX7249: 0 | AY7249: 0.59 | AZ7249: 0 | BA7249: 0.4 | BB7249: 0 | BC7249: 0.51 | BD7249: 0 | BE7249: 0.41 | BF7249: 0
A7260: Livro SINAPI: Cálculos e Parâmetros | B7260: =HYPERLINK("#"&CELL("address",OFFSET(Analítico!$B$1,MATCH(95377,Analítico!$B:$B,0)-1,3)),95377) -> 0 | C7260: CURSO DE CAPACITAÇÃO PARA SERRALHEIRO (ENCARGOS COMPLEMENTARES) - HORISTA | D7260: H | E7260: 0.24 | F7260: 0 | G7260: 0.23 | H7260: 0 | I7260: 0.28 | J7260: 0 | K7260: 0.22 | L7260: 0 | M7260: 0.25 | N7260: 0 | O7260: 0.23 | P7260: 0 | Q7260: 0.24 | R7260: 0 | S7260: 0.27 | T7260: 0 | U7260: 0.25 | V7260: 0 | W7260: 0.22 | X7260: 0 | Y7260: 0.27 | Z7260: 0 | AA7260: 0.23 | AB7260: 0 | AC7260: 0.23 | AD7260: 0 | AE7260: 0.23 | AF7260: 0 | AG7260: 0.23 | AH7260: 0 | AI7260: 0.24 | AJ7260: 0 | AK7260: 0.23 | AL7260: 0 | AM7260: 0.3 | AN7260: 0 | AO7260: 0.32 | AP7260: 0 | AQ7260: 0.21 | AR7260: 0 | AS7260: 0.24 | AT7260: 0 | AU7260: 0.27 | AV7260: 0 | AW7260: 0.24 | AX7260: 0 | AY7260: 0.32 | AZ7260: 0 | BA7260: 0.21 | BB7260: 0 | BC7260: 0.28 | BD7260: 0 | BE7260: 0.22 | BF7260: 0
A7262: Livro SINAPI: Cálculos e Parâmetros | B7262: =HYPERLINK("#"&CELL("address",OFFSET(Analítico!$B$1,MATCH(95378,Analítico!$B:$B,0)-1,3)),95378) -> 0 | C7262: CURSO DE CAPACITAÇÃO PARA SERVENTE (ENCARGOS COMPLEMENTARES) - HORISTA | D7262: H | E7262: 0.31 | F7262: 0 | G7262: 0.31 | H7262: 0 | I7262: 0.31 | J7262: 0 | K7262: 0.31 | L7262: 0 | M7262: 0.31 | N7262: 0 | O7262: 0.31 | P7262: 0 | Q7262: 0.3 | R7262: 0 | S7262: 0.32 | T7262: 0 | U7262: 0.3 | V7262: 0 | W7262: 0.3 | X7262: 0 | Y7262: 0.34 | Z7262: 0 | AA7262: 0.31 | AB7262: 0 | AC7262: 0.32 | AD7262: 0 | AE7262: 0.31 | AF7262: 0 | AG7262: 0.32 | AH7262: 0 | AI7262: 0.33 | AJ7262: 0 | AK7262: 0.31 | AL7262: 0 | AM7262: 0.4 | AN7262: 0 | AO7262: 0.42 | AP7262: 0 | AQ7262: 0.31 | AR7262: 0 | AS7262: 0.36 | AT7262: 0 | AU7262: 0.31 | AV7262: 0 | AW7262: 0.35 | AX7262: 0 | AY7262: 0.41 | AZ7262: 0 | BA7262: 0.3 | BB7262: 0 | BC7262: 0.42 | BD7262: 0 | BE7262: 0.31 | BF7262: 0
A7377: Livro SINAPI: Cálculos e Parâmetros | B7377: =HYPERLINK("#"&CELL("address",OFFSET(Analítico!$B$1,MATCH(88309,Analítico!$B:$B,0)-1,3)),88309) -> 0 | C7377: PEDREIRO COM ENCARGOS COMPLEMENTARES | D7377: H | E7377: 29.36 | F7377: 0 | G7377: 25.88 | H7377: 0 | I7377: 31.17 | J7377: 0 | K7377: 24.89 | L7377: 0 | M7377: 32.45 | N7377: 0 | O7377: 29.6 | P7377: 0 | Q7377: 31.09 | R7377: 0 | S7377: 32.87 | T7377: 0 | U7377: 30.39 | V7377: 0 | W7377: 26.35 | X7377: 0 | Y7377: 31.67 | Z7377: 0 | AA7377: 26.87 | AB7377: 0 | AC7377: 28.94 | AD7377: 0 | AE7377: 31.1 | AF7377: 0 | AG7377: 26.9 | AH7377: 0 | AI7377: 28.29 | AJ7377: 0 | AK7377: 27.82 | AL7377: 0 | AM7377: 38 | AN7377: 0 | AO7377: 38.89 | AP7377: 0 | AQ7377: 27.98 | AR7377: 0 | AS7377: 29.39 | AT7377: 0 | AU7377: 32.36 | AV7377: 0 | AW7377: 28.14 | AX7377: 0 | AY7377: 33.87 | AZ7377: 0 | BA7377: 26.32 | BB7377: 0 | BC7377: 33.9 | BD7377: 0 | BE7377: 27.35 | BF7377: 0
A7388: Livro SINAPI: Cálculos e Parâmetros | B7388: =HYPERLINK("#"&CELL("address",OFFSET(Analítico!$B$1,MATCH(88315,Analítico!$B:$B,0)-1,3)),88315) -> 0 | C7388: SERRALHEIRO COM ENCARGOS COMPLEMENTARES | D7388: H | E7388: 29.15 | F7388: 0 | G7388: 27.58 | H7388: 0 | I7388: 35.91 | J7388: 0 | K7388: 24.7 | L7388: 0 | M7388: 32.23 | N7388: 0 | O7388: 29.41 | P7388: 0 | Q7388: 30.88 | R7388: 0 | S7388: 36.33 | T7388: 0 | U7388: 30.17 | V7388: 0 | W7388: 26.16 | X7388: 0 | Y7388: 31.44 | Z7388: 0 | AA7388: 27.15 | AB7388: 0 | AC7388: 28.74 | AD7388: 0 | AE7388: 30.9 | AF7388: 0 | AG7388: 26.71 | AH7388: 0 | AI7388: 28.09 | AJ7388: 0 | AK7388: 27.63 | AL7388: 0 | AM7388: 37.74 | AN7388: 0 | AO7388: 38.62 | AP7388: 0 | AQ7388: 27.81 | AR7388: 0 | AS7388: 29.18 | AT7388: 0 | AU7388: 32.13 | AV7388: 0 | AW7388: 27.94 | AX7388: 0 | AY7388: 33.6 | AZ7388: 0 | BA7388: 26.13 | BB7388: 0 | BC7388: 34.31 | BD7388: 0 | BE7388: 27.16 | BF7388: 0
A7390: Livro SINAPI: Cálculos e Parâmetros | B7390: =HYPERLINK("#"&CELL("address",OFFSET(Analítico!$B$1,MATCH(88316,Analítico!$B:$B,0)-1,3)),88316) -> 0 | C7390: SERVENTE COM ENCARGOS COMPLEMENTARES | D7390: H | E7390: 22.62 | F7390: 0 | G7390: 21.72 | H7390: 0 | I7390: 25.89 | J7390: 0 | K7390: 19.77 | L7390: 0 | M7390: 24.6 | N7390: 0 | O7390: 23.99 | P7390: 0 | Q7390: 23.92 | R7390: 0 | S7390: 27.71 | T7390: 0 | U7390: 22.12 | V7390: 0 | W7390: 21.05 | X7390: 0 | Y7390: 23.58 | Z7390: 0 | AA7390: 21.55 | AB7390: 0 | AC7390: 23.48 | AD7390: 0 | AE7390: 25.66 | AF7390: 0 | AG7390: 22.05 | AH7390: 0 | AI7390: 22.98 | AJ7390: 0 | AK7390: 22.46 | AL7390: 0 | AM7390: 29.86 | AN7390: 0 | AO7390: 30.51 | AP7390: 0 | AQ7390: 24.35 | AR7390: 0 | AS7390: 25.31 | AT7390: 0 | AU7390: 23.4 | AV7390: 0 | AW7390: 23.48 | AX7390: 0 | AY7390: 24.86 | AZ7390: 0 | BA7390: 21.65 | BB7390: 0 | BC7390: 29.52 | BD7390: 0 | BE7390: 22.14 | BF7390: 0

Sheet CSE
A1: SINAPI - Sistema Nacional de Pesquisa de Custos e Índices da Construção Civil
A2: RELATÓRIO DE CUSTOS DE COMPOSIÇÕES - SEM ENCARGOS SOCIAIS
A3: Mês de Referência: | B3: 01/2026
A4: Data de emissão: | B4: 23/03/2026
A6: Observação: | B6: %AS (porcentagem Atribuído São Paulo) corresponde a porcentagem do custo total da
B7: composição que foi obtida utilizando preços de insumos de São Paulo por indisponibilidade
B8: dos preços de insumos necessários à composição no estado em questão. Custo zerado (hífen)
B9: indica que pelo menos um dos itens da composição não tem custo/preço. | E9: AC | G9: AL | I9: AM | K9: AP | M9: BA | O9: CE | Q9: DF | S9: ES | U9: GO | W9: MA | Y9: MG | AA9: MS | AC9: MT | AE9: PA | AG9: PB | AI9: PE | AK9: PI | AM9: PR | AO9: RJ | AQ9: RN | AS9: RO | AU9: RR | AW9: RS | AY9: SC | BA9: SE | BC9: SP | BE9: TO
A10: Grupo | B10: Código da Composição | C10: Descrição | D10: Unidade | E10: Custo (R$) | F10: %AS | G10: Custo (R$) | H10: %AS | I10: Custo (R$) | J10: %AS | K10: Custo (R$) | L10: %AS | M10: Custo (R$) | N10: %AS | O10: Custo (R$) | P10: %AS | Q10: Custo (R$) | R10: %AS | S10: Custo (R$) | T10: %AS | U10: Custo (R$) | V10: %AS | W10: Custo (R$) | X10: %AS | Y10: Custo (R$) | Z10: %AS | AA10: Custo (R$) | AB10: %AS | AC10: Custo (R$) | AD10: %AS | AE10: Custo (R$) | AF10: %AS | AG10: Custo (R$) | AH10: %AS | AI10: Custo (R$) | AJ10: %AS | AK10: Custo (R$) | AL10: %AS | AM10: Custo (R$) | AN10: %AS | AO10: Custo (R$) | AP10: %AS | AQ10: Custo (R$) | AR10: %AS | AS10: Custo (R$) | AT10: %AS | AU10: Custo (R$) | AV10: %AS | AW10: Custo (R$) | AX10: %AS | AY10: Custo (R$) | AZ10: %AS | BA10: Custo (R$) | BB10: %AS | BC10: Custo (R$) | BD10: %AS | BE10: Custo (R$) | BF10: %AS
A11: Acessibilidade | B11: =HYPERLINK("#"&CELL("address",OFFSET(Analítico!$B$1,MATCH(104658,Analítico!$B:$B,0)-1,3)),104658) -> 0 | C11: PISO PODOTÁTIL DE ALERTA OU DIRECIONAL, DE CONCRETO, ASSENTADO SOBRE ARGAMASSA. AF_03/2024 | D11: M2 | E11: 234.11 | F11: 0 | G11: 138.28 | H11: 0 | I11: 206.97 | J11: 0 | K11: 179.13 | L11: 0 | M11: 149.19 | N11: 0 | O11: 146.05 | P11: 0 | Q11: 170.74 | R11: 0 | S11: 158.68 | T11: 0 | U11: 160.44 | V11: 0 | W11: 145.22 | X11: 0 | Y11: 143.89 | Z11: 0 | AA11: 156.54 | AB11: 0 | AC11: 196.04 | AD11: 0 | AE11: 153.89 | AF11: 0 | AG11: 125.09 | AH11: 0 | AI11: 134.57 | AJ11: 0 | AK11: 130.43 | AL11: 0 | AM11: 135.79 | AN11: 0 | AO11: 156.47 | AP11: 0 | AQ11: 150.52 | AR11: 0 | AS11: 189.35 | AT11: 0 | AU11: 246.92 | AV11: 0 | AW11: 135.83 | AX11: 0 | AY11: 126.31 | AZ11: 0 | BA11: 151.98 | BB11: 0 | BC11: 170.41 | BD11: 0 | BE11: 177.07 | BF11: 0
A112: Argamassas | B112: =HYPERLINK("#"&CELL("address",OFFSET(Analítico!$B$1,MATCH(87398,Analítico!$B:$B,0)-1,3)),87398) -> 0 | C112: ARGAMASSA INDUSTRIALIZADA MULTIUSO PARA REVESTIMENTOS E ASSENTAMENTO DA ALVENARIA, PREPARO MANUAL. AF_08/2019 | D112: M3 | E112: 2873.27 | F112: 0 | G112: 2238.75 | H112: 0 | I112: 2858.5 | J112: 0 | K112: 2479.55 | L112: 0 | M112: 1952.2 | N112: 0 | O112: 2607.9 | P112: 0 | Q112: 1514.73 | R112: 0 | S112: 1741.62 | T112: 0 | U112: 1834.4 | V112: 0 | W112: 2288.77 | X112: 0 | Y112: 1591.98 | Z112: 0 | AA112: 2123.71 | AB112: 0 | AC112: 2771.58 | AD112: 0 | AE112: 2077.43 | AF112: 0 | AG112: 1822.95 | AH112: 0 | AI112: 2249.07 | AJ112: 0 | AK112: 1681.95 | AL112: 0 | AM112: 1822.76 | AN112: 0 | AO112: 1694.74 | AP112: 0 | AQ112: 2233.43 | AR112: 0 | AS112: 2400 | AT112: 0 | AU112: 3621.08 | AV112: 0 | AW112: 1835.54 | AX112: 0 | AY112: 1625.12 | AZ112: 0 | BA112: 2090.69 | BB112: 0 | BC112: 1888.67 | BD112: 0 | BE112: 1715.59 | BF112: 0
A1105: Brises | B1105: =HYPERLINK("#"&CELL("address",OFFSET(Analítico!$B$1,MATCH(104943,Analítico!$B:$B,0)-1,3)),104943) -> 0 | C1105: FORNECIMENTO E INSTALAÇÃO DE CONJUNTO DE BRISE EM REQUADRO DE ALUMÍNIO DESLIZANTE, COM PERFIS INTERNOS TUBULARES FIXOS, COM PINTURA ELETROSTÁTICA BRANCA, ACABAMENTO, 150 CM X 265 CM. AF_03/2024 | D1105: M2 | E1105: 0 | G1105: 0 | I1105: 0 | K1105: 0 | M1105: 0 | O1105: 0 | Q1105: 0 | S1105: 0 | U1105: 0 | W1105: 0 | Y1105: 0 | AA1105: 0 | AC1105: 0 | AE1105: 0 | AG1105: 0 | AI1105: 0 | AK1105: 0 | AM1105: 0 | AO1105: 0 | AQ1105: 0 | AS1105: 0 | AU1105: 0 | AW1105: 0 | AY1105: 0 | BA1105: 0 | BC1105: 0 | BE1105: 0
A1493: Custos Horários Produtivo e Improdutivo dos Equipamentos | B1493: =HYPERLINK("#"&CELL("address",OFFSET(Analítico!$B$1,MATCH(102953,Analítico!$B:$B,0)-1,3)),102953) -> 0 | C1493: BETONEIRA CAPACIDADE NOMINAL DE 250 L, CAPACIDADE DE MISTURA DE 175 L, MOTOR ELÉTRICO MONOFÁSICO POTÊNCIA 1CV - CHI DIURNO. AF_05/2023 | D1493: CHI | E1493: 0 | G1493: 0 | I1493: 0 | K1493: 0 | M1493: 0 | O1493: 0 | Q1493: 0 | S1493: 0 | U1493: 0 | W1493: 0 | Y1493: 0 | AA1493: 0 | AC1493: 0 | AE1493: 0 | AG1493: 0 | AI1493: 0 | AK1493: 0 | AM1493: 0 | AO1493: 0 | AQ1493: 0 | AS1493: 0 | AU1493: 0 | AW1493: 0 | AY1493: 0 | BA1493: 0 | BC1493: 0 | BE1493: 0
A1981: Depreciação, Juros, Impostos e Seguros, Manutenção e Materiais na Operação dos Equipamentos | B1981: =HYPERLINK("#"&CELL("address",OFFSET(Analítico!$B$1,MATCH(92715,Analítico!$B:$B,0)-1,3)),92715) -> 0 | C1981: APARELHO PARA CORTE E SOLDA OXI-ACETILENO SOBRE RODAS, INCLUSIVE CILINDROS E MAÇARICOS - MATERIAIS NA OPERAÇÃO. AF_05/2023 | D1981: H | E1981: 114.72 | F1981: 1 | G1981: 139.08 | H1981: 0 | I1981: 114.72 | J1981: 1 | K1981: 114.72 | L1981: 1 | M1981: 164.59 | N1981: 0 | O1981: 105.48 | P1981: 0 | Q1981: 114.72 | R1981: 1 | S1981: 109.52 | T1981: 0 | U1981: 101.96 | V1981: 0 | W1981: 114.72 | X1981: 1 | Y1981: 83.44 | Z1981: 0 | AA1981: 104.3 | AB1981: 0 | AC1981: 124.8 | AD1981: 0 | AE1981: 114.72 | AF1981: 1 | AG1981: 114.72 | AH1981: 1 | AI1981: 114.72 | AJ1981: 1 | AK1981: 114.72 | AL1981: 1 | AM1981: 146.04 | AN1981: 0 | AO1981: 114.72 | AP1981: 1 | AQ1981: 114.72 | AR1981: 1 | AS1981: 114.72 | AT1981: 1 | AU1981: 114.72 | AV1981: 1 | AW1981: 115.24 | AX1981: 0 | AY1981: 114.72 | AZ1981: 1 | BA1981: 114.72 | BB1981: 1 | BC1981: 114.72 | BD1981: 0 | BE1981: 114.72 | BF1981: 1
A1999: Depreciação, Juros, Impostos e Seguros, Manutenção e Materiais na Operação dos Equipamentos | B1999: =HYPERLINK("#"&CELL("address",OFFSET(Analítico!$B$1,MATCH(102948,Analítico!$B:$B,0)-1,3)),102948) -> 0 | C1999: BETONEIRA CAPACIDADE NOMINAL DE 250 L, CAPACIDADE DE MISTURA DE 175 L, MOTOR ELÉTRICO MONOFÁSICO POTÊNCIA 1CV - DEPRECIAÇÃO. AF_05/2023 | D1999: H | E1999: 0 | G1999: 0 | I1999: 0 | K1999: 0 | M1999: 0 | O1999: 0 | Q1999: 0 | S1999: 0 | U1999: 0 | W1999: 0 | Y1999: 0 | AA1999: 0 | AC1999: 0 | AE1999: 0 | AG1999: 0 | AI1999: 0 | AK1999: 0 | AM1999: 0 | AO1999: 0 | AQ1999: 0 | AS1999: 0 | AU1999: 0 | AW1999: 0 | AY1999: 0 | BA1999: 0 | BC1999: 0 | BE1999: 0
A2000: Depreciação, Juros, Impostos e Seguros, Manutenção e Materiais na Operação dos Equipamentos | B2000: =HYPERLINK("#"&CELL("address",OFFSET(Analítico!$B$1,MATCH(102949,Analítico!$B:$B,0)-1,3)),102949) -> 0 | C2000: BETONEIRA CAPACIDADE NOMINAL DE 250 L, CAPACIDADE DE MISTURA DE 175 L, MOTOR ELÉTRICO MONOFÁSICO POTÊNCIA 1CV - JUROS. AF_05/2023 | D2000: H | E2000: 0 | G2000: 0 | I2000: 0 | K2000: 0 | M2000: 0 | O2000: 0 | Q2000: 0 | S2000: 0 | U2000: 0 | W2000: 0 | Y2000: 0 | AA2000: 0 | AC2000: 0 | AE2000: 0 | AG2000: 0 | AI2000: 0 | AK2000: 0 | AM2000: 0 | AO2000: 0 | AQ2000: 0 | AS2000: 0 | AU2000: 0 | AW2000: 0 | AY2000: 0 | BA2000: 0 | BC2000: 0 | BE2000: 0
A7249: Livro SINAPI: Cálculos e Parâmetros | B7249: =HYPERLINK("#"&CELL("address",OFFSET(Analítico!$B$1,MATCH(95371,Analítico!$B:$B,0)-1,3)),95371) -> 0 | C7249: CURSO DE CAPACITAÇÃO PARA PEDREIRO (ENCARGOS COMPLEMENTARES) - HORISTA | D7249: H | E7249: 0.23 | F7249: 0 | G7249: 0.19 | H7249: 0 | I7249: 0.21 | J7249: 0 | K7249: 0.21 | L7249: 0 | M7249: 0.23 | N7249: 0 | O7249: 0.21 | P7249: 0 | Q7249: 0.23 | R7249: 0 | S7249: 0.21 | T7249: 0 | U7249: 0.24 | V7249: 0 | W7249: 0.21 | X7249: 0 | Y7249: 0.25 | Z7249: 0 | AA7249: 0.2 | AB7249: 0 | AC7249: 0.23 | AD7249: 0 | AE7249: 0.21 | AF7249: 0 | AG7249: 0.2 | AH7249: 0 | AI7249: 0.22 | AJ7249: 0 | AK7249: 0.21 | AL7249: 0 | AM7249: 0.28 | AN7249: 0 | AO7249: 0.3 | AP7249: 0 | AQ7249: 0.19 | AR7249: 0 | AS7249: 0.22 | AT7249: 0 | AU7249: 0.25 | AV7249: 0 | AW7249: 0.22 | AX7249: 0 | AY7249: 0.3 | AZ7249: 0 | BA7249: 0.2 | BB7249: 0 | BC7249: 0.25 | BD7249: 0 | BE7249: 0.2 | BF7249: 0
A7260: Livro SINAPI: Cálculos e Parâmetros | B7260: =HYPERLINK("#"&CELL("address",OFFSET(Analítico!$B$1,MATCH(95377,Analítico!$B:$B,0)-1,3)),95377) -> 0 | C7260: CURSO DE CAPACITAÇÃO PARA SERRALHEIRO (ENCARGOS COMPLEMENTARES) - HORISTA | D7260: H | E7260: 0.12 | F7260: 0 | G7260: 0.11 | H7260: 0 | I7260: 0.14 | J7260: 0 | K7260: 0.11 | L7260: 0 | M7260: 0.12 | N7260: 0 | O7260: 0.11 | P7260: 0 | Q7260: 0.12 | R7260: 0 | S7260: 0.13 | T7260: 0 | U7260: 0.13 | V7260: 0 | W7260: 0.11 | X7260: 0 | Y7260: 0.13 | Z7260: 0 | AA7260: 0.11 | AB7260: 0 | AC7260: 0.12 | AD7260: 0 | AE7260: 0.11 | AF7260: 0 | AG7260: 0.11 | AH7260: 0 | AI7260: 0.12 | AJ7260: 0 | AK7260: 0.11 | AL7260: 0 | AM7260: 0.15 | AN7260: 0 | AO7260: 0.16 | AP7260: 0 | AQ7260: 0.1 | AR7260: 0 | AS7260: 0.12 | AT7260: 0 | AU7260: 0.13 | AV7260: 0 | AW7260: 0.12 | AX7260: 0 | AY7260: 0.16 | AZ7260: 0 | BA7260: 0.11 | BB7260: 0 | BC7260: 0.14 | BD7260: 0 | BE7260: 0.11 | BF7260: 0
A7262: Livro SINAPI: Cálculos e Parâmetros | B7262: =HYPERLINK("#"&CELL("address",OFFSET(Analítico!$B$1,MATCH(95378,Analítico!$B:$B,0)-1,3)),95378) -> 0 | C7262: CURSO DE CAPACITAÇÃO PARA SERVENTE (ENCARGOS COMPLEMENTARES) - HORISTA | D7262: H | E7262: 0.16 | F7262: 0 | G7262: 0.15 | H7262: 0 | I7262: 0.15 | J7262: 0 | K7262: 0.15 | L7262: 0 | M7262: 0.15 | N7262: 0 | O7262: 0.15 | P7262: 0 | Q7262: 0.15 | R7262: 0 | S7262: 0.16 | T7262: 0 | U7262: 0.15 | V7262: 0 | W7262: 0.15 | X7262: 0 | Y7262: 0.17 | Z7262: 0 | AA7262: 0.15 | AB7262: 0 | AC7262: 0.17 | AD7262: 0 | AE7262: 0.15 | AF7262: 0 | AG7262: 0.15 | AH7262: 0 | AI7262: 0.16 | AJ7262: 0 | AK7262: 0.15 | AL7262: 0 | AM7262: 0.2 | AN7262: 0 | AO7262: 0.21 | AP7262: 0 | AQ7262: 0.15 | AR7262: 0 | AS7262: 0.18 | AT7262: 0 | AU7262: 0.15 | AV7262: 0 | AW7262: 0.17 | AX7262: 0 | AY7262: 0.2 | AZ7262: 0 | BA7262: 0.15 | BB7262: 0 | BC7262: 0.21 | BD7262: 0 | BE7262: 0.15 | BF7262: 0
A7377: Livro SINAPI: Cálculos e Parâmetros | B7377: =HYPERLINK("#"&CELL("address",OFFSET(Analítico!$B$1,MATCH(88309,Analítico!$B:$B,0)-1,3)),88309) -> 0 | C7377: PEDREIRO COM ENCARGOS COMPLEMENTARES | D7377: H | E7377: 18.49 | F7377: 0 | G7377: 16.29 | H7377: 0 | I7377: 21.01 | J7377: 0 | K7377: 14.86 | L7377: 0 | M7377: 20.87 | N7377: 0 | O7377: 19.28 | P7377: 0 | Q7377: 20.45 | R7377: 0 | S7377: 22.31 | T7377: 0 | U7377: 19.39 | V7377: 0 | W7377: 16.38 | X7377: 0 | Y7377: 19.43 | Z7377: 0 | AA7377: 16.85 | AB7377: 0 | AC7377: 18.87 | AD7377: 0 | AE7377: 20.57 | AF7377: 0 | AG7377: 16.58 | AH7377: 0 | AI7377: 17.7 | AJ7377: 0 | AK7377: 17.62 | AL7377: 0 | AM7377: 24.3 | AN7377: 0 | AO7377: 24.78 | AP7377: 0 | AQ7377: 18.57 | AR7377: 0 | AS7377: 18.55 | AT7377: 0 | AU7377: 20.36 | AV7377: 0 | AW7377: 17.6 | AX7377: 0 | AY7377: 19.57 | AZ7377: 0 | BA7377: 16.85 | BB7377: 0 | BC7377: 21.65 | BD7377: 0 | BE7377: 17.32 | BF7377: 0
A7388: Livro SINAPI: Cálculos e Parâmetros | B7388: =HYPERLINK("#"&CELL("address",OFFSET(Analítico!$B$1,MATCH(88315,Analítico!$B:$B,0)-1,3)),88315) -> 0 | C7388: SERRALHEIRO COM ENCARGOS COMPLEMENTARES | D7388: H | E7388: 18.38 | F7388: 0 | G7388: 17.14 | H7388: 0 | I7388: 23.4 | J7388: 0 | K7388: 14.76 | L7388: 0 | M7388: 20.76 | N7388: 0 | O7388: 19.18 | P7388: 0 | Q7388: 20.34 | R7388: 0 | S7388: 24.02 | T7388: 0 | U7388: 19.28 | V7388: 0 | W7388: 16.28 | X7388: 0 | Y7388: 19.31 | Z7388: 0 | AA7388: 16.99 | AB7388: 0 | AC7388: 18.76 | AD7388: 0 | AE7388: 20.47 | AF7388: 0 | AG7388: 16.49 | AH7388: 0 | AI7388: 17.6 | AJ7388: 0 | AK7388: 17.52 | AL7388: 0 | AM7388: 24.17 | AN7388: 0 | AO7388: 24.64 | AP7388: 0 | AQ7388: 18.48 | AR7388: 0 | AS7388: 18.45 | AT7388: 0 | AU7388: 20.24 | AV7388: 0 | AW7388: 17.5 | AX7388: 0 | AY7388: 19.43 | AZ7388: 0 | BA7388: 16.76 | BB7388: 0 | BC7388: 21.86 | BD7388: 0 | BE7388: 17.23 | BF7388: 0
A7390: Livro SINAPI: Cálculos e Parâmetros | B7390: =HYPERLINK("#"&CELL("address",OFFSET(Analítico!$B$1,MATCH(88316,Analítico!$B:$B,0)-1,3)),88316) -> 0 | C7390: SERVENTE COM ENCARGOS COMPLEMENTARES | D7390: H | E7390: 15.05 | F7390: 0 | G7390: 14.19 | H7390: 0 | I7390: 18.38 | J7390: 0 | K7390: 12.3 | L7390: 0 | M7390: 16.95 | N7390: 0 | O7390: 16.49 | P7390: 0 | Q7390: 16.73 | R7390: 0 | S7390: 19.74 | T7390: 0 | U7390: 15.1 | V7390: 0 | W7390: 13.66 | X7390: 0 | Y7390: 15.36 | Z7390: 0 | AA7390: 14.06 | AB7390: 0 | AC7390: 15.98 | AD7390: 0 | AE7390: 17.89 | AF7390: 0 | AG7390: 14.19 | AH7390: 0 | AI7390: 15.01 | AJ7390: 0 | AK7390: 15 | AL7390: 0 | AM7390: 20.18 | AN7390: 0 | AO7390: 20.52 | AP7390: 0 | AQ7390: 16.77 | AR7390: 0 | AS7390: 16.49 | AT7390: 0 | AU7390: 15.9 | AV7390: 0 | AW7390: 15.19 | AX7390: 0 | AY7390: 14.99 | AZ7390: 0 | BA7390: 14.44 | BB7390: 0 | BC7390: 19.41 | BD7390: 0 | BE7390: 14.67 | BF7390: 0

Sheet Analítico
A1: SINAPI - Sistema Nacional de Pesquisa de Custos e Índices da Construção Civil
A2: RELATÓRIO ANALÍTICO DE COMPOSIÇÕES
A3: Mês de Referência: | B3: 01/2026 | D3: Situações
A4: Data de emissão: | B4: 23/03/2026 | D4: COM PREÇO | E4: Insumos com preço coletado ou obtidos por aplicação de coeficiente em pelo menos uma UF.
D5: SEM PREÇO | E5: Insumos necessários como item, mas ainda não participam do processo de coleta preços (não aparecem em outros relatórios).
D6: COM CUSTO | E6: Composições com custo calculado, com todos seus itens em situação COM CUSTO ou COM PREÇO.
D7: SEM CUSTO | E7: Composições sem custo calculado pela falta de custo/preço de pelo menos um de seus itens.
D8: EM ESTUDO | E8: Composições necessárias como item, porém atualmente em estudo (não aparecem em outros relatórios).
A10: Grupo | B10: Código da Composição | C10: Tipo Item | D10: Código do Item | E10: Descrição | F10: Unidade | G10: Coeficiente | H10: Situação
A11: Acessibilidade | B11: 104658 | E11: PISO PODOTÁTIL DE ALERTA OU DIRECIONAL, DE CONCRETO, ASSENTADO SOBRE ARGAMASSA. AF_03/2024 | F11: M2 | H11: COM CUSTO
A12: Acessibilidade | B12: 104658 | C12: COMPOSICAO | D12: 88316 | E12: SERVENTE COM ENCARGOS COMPLEMENTARES | F12: H | G12: 1.279 | H12: COM CUSTO
A13: Acessibilidade | B13: 104658 | C13: COMPOSICAO | D13: 88309 | E13: PEDREIRO COM ENCARGOS COMPLEMENTARES | F13: H | G13: 0.639 | H13: COM CUSTO
A14: Acessibilidade | B14: 104658 | C14: INSUMO | D14: 36178 | E14: PISO TATIL / PODOTATIL, LADRILHO HIDRAULICO/CONCRETO, *40 X 40* CM, E= 2,5* CM, PADRAO TATIL ALERTA OU DIRECIONAL, COR NATURAL | F14: UN | G14: 6.4375 | H14: COM PREÇO
A15: Acessibilidade | B15: 104658 | C15: INSUMO | D15: 34357 | E15: REJUNTE CIMENTICIO, QUALQUER COR | F15: KG | G15: 0.24 | H15: COM PREÇO
A16: Acessibilidade | B16: 104658 | C16: INSUMO | D16: 34353 | E16: ARGAMASSA COLANTE AC II | F16: KG | G16: 8.62 | H16: COM PREÇO
A713: Argamassas | B713: 87398 | E713: ARGAMASSA INDUSTRIALIZADA MULTIUSO PARA REVESTIMENTOS E ASSENTAMENTO DA ALVENARIA, PREPARO MANUAL. AF_08/2019 | F713: M3 | H713: COM CUSTO
A714: Argamassas | B714: 87398 | C714: COMPOSICAO | D714: 88316 | E714: SERVENTE COM ENCARGOS COMPLEMENTARES | F714: H | G714: 12.59 | H714: COM CUSTO
A715: Argamassas | B715: 87398 | C715: INSUMO | D715: 371 | E715: ARGAMASSA INDUSTRIALIZADA MULTIUSO, PARA REVESTIMENTO INTERNO E EXTERNO E ASSENTAMENTO DE BLOCOS DIVERSOS | F715: KG | G715: 1890 | H715: COM PREÇO
A8227: Brises | B8227: 104943 | E8227: FORNECIMENTO E INSTALAÇÃO DE CONJUNTO DE BRISE EM REQUADRO DE ALUMÍNIO DESLIZANTE, COM PERFIS INTERNOS TUBULARES FIXOS, COM PINTURA ELETROSTÁTICA BRANCA, ACABAMENTO, 150 CM X 265 CM. AF_03/2024 | F8227: M2 | H8227: SEM CUSTO
A8228: Brises | B8228: 104943 | C8228: COMPOSICAO | D8228: 88315 | E8228: SERRALHEIRO COM ENCARGOS COMPLEMENTARES | F8228: H | G8228: 1.556 | H8228: COM CUSTO
A8229: Brises | B8229: 104943 | C8229: INSUMO | D8229: 45098 | E8229: CONJUNTO DE BRISE / VENEZIANA EM REQUADRO DE ALUMINIO DESLIZANTE / DE CORRER PARA FACHADA, COM MARCO 150 CM X 265 CM, PAINEIS EM PERFIS FIXOS TUBULARES 25 MM X 50 MM, ESPACAMENTO 79 MM, TRILHO INTERNO SIMPLES, PINTURA ELETROSTATICA BRANCA, ACABAMENTO LISO, INCLUI ACESSORIOS DE INSTALACAO (PARAFUSOS E BUCHAS), NAO INCLUI INSTALACAO | F8229: M2 | G8229: 1 | H8229: SEM PREÇO
A11336: Custos Horários Produtivo e Improdutivo dos Equipamentos | B11336: 102953 | E11336: BETONEIRA CAPACIDADE NOMINAL DE 250 L, CAPACIDADE DE MISTURA DE 175 L, MOTOR ELÉTRICO MONOFÁSICO POTÊNCIA 1CV - CHI DIURNO. AF_05/2023 | F11336: CHI | H11336: SEM CUSTO
A11337: Custos Horários Produtivo e Improdutivo dos Equipamentos | B11337: 102953 | C11337: COMPOSICAO | D11337: 102949 | E11337: BETONEIRA CAPACIDADE NOMINAL DE 250 L, CAPACIDADE DE MISTURA DE 175 L, MOTOR ELÉTRICO MONOFÁSICO POTÊNCIA 1CV - JUROS. AF_05/2023 | F11337: H | G11337: 1 | H11337: SEM CUSTO
A11338: Custos Horários Produtivo e Improdutivo dos Equipamentos | B11338: 102953 | C11338: COMPOSICAO | D11338: 102948 | E11338: BETONEIRA CAPACIDADE NOMINAL DE 250 L, CAPACIDADE DE MISTURA DE 175 L, MOTOR ELÉTRICO MONOFÁSICO POTÊNCIA 1CV - DEPRECIAÇÃO. AF_05/2023 | F11338: H | G11338: 1 | H11338: SEM CUSTO
A13601: Depreciação, Juros, Impostos e Seguros, Manutenção e Materiais na Operação dos Equipamentos | B13601: 92715 | E13601: APARELHO PARA CORTE E SOLDA OXI-ACETILENO SOBRE RODAS, INCLUSIVE CILINDROS E MAÇARICOS - MATERIAIS NA OPERAÇÃO. AF_05/2023 | F13601: H | H13601: COM CUSTO
A13602: Depreciação, Juros, Impostos e Seguros, Manutenção e Materiais na Operação dos Equipamentos | B13602: 92715 | C13602: INSUMO | D13602: 2 | E13602: OXIGENIO - RECARGA DE GAS PARA CILINDRO (NAO INCLUI TROCA/MANUTENCAO DO CILINDRO) | F13602: M3 | G13602: 2.75 | H13602: COM PREÇO
A13603: Depreciação, Juros, Impostos e Seguros, Manutenção e Materiais na Operação dos Equipamentos | B13603: 92715 | C13603: INSUMO | D13603: 1 | E13603: ACETILENO - RECARGA DE GAS PARA CILINDRO (NAO INCLUI TROCA/MANUTENCAO DO CILINDRO) | F13603: KG | G13603: 0.44051 | H13603: COM PREÇO
A13642: Depreciação, Juros, Impostos e Seguros, Manutenção e Materiais na Operação dos Equipamentos | B13642: 102948 | E13642: BETONEIRA CAPACIDADE NOMINAL DE 250 L, CAPACIDADE DE MISTURA DE 175 L, MOTOR ELÉTRICO MONOFÁSICO POTÊNCIA 1CV - DEPRECIAÇÃO. AF_05/2023 | F13642: H | H13642: SEM CUSTO
A13643: Depreciação, Juros, Impostos e Seguros, Manutenção e Materiais na Operação dos Equipamentos | B13643: 102948 | C13643: INSUMO | D13643: 44008 | E13643: BETONEIRA, CAPACIDADE NOMINAL 250 L, CAPACIDADE DE MISTURA *200* L, MOTOR ELETRICO MONOFASICO, POTENCIA 1CV, SEM CARREGADOR | F13643: UN | G13643: 6.4e-05 | H13643: SEM PREÇO
A13644: Depreciação, Juros, Impostos e Seguros, Manutenção e Materiais na Operação dos Equipamentos | B13644: 102949 | E13644: BETONEIRA CAPACIDADE NOMINAL DE 250 L, CAPACIDADE DE MISTURA DE 175 L, MOTOR ELÉTRICO MONOFÁSICO POTÊNCIA 1CV - JUROS. AF_05/2023 | F13644: H | H13644: SEM CUSTO
A13645: Depreciação, Juros, Impostos e Seguros, Manutenção e Materiais na Operação dos Equipamentos | B13645: 102949 | C13645: INSUMO | D13645: 44008 | E13645: BETONEIRA, CAPACIDADE NOMINAL 250 L, CAPACIDADE DE MISTURA *200* L, MOTOR ELETRICO MONOFASICO, POTENCIA 1CV, SEM CARREGADOR | F13645: UN | G13645: 1.48e-05 | H13645: SEM PREÇO
A44554: Livro SINAPI: Cálculos e Parâmetros | B44554: 95371 | E44554: CURSO DE CAPACITAÇÃO PARA PEDREIRO (ENCARGOS COMPLEMENTARES) - HORISTA | F44554: H | H44554: COM CUSTO
A44555: Livro SINAPI: Cálculos e Parâmetros | B44555: 95371 | C44555: INSUMO | D44555: 4750 | E44555: PEDREIRO (HORISTA) | F44555: H | G44555: 0.0212 | H44555: COM PREÇO
A44576: Livro SINAPI: Cálculos e Parâmetros | B44576: 95377 | E44576: CURSO DE CAPACITAÇÃO PARA SERRALHEIRO (ENCARGOS COMPLEMENTARES) - HORISTA | F44576: H | H44576: COM CUSTO
A44577: Livro SINAPI: Cálculos e Parâmetros | B44577: 95377 | C44577: INSUMO | D44577: 6110 | E44577: SERRALHEIRO (HORISTA) | F44577: H | G44577: 0.01154 | H44577: COM PREÇO
A44580: Livro SINAPI: Cálculos e Parâmetros | B44580: 95378 | E44580: CURSO DE CAPACITAÇÃO PARA SERVENTE (ENCARGOS COMPLEMENTARES) - HORISTA | F44580: H | H44580: COM CUSTO
A44581: Livro SINAPI: Cálculos e Parâmetros | B44581: 95378 | C44581: INSUMO | D44581: 6111 | E44581: SERVENTE DE OBRAS (HORISTA) | F44581: H | G44581: 0.0212 | H44581: COM PREÇO
A45403: Livro SINAPI: Cálculos e Parâmetros | B45403: 88309 | E45403: PEDREIRO COM ENCARGOS COMPLEMENTARES | F45403: H | H45403: COM CUSTO
A45404: Livro SINAPI: Cálculos e Parâmetros | B45404: 88309 | C45404: COMPOSICAO | D45404: 95371 | E45404: CURSO DE CAPACITAÇÃO PARA PEDREIRO (ENCARGOS COMPLEMENTARES) - HORISTA | F45404: H | G45404: 1 | H45404: COM CUSTO
A45405: Livro SINAPI: Cálculos e Parâmetros | B45405: 88309 | C45405: INSUMO | D45405: 43489 | E45405: EPI - FAMILIA PEDREIRO - HORISTA (ENCARGOS COMPLEMENTARES - COLETADO CAIXA) | F45405: H | G45405: 1 | H45405: COM PREÇO
A45406: Livro SINAPI: Cálculos e Parâmetros | B45406: 88309 | C45406: INSUMO | D45406: 43465 | E45406: FERRAMENTAS - FAMILIA PEDREIRO - HORISTA (ENCARGOS COMPLEMENTARES - COLETADO CAIXA) | F45406: H | G45406: 1 | H45406: COM PREÇO
A45407: Livro SINAPI: Cálculos e Parâmetros | B45407: 88309 | C45407: INSUMO | D45407: 37373 | E45407: SEGURO - HORISTA (COLETADO CAIXA - ENCARGOS COMPLEMENTARES) | F45407: H | G45407: 1 | H45407: COM PREÇO
A45408: Livro SINAPI: Cálculos e Parâmetros | B45408: 88309 | C45408: INSUMO | D45408: 37372 | E45408: EXAMES - HORISTA (COLETADO CAIXA - ENCARGOS COMPLEMENTARES) | F45408: H | G45408: 1 | H45408: COM PREÇO
A45409: Livro SINAPI: Cálculos e Parâmetros | B45409: 88309 | C45409: INSUMO | D45409: 37371 | E45409: TRANSPORTE - HORISTA (COLETADO CAIXA - ENCARGOS COMPLEMENTARES) | F45409: H | G45409: 1 | H45409: COM PREÇO
A45410: Livro SINAPI: Cálculos e Parâmetros | B45410: 88309 | C45410: INSUMO | D45410: 37370 | E45410: ALIMENTACAO - HORISTA (COLETADO CAIXA - ENCARGOS COMPLEMENTARES) | F45410: H | G45410: 1 | H45410: COM PREÇO
A45411: Livro SINAPI: Cálculos e Parâmetros | B45411: 88309 | C45411: INSUMO | D45411: 4750 | E45411: PEDREIRO (HORISTA) | F45411: H | G45411: 1 | H45411: COM PREÇO
A45497: Livro SINAPI: Cálculos e Parâmetros | B45497: 88315 | E45497: SERRALHEIRO COM ENCARGOS COMPLEMENTARES | F45497: H | H45497: COM CUSTO
A45498: Livro SINAPI: Cálculos e Parâmetros | B45498: 88315 | C45498: COMPOSICAO | D45498: 95377 | E45498: CURSO DE CAPACITAÇÃO PARA SERRALHEIRO (ENCARGOS COMPLEMENTARES) - HORISTA | F45498: H | G45498: 1 | H45498: COM CUSTO
A45499: Livro SINAPI: Cálculos e Parâmetros | B45499: 88315 | C45499: INSUMO | D45499: 43489 | E45499: EPI - FAMILIA PEDREIRO - HORISTA (ENCARGOS COMPLEMENTARES - COLETADO CAIXA) | F45499: H | G45499: 1 | H45499: COM PREÇO
A45500: Livro SINAPI: Cálculos e Parâmetros | B45500: 88315 | C45500: INSUMO | D45500: 43465 | E45500: FERRAMENTAS - FAMILIA PEDREIRO - HORISTA (ENCARGOS COMPLEMENTARES - COLETADO CAIXA) | F45500: H | G45500: 1 | H45500: COM PREÇO
A45501: Livro SINAPI: Cálculos e Parâmetros | B45501: 88315 | C45501: INSUMO | D45501: 37373 | E45501: SEGURO - HORISTA (COLETADO CAIXA - ENCARGOS COMPLEMENTARES) | F45501: H | G45501: 1 | H45501: COM PREÇO
A45502: Livro SINAPI: Cálculos e Parâmetros | B45502: 88315 | C45502: INSUMO | D45502: 37372 | E45502: EXAMES - HORISTA (COLETADO CAIXA - ENCARGOS COMPLEMENTARES) | F45502: H | G45502: 1 | H45502: COM PREÇO
A45503: Livro SINAPI: Cálculos e Parâmetros | B45503: 88315 | C45503: INSUMO | D45503: 37371 | E45503: TRANSPORTE - HORISTA (COLETADO CAIXA - ENCARGOS COMPLEMENTARES) | F45503: H | G45503: 1 | H45503: COM PREÇO
A45504: Livro SINAPI: Cálculos e Parâmetros | B45504: 88315 | C45504: INSUMO | D45504: 37370 | E45504: ALIMENTACAO - HORISTA (COLETADO CAIXA - ENCARGOS COMPLEMENTARES) | F45504: H | G45504: 1 | H45504: COM PREÇO
A45505: Livro SINAPI: Cálculos e Parâmetros | B45505: 88315 | C45505: INSUMO | D45505: 6110 | E45505: SERRALHEIRO (HORISTA) | F45505: H | G45505: 1 | H45505: COM PREÇO
A45514: Livro SINAPI: Cálculos e Parâmetros | B45514: 88316 | E45514: SERVENTE COM ENCARGOS COMPLEMENTARES | F45514: H | H45514: COM CUSTO
A45515: Livro SINAPI: Cálculos e Parâmetros | B45515: 88316 | C45515: COMPOSICAO | D45515: 95378 | E45515: CURSO DE CAPACITAÇÃO PARA SERVENTE (ENCARGOS COMPLEMENTARES) - HORISTA | F45515: H | G45515: 1 | H45515: COM CUSTO
A45516: Livro SINAPI: Cálculos e Parâmetros | B45516: 88316 | C45516: INSUMO | D45516: 43491 | E45516: EPI - FAMILIA SERVENTE - HORISTA (ENCARGOS COMPLEMENTARES - COLETADO CAIXA) | F45516: H | G45516: 1 | H45516: COM PREÇO
A45517: Livro SINAPI: Cálculos e Parâmetros | B45517: 88316 | C45517: INSUMO | D45517: 43467 | E45517: FERRAMENTAS - FAMILIA SERVENTE - HORISTA (ENCARGOS COMPLEMENTARES - COLETADO CAIXA) | F45517: H | G45517: 1 | H45517: COM PREÇO
A45518: Livro SINAPI: Cálculos e Parâmetros | B45518: 88316 | C45518: INSUMO | D45518: 37373 | E45518: SEGURO - HORISTA (COLETADO CAIXA - ENCARGOS COMPLEMENTARES) | F45518: H | G45518: 1 | H45518: COM PREÇO
A45519: Livro SINAPI: Cálculos e Parâmetros | B45519: 88316 | C45519: INSUMO | D45519: 37372 | E45519: EXAMES - HORISTA (COLETADO CAIXA - ENCARGOS COMPLEMENTARES) | F45519: H | G45519: 1 | H45519: COM PREÇO
A45520: Livro SINAPI: Cálculos e Parâmetros | B45520: 88316 | C45520: INSUMO | D45520: 37371 | E45520: TRANSPORTE - HORISTA (COLETADO CAIXA - ENCARGOS COMPLEMENTARES) | F45520: H | G45520: 1 | H45520: COM PREÇO
A45521: Livro SINAPI: Cálculos e Parâmetros | B45521: 88316 | C45521: INSUMO | D45521: 37370 | E45521: ALIMENTACAO - HORISTA (COLETADO CAIXA - ENCARGOS COMPLEMENTARES) | F45521: H | G45521: 1 | H45521: COM PREÇO
A45522: Livro SINAPI: Cálculos e Parâmetros | B45522: 88316 | C45522: INSUMO | D45522: 6111 | E45522: SERVENTE DE OBRAS (HORISTA) | F45522: H | G45522: 1 | H45522: COM PREÇO

Sheet Analítico com Custo
A1: SINAPI - Sistema Nacional de Pesquisa de Custos e Índices da Construção Civil
A2: ANALÍTICO DE COMPOSIÇÃO COM CUSTO | I2: Funciona somente em versões do Excel que tenham disponíveis as fórmulas FILTRO, LET, PROCX
A3: Mês de Referência: | B3: 01/2026 | I3: Vide explicação das situações na aba Analítico
A4: Data de emissão: | B4: 23/03/2026
A6: Preencha abaixo:
A7: Encargos Sociais: | B7: UF: | C7: Código da Composição:
A8: SEM DESONERAÇÃO | B8: SP | C8: 95995
H9: %AS (porcentagem Atribuído São Paulo) porcentagem da composição/item que foi obtida utilizando preços de insumos de São Paulo por indisponibilidade destes no estado em questão.
A10: Tipo Item | B10: Código do Item | C10: Descrição | D10: Unidade | E10: Coeficiente | F10: Custo Unit. | G10: Custo Total | H10: %AS | I10: Situação
A11: {=_xlfn.XLOOKUP($C$8,'CSD'!$B:$B,'CSD'!$B:$B)} -> 0 | C11: {=_xlfn.XLOOKUP($C$8,'CSD'!$B:$B,'CSD'!$C:$C)} -> 0 | D11: {=_xlfn.XLOOKUP($C$8,'CSD'!$B:$B,'CSD'!$D:$D)} -> 0 | G11: {=IF($A$8="SEM DESONERAÇÃO",_xlfn.XLOOKUP($C$8,'CSD'!$B:$B,OFFSET('CSD'!$D:$D,0,MATCH($B$8,'CSD'!$E$4:$BF$4,0))), IF($A$8="COM DESONERAÇÃO",_xlfn.XLOOKUP($C$8,'CCD'!$B:$B,OFFSET('CCD'!$D:$D,0,MATCH($B$8,'CCD'!$E$4:$BF$4,0))), IF($A$8="SEM ENCARGOS SOCIAIS",_xlfn.XLOOKUP($C$8,'CSE'!$B:$B,OFFSET('CSE'!$D:$D,0,MATCH($B$8,'CSE'!$E$9:$BF$9,0))), "")))} -> 0 | H11: {=IF($A$8="SEM DESONERAÇÃO",_xlfn.XLOOKUP($C$8,'CSD'!$B:$B,OFFSET('CSD'!$D:$D,0,1+MATCH($B$8,'CSD'!$E$4:$BF$4,0))), IF($A$8="COM DESONERAÇÃO",_xlfn.XLOOKUP($C$8,'CCD'!$B:$B,OFFSET('CCD'!$D:$D,0,1+MATCH($B$8,'CCD'!$E$4:$BF$4,0))), IF($A$8="SEM ENCARGOS SOCIAIS",_xlfn.XLOOKUP($C$8,'CSE'!$B:$B,OFFSET('CSE'!$D:$D,0,1+MATCH($B$8,'CSE'!$E$9:$BF$9,0))), "")))} -> 0 | I11: {=_xlfn.XLOOKUP($C$8,'Analítico'!$B:$B,'Analítico'!$H:$H)} -> 0
A12: {=_xlfn._xlws.FILTER(Analítico!$C:$G,(Analítico!$B:$B='Analítico com Custo'!$C$8)*(Analítico!$C:$C<>0))} -> 0 | F12: {=IF($A12="","", IF(AND($A12="INSUMO",$A$8="SEM DESONERAÇÃO"),_xlfn.LET(_xlpm.linha_insumo,MATCH($B12,'ISD'!$B:$B,0),_xlpm.coluna_uf,MATCH($B$8,'ISD'!$F$4:$AF$4,0),_xlpm.coluna_sp,MATCH("SP",'ISD'!$F$4:$AF$4,0),_xlpm.preco_uf,INDEX('ISD'!$F:$AF,_xlpm.linha_insumo,_xlpm.coluna_uf),_xlpm.preco_sp,INDEX('ISD'!$F:$AF,_xlpm.linha_insumo,_xlpm.coluna_sp), _xlpm.preco_regional_as,INDEX($M:$M,MATCH($B12&"_"&$B$8,$K:$K,0)), IF(ISERROR(_xlpm.linha_insumo),0,IF(_xlpm.preco_uf<>0,_xlpm.preco_uf,IF(ISNUMBER(_xlpm.preco_regional_as),_xlpm.preco_regional_as,_xlpm.preco_sp)))), IF(AND($A12="INSUMO",$A$8="COM DESONERAÇÃO"),_xlfn.LET(_xlpm.linha_insumo,MATCH($B12,'ICD'!$B:$B,0),_xlpm.coluna_uf,MATCH($B$8,'ICD'!$F$4:$AF$4,0),_xlpm.coluna_sp,MATCH("SP",'ICD'!$F$4:$AF$4,0),_xlpm.preco_uf,INDEX('ICD'!$F:$AF,_xlpm.linha_insumo,_xlpm.coluna_uf),_xlpm.preco_sp,INDEX('ICD'!$F:$AF,_xlpm.linha_insumo,_xlpm.coluna_sp), _xlpm.preco_regional_as,INDEX($N:$N,MATCH($B12&"_"&$B$8,$K:$K,0)), IF(ISERROR(_xlpm.linha_insumo),0,IF(_xlpm.preco_uf<>0,_xlpm.preco_uf,IF(ISNUMBER(_xlpm.preco_regional_as),_xlpm.preco_regional_as,_xlpm.preco_sp)))), IF(AND($A12="INSUMO",$A$8="SEM ENCARGOS SOCIAIS"),_xlfn.LET(_xlpm.linha_insumo,MATCH($B12,'ISE'!$B:$B,0),_xlpm.coluna_uf,MATCH($B$8,'ISE'!$F$10:$AF$10,0),_xlpm.coluna_sp,MATCH("SP",'ISE'!$F$10:$AF$10,0),_xlpm.preco_uf,INDEX('ISE'!$F:$AF,_xlpm.linha_insumo,_xlpm.coluna_uf),_xlpm.preco_sp,INDEX('ISE'!$F:$AF,_xlpm.linha_insumo,_xlpm.coluna_sp), _xlpm.preco_regional_as,INDEX($L:$L,MATCH($B12&"_"&$B$8,$K:$K,0)), IF(ISERROR(_xlpm.linha_insumo),0,IF(_xlpm.preco_uf<>0,_xlpm.preco_uf,IF(ISNUMBER(_xlpm.preco_regional_as),_xlpm.preco_regional_as,_xlpm.preco_sp)))), IF(AND($A12="COMPOSICAO",$A$8="SEM DESONERAÇÃO"),_xlfn.XLOOKUP($B12,'CSD'!B:B,OFFSET('CSD'!$D:$D,0,MATCH($B$8,'CSD'!$E$4:$BF$4,0)),0), IF(AND($A12="COMPOSICAO",$A$8="COM DESONERAÇÃO"),_xlfn.XLOOKUP($B12,'CCD'!B:B,OFFSET('CCD'!$D:$D,0,MATCH($B$8,'CCD'!$E$4:$BF$4,0)),0), IF(AND($A12="COMPOSICAO",$A$8="SEM ENCARGOS SOCIAIS"),_xlfn.XLOOKUP($B12,'CSE'!B:B,OFFSET('CSE'!$D:$D,0,MATCH($B$8,'CSE'!$E$9:$BF$9,0)),0),"" )))))))} -> 0 | G12: =IF($A12="","",TRUNC(E12*F12,2)) -> 0 | H12: {=IF($A12="","", IF(AND($A12="INSUMO",$A$8="SEM DESONERAÇÃO"),_xlfn.LET(_xlpm.linha_insumo,MATCH($B12,'ISD'!$B:$B,0),_xlpm.coluna_uf,MATCH($B$8,'ISD'!$F$4:$AF$4,0),_xlpm.preco_uf,INDEX('ISD'!$F:$AF,_xlpm.linha_insumo,_xlpm.coluna_uf),IF(ISERROR(_xlpm.linha_insumo),"",IF(_xlpm.preco_uf<>0,0%,100%))), IF(AND($A12="INSUMO",$A$8="COM DESONERAÇÃO"),_xlfn.LET(_xlpm.linha_insumo,MATCH($B12,'ICD'!$B:$B,0),_xlpm.coluna_uf,MATCH($B$8,'ICD'!$F$4:$AF$4,0),_xlpm.preco_uf,INDEX('ICD'!$F:$AF,_xlpm.linha_insumo,_xlpm.coluna_uf),IF(ISERROR(_xlpm.linha_insumo),"",IF(_xlpm.preco_uf<>0,0%,100%))), IF(AND($A12="INSUMO",$A$8="SEM ENCARGOS SOCIAIS"),_xlfn.LET(_xlpm.linha_insumo,MATCH($B12,'ISE'!$B:$B,0),_xlpm.coluna_uf,MATCH($B$8,'ISE'!$F$10:$AF$10,0),_xlpm.preco_uf,INDEX('ISE'!$F:$AF,_xlpm.linha_insumo,_xlpm.coluna_uf),IF(ISERROR(_xlpm.linha_insumo),"",IF(_xlpm.preco_uf<>0,0%,100%))), IF(AND($A12="COMPOSICAO",$A$8="SEM DESONERAÇÃO"),_xlfn.XLOOKUP($B12,'CSD'!B:B,OFFSET('CSD'!$D:$D,0,1+MATCH($B$8,'CSD'!$E$4:$BF$4,0)),0), IF(AND($A12="COMPOSICAO",$A$8="COM DESONERAÇÃO"),_xlfn.XLOOKUP($B12,'CCD'!B:B,OFFSET('CCD'!$D:$D,0,1+MATCH($B$8,'CCD'!$E$4:$BF$4,0)),0), IF(AND($A12="COMPOSICAO",$A$8="SEM ENCARGOS SOCIAIS"),_xlfn.XLOOKUP($B12,'CSE'!B:B,OFFSET('CSE'!$D:$D,0,1+MATCH($B$8,'CSE'!$E$9:$BF$9,0)),0),"" )))))))} -> 0 | I12: {=_xlfn._xlws.FILTER(Analítico!$H:$H,(Analítico!$B:$B='Analítico com Custo'!$C$8)*(Analítico!$C:$C<>0))} -> 0
F13: {=IF($A13="","", IF(AND($A13="INSUMO",$A$8="SEM DESONERAÇÃO"),_xlfn.LET(_xlpm.linha_insumo,MATCH($B13,'ISD'!$B:$B,0),_xlpm.coluna_uf,MATCH($B$8,'ISD'!$F$4:$AF$4,0),_xlpm.coluna_sp,MATCH("SP",'ISD'!$F$4:$AF$4,0),_xlpm.preco_uf,INDEX('ISD'!$F:$AF,_xlpm.linha_insumo,_xlpm.coluna_uf),_xlpm.preco_sp,INDEX('ISD'!$F:$AF,_xlpm.linha_insumo,_xlpm.coluna_sp), _xlpm.preco_regional_as,INDEX($M:$M,MATCH($B13&"_"&$B$8,$K:$K,0)), IF(ISERROR(_xlpm.linha_insumo),0,IF(_xlpm.preco_uf<>0,_xlpm.preco_uf,IF(ISNUMBER(_xlpm.preco_regional_as),_xlpm.preco_regional_as,_xlpm.preco_sp)))), IF(AND($A13="INSUMO",$A$8="COM DESONERAÇÃO"),_xlfn.LET(_xlpm.linha_insumo,MATCH($B13,'ICD'!$B:$B,0),_xlpm.coluna_uf,MATCH($B$8,'ICD'!$F$4:$AF$4,0),_xlpm.coluna_sp,MATCH("SP",'ICD'!$F$4:$AF$4,0),_xlpm.preco_uf,INDEX('ICD'!$F:$AF,_xlpm.linha_insumo,_xlpm.coluna_uf),_xlpm.preco_sp,INDEX('ICD'!$F:$AF,_xlpm.linha_insumo,_xlpm.coluna_sp), _xlpm.preco_regional_as,INDEX($N:$N,MATCH($B13&"_"&$B$8,$K:$K,0)), IF(ISERROR(_xlpm.linha_insumo),0,IF(_xlpm.preco_uf<>0,_xlpm.preco_uf,IF(ISNUMBER(_xlpm.preco_regional_as),_xlpm.preco_regional_as,_xlpm.preco_sp)))), IF(AND($A13="INSUMO",$A$8="SEM ENCARGOS SOCIAIS"),_xlfn.LET(_xlpm.linha_insumo,MATCH($B13,'ISE'!$B:$B,0),_xlpm.coluna_uf,MATCH($B$8,'ISE'!$F$10:$AF$10,0),_xlpm.coluna_sp,MATCH("SP",'ISE'!$F$10:$AF$10,0),_xlpm.preco_uf,INDEX('ISE'!$F:$AF,_xlpm.linha_insumo,_xlpm.coluna_uf),_xlpm.preco_sp,INDEX('ISE'!$F:$AF,_xlpm.linha_insumo,_xlpm.coluna_sp), _xlpm.preco_regional_as,INDEX($L:$L,MATCH($B13&"_"&$B$8,$K:$K,0)), IF(ISERROR(_xlpm.linha_insumo),0,IF(_xlpm.preco_uf<>0,_xlpm.preco_uf,IF(ISNUMBER(_xlpm.preco_regional_as),_xlpm.preco_regional_as,_xlpm.preco_sp)))), IF(AND($A13="COMPOSICAO",$A$8="SEM DESONERAÇÃO"),_xlfn.XLOOKUP($B13,'CSD'!B:B,OFFSET('CSD'!$D:$D,0,MATCH($B$8,'CSD'!$E$4:$BF$4,0)),0), IF(AND($A13="COMPOSICAO",$A$8="COM DESONERAÇÃO"),_xlfn.XLOOKUP($B13,'CCD'!B:B,OFFSET('CCD'!$D:$D,0,MATCH($B$8,'CCD'!$E$4:$BF$4,0)),0), IF(AND($A13="COMPOSICAO",$A$8="SEM ENCARGOS SOCIAIS"),_xlfn.XLOOKUP($B13,'CSE'!B:B,OFFSET('CSE'!$D:$D,0,MATCH($B$8,'CSE'!$E$9:$BF$9,0)),0),"" )))))))} -> 0 | G13: =IF($A13="","",TRUNC(E13*F13,2)) -> 0 | H13: {=IF($A13="","", IF(AND($A13="INSUMO",$A$8="SEM DESONERAÇÃO"),_xlfn.LET(_xlpm.linha_insumo,MATCH($B13,'ISD'!$B:$B,0),_xlpm.coluna_uf,MATCH($B$8,'ISD'!$F$4:$AF$4,0),_xlpm.preco_uf,INDEX('ISD'!$F:$AF,_xlpm.linha_insumo,_xlpm.coluna_uf),IF(ISERROR(_xlpm.linha_insumo),"",IF(_xlpm.preco_uf<>0,0%,100%))), IF(AND($A13="INSUMO",$A$8="COM DESONERAÇÃO"),_xlfn.LET(_xlpm.linha_insumo,MATCH($B13,'ICD'!$B:$B,0),_xlpm.coluna_uf,MATCH($B$8,'ICD'!$F$4:$AF$4,0),_xlpm.preco_uf,INDEX('ICD'!$F:$AF,_xlpm.linha_insumo,_xlpm.coluna_uf),IF(ISERROR(_xlpm.linha_insumo),"",IF(_xlpm.preco_uf<>0,0%,100%))), IF(AND($A13="INSUMO",$A$8="SEM ENCARGOS SOCIAIS"),_xlfn.LET(_xlpm.linha_insumo,MATCH($B13,'ISE'!$B:$B,0),_xlpm.coluna_uf,MATCH($B$8,'ISE'!$F$10:$AF$10,0),_xlpm.preco_uf,INDEX('ISE'!$F:$AF,_xlpm.linha_insumo,_xlpm.coluna_uf),IF(ISERROR(_xlpm.linha_insumo),"",IF(_xlpm.preco_uf<>0,0%,100%))), IF(AND($A13="COMPOSICAO",$A$8="SEM DESONERAÇÃO"),_xlfn.XLOOKUP($B13,'CSD'!B:B,OFFSET('CSD'!$D:$D,0,1+MATCH($B$8,'CSD'!$E$4:$BF$4,0)),0), IF(AND($A13="COMPOSICAO",$A$8="COM DESONERAÇÃO"),_xlfn.XLOOKUP($B13,'CCD'!B:B,OFFSET('CCD'!$D:$D,0,1+MATCH($B$8,'CCD'!$E$4:$BF$4,0)),0), IF(AND($A13="COMPOSICAO",$A$8="SEM ENCARGOS SOCIAIS"),_xlfn.XLOOKUP($B13,'CSE'!B:B,OFFSET('CSE'!$D:$D,0,1+MATCH($B$8,'CSE'!$E$9:$BF$9,0)),0),"" )))))))} -> 0
F14: {=IF($A14="","", IF(AND($A14="INSUMO",$A$8="SEM DESONERAÇÃO"),_xlfn.LET(_xlpm.linha_insumo,MATCH($B14,'ISD'!$B:$B,0),_xlpm.coluna_uf,MATCH($B$8,'ISD'!$F$4:$AF$4,0),_xlpm.coluna_sp,MATCH("SP",'ISD'!$F$4:$AF$4,0),_xlpm.preco_uf,INDEX('ISD'!$F:$AF,_xlpm.linha_insumo,_xlpm.coluna_uf),_xlpm.preco_sp,INDEX('ISD'!$F:$AF,_xlpm.linha_insumo,_xlpm.coluna_sp), _xlpm.preco_regional_as,INDEX($M:$M,MATCH($B14&"_"&$B$8,$K:$K,0)), IF(ISERROR(_xlpm.linha_insumo),0,IF(_xlpm.preco_uf<>0,_xlpm.preco_uf,IF(ISNUMBER(_xlpm.preco_regional_as),_xlpm.preco_regional_as,_xlpm.preco_sp)))), IF(AND($A14="INSUMO",$A$8="COM DESONERAÇÃO"),_xlfn.LET(_xlpm.linha_insumo,MATCH($B14,'ICD'!$B:$B,0),_xlpm.coluna_uf,MATCH($B$8,'ICD'!$F$4:$AF$4,0),_xlpm.coluna_sp,MATCH("SP",'ICD'!$F$4:$AF$4,0),_xlpm.preco_uf,INDEX('ICD'!$F:$AF,_xlpm.linha_insumo,_xlpm.coluna_uf),_xlpm.preco_sp,INDEX('ICD'!$F:$AF,_xlpm.linha_insumo,_xlpm.coluna_sp), _xlpm.preco_regional_as,INDEX($N:$N,MATCH($B14&"_"&$B$8,$K:$K,0)), IF(ISERROR(_xlpm.linha_insumo),0,IF(_xlpm.preco_uf<>0,_xlpm.preco_uf,IF(ISNUMBER(_xlpm.preco_regional_as),_xlpm.preco_regional_as,_xlpm.preco_sp)))), IF(AND($A14="INSUMO",$A$8="SEM ENCARGOS SOCIAIS"),_xlfn.LET(_xlpm.linha_insumo,MATCH($B14,'ISE'!$B:$B,0),_xlpm.coluna_uf,MATCH($B$8,'ISE'!$F$10:$AF$10,0),_xlpm.coluna_sp,MATCH("SP",'ISE'!$F$10:$AF$10,0),_xlpm.preco_uf,INDEX('ISE'!$F:$AF,_xlpm.linha_insumo,_xlpm.coluna_uf),_xlpm.preco_sp,INDEX('ISE'!$F:$AF,_xlpm.linha_insumo,_xlpm.coluna_sp), _xlpm.preco_regional_as,INDEX($L:$L,MATCH($B14&"_"&$B$8,$K:$K,0)), IF(ISERROR(_xlpm.linha_insumo),0,IF(_xlpm.preco_uf<>0,_xlpm.preco_uf,IF(ISNUMBER(_xlpm.preco_regional_as),_xlpm.preco_regional_as,_xlpm.preco_sp)))), IF(AND($A14="COMPOSICAO",$A$8="SEM DESONERAÇÃO"),_xlfn.XLOOKUP($B14,'CSD'!B:B,OFFSET('CSD'!$D:$D,0,MATCH($B$8,'CSD'!$E$4:$BF$4,0)),0), IF(AND($A14="COMPOSICAO",$A$8="COM DESONERAÇÃO"),_xlfn.XLOOKUP($B14,'CCD'!B:B,OFFSET('CCD'!$D:$D,0,MATCH($B$8,'CCD'!$E$4:$BF$4,0)),0), IF(AND($A14="COMPOSICAO",$A$8="SEM ENCARGOS SOCIAIS"),_xlfn.XLOOKUP($B14,'CSE'!B:B,OFFSET('CSE'!$D:$D,0,MATCH($B$8,'CSE'!$E$9:$BF$9,0)),0),"" )))))))} -> 0 | G14: =IF($A14="","",TRUNC(E14*F14,2)) -> 0 | H14: {=IF($A14="","", IF(AND($A14="INSUMO",$A$8="SEM DESONERAÇÃO"),_xlfn.LET(_xlpm.linha_insumo,MATCH($B14,'ISD'!$B:$B,0),_xlpm.coluna_uf,MATCH($B$8,'ISD'!$F$4:$AF$4,0),_xlpm.preco_uf,INDEX('ISD'!$F:$AF,_xlpm.linha_insumo,_xlpm.coluna_uf),IF(ISERROR(_xlpm.linha_insumo),"",IF(_xlpm.preco_uf<>0,0%,100%))), IF(AND($A14="INSUMO",$A$8="COM DESONERAÇÃO"),_xlfn.LET(_xlpm.linha_insumo,MATCH($B14,'ICD'!$B:$B,0),_xlpm.coluna_uf,MATCH($B$8,'ICD'!$F$4:$AF$4,0),_xlpm.preco_uf,INDEX('ICD'!$F:$AF,_xlpm.linha_insumo,_xlpm.coluna_uf),IF(ISERROR(_xlpm.linha_insumo),"",IF(_xlpm.preco_uf<>0,0%,100%))), IF(AND($A14="INSUMO",$A$8="SEM ENCARGOS SOCIAIS"),_xlfn.LET(_xlpm.linha_insumo,MATCH($B14,'ISE'!$B:$B,0),_xlpm.coluna_uf,MATCH($B$8,'ISE'!$F$10:$AF$10,0),_xlpm.preco_uf,INDEX('ISE'!$F:$AF,_xlpm.linha_insumo,_xlpm.coluna_uf),IF(ISERROR(_xlpm.linha_insumo),"",IF(_xlpm.preco_uf<>0,0%,100%))), IF(AND($A14="COMPOSICAO",$A$8="SEM DESONERAÇÃO"),_xlfn.XLOOKUP($B14,'CSD'!B:B,OFFSET('CSD'!$D:$D,0,1+MATCH($B$8,'CSD'!$E$4:$BF$4,0)),0), IF(AND($A14="COMPOSICAO",$A$8="COM DESONERAÇÃO"),_xlfn.XLOOKUP($B14,'CCD'!B:B,OFFSET('CCD'!$D:$D,0,1+MATCH($B$8,'CCD'!$E$4:$BF$4,0)),0), IF(AND($A14="COMPOSICAO",$A$8="SEM ENCARGOS SOCIAIS"),_xlfn.XLOOKUP($B14,'CSE'!B:B,OFFSET('CSE'!$D:$D,0,1+MATCH($B$8,'CSE'!$E$9:$BF$9,0)),0),"" )))))))} -> 0
F15: {=IF($A15="","", IF(AND($A15="INSUMO",$A$8="SEM DESONERAÇÃO"),_xlfn.LET(_xlpm.linha_insumo,MATCH($B15,'ISD'!$B:$B,0),_xlpm.coluna_uf,MATCH($B$8,'ISD'!$F$4:$AF$4,0),_xlpm.coluna_sp,MATCH("SP",'ISD'!$F$4:$AF$4,0),_xlpm.preco_uf,INDEX('ISD'!$F:$AF,_xlpm.linha_insumo,_xlpm.coluna_uf),_xlpm.preco_sp,INDEX('ISD'!$F:$AF,_xlpm.linha_insumo,_xlpm.coluna_sp), _xlpm.preco_regional_as,INDEX($M:$M,MATCH($B15&"_"&$B$8,$K:$K,0)), IF(ISERROR(_xlpm.linha_insumo),0,IF(_xlpm.preco_uf<>0,_xlpm.preco_uf,IF(ISNUMBER(_xlpm.preco_regional_as),_xlpm.preco_regional_as,_xlpm.preco_sp)))), IF(AND($A15="INSUMO",$A$8="COM DESONERAÇÃO"),_xlfn.LET(_xlpm.linha_insumo,MATCH($B15,'ICD'!$B:$B,0),_xlpm.coluna_uf,MATCH($B$8,'ICD'!$F$4:$AF$4,0),_xlpm.coluna_sp,MATCH("SP",'ICD'!$F$4:$AF$4,0),_xlpm.preco_uf,INDEX('ICD'!$F:$AF,_xlpm.linha_insumo,_xlpm.coluna_uf),_xlpm.preco_sp,INDEX('ICD'!$F:$AF,_xlpm.linha_insumo,_xlpm.coluna_sp), _xlpm.preco_regional_as,INDEX($N:$N,MATCH($B15&"_"&$B$8,$K:$K,0)), IF(ISERROR(_xlpm.linha_insumo),0,IF(_xlpm.preco_uf<>0,_xlpm.preco_uf,IF(ISNUMBER(_xlpm.preco_regional_as),_xlpm.preco_regional_as,_xlpm.preco_sp)))), IF(AND($A15="INSUMO",$A$8="SEM ENCARGOS SOCIAIS"),_xlfn.LET(_xlpm.linha_insumo,MATCH($B15,'ISE'!$B:$B,0),_xlpm.coluna_uf,MATCH($B$8,'ISE'!$F$10:$AF$10,0),_xlpm.coluna_sp,MATCH("SP",'ISE'!$F$10:$AF$10,0),_xlpm.preco_uf,INDEX('ISE'!$F:$AF,_xlpm.linha_insumo,_xlpm.coluna_uf),_xlpm.preco_sp,INDEX('ISE'!$F:$AF,_xlpm.linha_insumo,_xlpm.coluna_sp), _xlpm.preco_regional_as,INDEX($L:$L,MATCH($B15&"_"&$B$8,$K:$K,0)), IF(ISERROR(_xlpm.linha_insumo),0,IF(_xlpm.preco_uf<>0,_xlpm.preco_uf,IF(ISNUMBER(_xlpm.preco_regional_as),_xlpm.preco_regional_as,_xlpm.preco_sp)))), IF(AND($A15="COMPOSICAO",$A$8="SEM DESONERAÇÃO"),_xlfn.XLOOKUP($B15,'CSD'!B:B,OFFSET('CSD'!$D:$D,0,MATCH($B$8,'CSD'!$E$4:$BF$4,0)),0), IF(AND($A15="COMPOSICAO",$A$8="COM DESONERAÇÃO"),_xlfn.XLOOKUP($B15,'CCD'!B:B,OFFSET('CCD'!$D:$D,0,MATCH($B$8,'CCD'!$E$4:$BF$4,0)),0), IF(AND($A15="COMPOSICAO",$A$8="SEM ENCARGOS SOCIAIS"),_xlfn.XLOOKUP($B15,'CSE'!B:B,OFFSET('CSE'!$D:$D,0,MATCH($B$8,'CSE'!$E$9:$BF$9,0)),0),"" )))))))} -> 0 | G15: =IF($A15="","",TRUNC(E15*F15,2)) -> 0 | H15: {=IF($A15="","", IF(AND($A15="INSUMO",$A$8="SEM DESONERAÇÃO"),_xlfn.LET(_xlpm.linha_insumo,MATCH($B15,'ISD'!$B:$B,0),_xlpm.coluna_uf,MATCH($B$8,'ISD'!$F$4:$AF$4,0),_xlpm.preco_uf,INDEX('ISD'!$F:$AF,_xlpm.linha_insumo,_xlpm.coluna_uf),IF(ISERROR(_xlpm.linha_insumo),"",IF(_xlpm.preco_uf<>0,0%,100%))), IF(AND($A15="INSUMO",$A$8="COM DESONERAÇÃO"),_xlfn.LET(_xlpm.linha_insumo,MATCH($B15,'ICD'!$B:$B,0),_xlpm.coluna_uf,MATCH($B$8,'ICD'!$F$4:$AF$4,0),_xlpm.preco_uf,INDEX('ICD'!$F:$AF,_xlpm.linha_insumo,_xlpm.coluna_uf),IF(ISERROR(_xlpm.linha_insumo),"",IF(_xlpm.preco_uf<>0,0%,100%))), IF(AND($A15="INSUMO",$A$8="SEM ENCARGOS SOCIAIS"),_xlfn.LET(_xlpm.linha_insumo,MATCH($B15,'ISE'!$B:$B,0),_xlpm.coluna_uf,MATCH($B$8,'ISE'!$F$10:$AF$10,0),_xlpm.preco_uf,INDEX('ISE'!$F:$AF,_xlpm.linha_insumo,_xlpm.coluna_uf),IF(ISERROR(_xlpm.linha_insumo),"",IF(_xlpm.preco_uf<>0,0%,100%))), IF(AND($A15="COMPOSICAO",$A$8="SEM DESONERAÇÃO"),_xlfn.XLOOKUP($B15,'CSD'!B:B,OFFSET('CSD'!$D:$D,0,1+MATCH($B$8,'CSD'!$E$4:$BF$4,0)),0), IF(AND($A15="COMPOSICAO",$A$8="COM DESONERAÇÃO"),_xlfn.XLOOKUP($B15,'CCD'!B:B,OFFSET('CCD'!$D:$D,0,1+MATCH($B$8,'CCD'!$E$4:$BF$4,0)),0), IF(AND($A15="COMPOSICAO",$A$8="SEM ENCARGOS SOCIAIS"),_xlfn.XLOOKUP($B15,'CSE'!B:B,OFFSET('CSE'!$D:$D,0,1+MATCH($B$8,'CSE'!$E$9:$BF$9,0)),0),"" )))))))} -> 0
F16: {=IF($A16="","", IF(AND($A16="INSUMO",$A$8="SEM DESONERAÇÃO"),_xlfn.LET(_xlpm.linha_insumo,MATCH($B16,'ISD'!$B:$B,0),_xlpm.coluna_uf,MATCH($B$8,'ISD'!$F$4:$AF$4,0),_xlpm.coluna_sp,MATCH("SP",'ISD'!$F$4:$AF$4,0),_xlpm.preco_uf,INDEX('ISD'!$F:$AF,_xlpm.linha_insumo,_xlpm.coluna_uf),_xlpm.preco_sp,INDEX('ISD'!$F:$AF,_xlpm.linha_insumo,_xlpm.coluna_sp), _xlpm.preco_regional_as,INDEX($M:$M,MATCH($B16&"_"&$B$8,$K:$K,0)), IF(ISERROR(_xlpm.linha_insumo),0,IF(_xlpm.preco_uf<>0,_xlpm.preco_uf,IF(ISNUMBER(_xlpm.preco_regional_as),_xlpm.preco_regional_as,_xlpm.preco_sp)))), IF(AND($A16="INSUMO",$A$8="COM DESONERAÇÃO"),_xlfn.LET(_xlpm.linha_insumo,MATCH($B16,'ICD'!$B:$B,0),_xlpm.coluna_uf,MATCH($B$8,'ICD'!$F$4:$AF$4,0),_xlpm.coluna_sp,MATCH("SP",'ICD'!$F$4:$AF$4,0),_xlpm.preco_uf,INDEX('ICD'!$F:$AF,_xlpm.linha_insumo,_xlpm.coluna_uf),_xlpm.preco_sp,INDEX('ICD'!$F:$AF,_xlpm.linha_insumo,_xlpm.coluna_sp), _xlpm.preco_regional_as,INDEX($N:$N,MATCH($B16&"_"&$B$8,$K:$K,0)), IF(ISERROR(_xlpm.linha_insumo),0,IF(_xlpm.preco_uf<>0,_xlpm.preco_uf,IF(ISNUMBER(_xlpm.preco_regional_as),_xlpm.preco_regional_as,_xlpm.preco_sp)))), IF(AND($A16="INSUMO",$A$8="SEM ENCARGOS SOCIAIS"),_xlfn.LET(_xlpm.linha_insumo,MATCH($B16,'ISE'!$B:$B,0),_xlpm.coluna_uf,MATCH($B$8,'ISE'!$F$10:$AF$10,0),_xlpm.coluna_sp,MATCH("SP",'ISE'!$F$10:$AF$10,0),_xlpm.preco_uf,INDEX('ISE'!$F:$AF,_xlpm.linha_insumo,_xlpm.coluna_uf),_xlpm.preco_sp,INDEX('ISE'!$F:$AF,_xlpm.linha_insumo,_xlpm.coluna_sp), _xlpm.preco_regional_as,INDEX($L:$L,MATCH($B16&"_"&$B$8,$K:$K,0)), IF(ISERROR(_xlpm.linha_insumo),0,IF(_xlpm.preco_uf<>0,_xlpm.preco_uf,IF(ISNUMBER(_xlpm.preco_regional_as),_xlpm.preco_regional_as,_xlpm.preco_sp)))), IF(AND($A16="COMPOSICAO",$A$8="SEM DESONERAÇÃO"),_xlfn.XLOOKUP($B16,'CSD'!B:B,OFFSET('CSD'!$D:$D,0,MATCH($B$8,'CSD'!$E$4:$BF$4,0)),0), IF(AND($A16="COMPOSICAO",$A$8="COM DESONERAÇÃO"),_xlfn.XLOOKUP($B16,'CCD'!B:B,OFFSET('CCD'!$D:$D,0,MATCH($B$8,'CCD'!$E$4:$BF$4,0)),0), IF(AND($A16="COMPOSICAO",$A$8="SEM ENCARGOS SOCIAIS"),_xlfn.XLOOKUP($B16,'CSE'!B:B,OFFSET('CSE'!$D:$D,0,MATCH($B$8,'CSE'!$E$9:$BF$9,0)),0),"" )))))))} -> 0 | G16: =IF($A16="","",TRUNC(E16*F16,2)) -> 0 | H16: {=IF($A16="","", IF(AND($A16="INSUMO",$A$8="SEM DESONERAÇÃO"),_xlfn.LET(_xlpm.linha_insumo,MATCH($B16,'ISD'!$B:$B,0),_xlpm.coluna_uf,MATCH($B$8,'ISD'!$F$4:$AF$4,0),_xlpm.preco_uf,INDEX('ISD'!$F:$AF,_xlpm.linha_insumo,_xlpm.coluna_uf),IF(ISERROR(_xlpm.linha_insumo),"",IF(_xlpm.preco_uf<>0,0%,100%))), IF(AND($A16="INSUMO",$A$8="COM DESONERAÇÃO"),_xlfn.LET(_xlpm.linha_insumo,MATCH($B16,'ICD'!$B:$B,0),_xlpm.coluna_uf,MATCH($B$8,'ICD'!$F$4:$AF$4,0),_xlpm.preco_uf,INDEX('ICD'!$F:$AF,_xlpm.linha_insumo,_xlpm.coluna_uf),IF(ISERROR(_xlpm.linha_insumo),"",IF(_xlpm.preco_uf<>0,0%,100%))), IF(AND($A16="INSUMO",$A$8="SEM ENCARGOS SOCIAIS"),_xlfn.LET(_xlpm.linha_insumo,MATCH($B16,'ISE'!$B:$B,0),_xlpm.coluna_uf,MATCH($B$8,'ISE'!$F$10:$AF$10,0),_xlpm.preco_uf,INDEX('ISE'!$F:$AF,_xlpm.linha_insumo,_xlpm.coluna_uf),IF(ISERROR(_xlpm.linha_insumo),"",IF(_xlpm.preco_uf<>0,0%,100%))), IF(AND($A16="COMPOSICAO",$A$8="SEM DESONERAÇÃO"),_xlfn.XLOOKUP($B16,'CSD'!B:B,OFFSET('CSD'!$D:$D,0,1+MATCH($B$8,'CSD'!$E$4:$BF$4,0)),0), IF(AND($A16="COMPOSICAO",$A$8="COM DESONERAÇÃO"),_xlfn.XLOOKUP($B16,'CCD'!B:B,OFFSET('CCD'!$D:$D,0,1+MATCH($B$8,'CCD'!$E$4:$BF$4,0)),0), IF(AND($A16="COMPOSICAO",$A$8="SEM ENCARGOS SOCIAIS"),_xlfn.XLOOKUP($B16,'CSE'!B:B,OFFSET('CSE'!$D:$D,0,1+MATCH($B$8,'CSE'!$E$9:$BF$9,0)),0),"" )))))))} -> 0
F17: {=IF($A17="","", IF(AND($A17="INSUMO",$A$8="SEM DESONERAÇÃO"),_xlfn.LET(_xlpm.linha_insumo,MATCH($B17,'ISD'!$B:$B,0),_xlpm.coluna_uf,MATCH($B$8,'ISD'!$F$4:$AF$4,0),_xlpm.coluna_sp,MATCH("SP",'ISD'!$F$4:$AF$4,0),_xlpm.preco_uf,INDEX('ISD'!$F:$AF,_xlpm.linha_insumo,_xlpm.coluna_uf),_xlpm.preco_sp,INDEX('ISD'!$F:$AF,_xlpm.linha_insumo,_xlpm.coluna_sp), _xlpm.preco_regional_as,INDEX($M:$M,MATCH($B17&"_"&$B$8,$K:$K,0)), IF(ISERROR(_xlpm.linha_insumo),0,IF(_xlpm.preco_uf<>0,_xlpm.preco_uf,IF(ISNUMBER(_xlpm.preco_regional_as),_xlpm.preco_regional_as,_xlpm.preco_sp)))), IF(AND($A17="INSUMO",$A$8="COM DESONERAÇÃO"),_xlfn.LET(_xlpm.linha_insumo,MATCH($B17,'ICD'!$B:$B,0),_xlpm.coluna_uf,MATCH($B$8,'ICD'!$F$4:$AF$4,0),_xlpm.coluna_sp,MATCH("SP",'ICD'!$F$4:$AF$4,0),_xlpm.preco_uf,INDEX('ICD'!$F:$AF,_xlpm.linha_insumo,_xlpm.coluna_uf),_xlpm.preco_sp,INDEX('ICD'!$F:$AF,_xlpm.linha_insumo,_xlpm.coluna_sp), _xlpm.preco_regional_as,INDEX($N:$N,MATCH($B17&"_"&$B$8,$K:$K,0)), IF(ISERROR(_xlpm.linha_insumo),0,IF(_xlpm.preco_uf<>0,_xlpm.preco_uf,IF(ISNUMBER(_xlpm.preco_regional_as),_xlpm.preco_regional_as,_xlpm.preco_sp)))), IF(AND($A17="INSUMO",$A$8="SEM ENCARGOS SOCIAIS"),_xlfn.LET(_xlpm.linha_insumo,MATCH($B17,'ISE'!$B:$B,0),_xlpm.coluna_uf,MATCH($B$8,'ISE'!$F$10:$AF$10,0),_xlpm.coluna_sp,MATCH("SP",'ISE'!$F$10:$AF$10,0),_xlpm.preco_uf,INDEX('ISE'!$F:$AF,_xlpm.linha_insumo,_xlpm.coluna_uf),_xlpm.preco_sp,INDEX('ISE'!$F:$AF,_xlpm.linha_insumo,_xlpm.coluna_sp), _xlpm.preco_regional_as,INDEX($L:$L,MATCH($B17&"_"&$B$8,$K:$K,0)), IF(ISERROR(_xlpm.linha_insumo),0,IF(_xlpm.preco_uf<>0,_xlpm.preco_uf,IF(ISNUMBER(_xlpm.preco_regional_as),_xlpm.preco_regional_as,_xlpm.preco_sp)))), IF(AND($A17="COMPOSICAO",$A$8="SEM DESONERAÇÃO"),_xlfn.XLOOKUP($B17,'CSD'!B:B,OFFSET('CSD'!$D:$D,0,MATCH($B$8,'CSD'!$E$4:$BF$4,0)),0), IF(AND($A17="COMPOSICAO",$A$8="COM DESONERAÇÃO"),_xlfn.XLOOKUP($B17,'CCD'!B:B,OFFSET('CCD'!$D:$D,0,MATCH($B$8,'CCD'!$E$4:$BF$4,0)),0), IF(AND($A17="COMPOSICAO",$A$8="SEM ENCARGOS SOCIAIS"),_xlfn.XLOOKUP($B17,'CSE'!B:B,OFFSET('CSE'!$D:$D,0,MATCH($B$8,'CSE'!$E$9:$BF$9,0)),0),"" )))))))} -> 0 | G17: =IF($A17="","",TRUNC(E17*F17,2)) -> 0 | H17: {=IF($A17="","", IF(AND($A17="INSUMO",$A$8="SEM DESONERAÇÃO"),_xlfn.LET(_xlpm.linha_insumo,MATCH($B17,'ISD'!$B:$B,0),_xlpm.coluna_uf,MATCH($B$8,'ISD'!$F$4:$AF$4,0),_xlpm.preco_uf,INDEX('ISD'!$F:$AF,_xlpm.linha_insumo,_xlpm.coluna_uf),IF(ISERROR(_xlpm.linha_insumo),"",IF(_xlpm.preco_uf<>0,0%,100%))), IF(AND($A17="INSUMO",$A$8="COM DESONERAÇÃO"),_xlfn.LET(_xlpm.linha_insumo,MATCH($B17,'ICD'!$B:$B,0),_xlpm.coluna_uf,MATCH($B$8,'ICD'!$F$4:$AF$4,0),_xlpm.preco_uf,INDEX('ICD'!$F:$AF,_xlpm.linha_insumo,_xlpm.coluna_uf),IF(ISERROR(_xlpm.linha_insumo),"",IF(_xlpm.preco_uf<>0,0%,100%))), IF(AND($A17="INSUMO",$A$8="SEM ENCARGOS SOCIAIS"),_xlfn.LET(_xlpm.linha_insumo,MATCH($B17,'ISE'!$B:$B,0),_xlpm.coluna_uf,MATCH($B$8,'ISE'!$F$10:$AF$10,0),_xlpm.preco_uf,INDEX('ISE'!$F:$AF,_xlpm.linha_insumo,_xlpm.coluna_uf),IF(ISERROR(_xlpm.linha_insumo),"",IF(_xlpm.preco_uf<>0,0%,100%))), IF(AND($A17="COMPOSICAO",$A$8="SEM DESONERAÇÃO"),_xlfn.XLOOKUP($B17,'CSD'!B:B,OFFSET('CSD'!$D:$D,0,1+MATCH($B$8,'CSD'!$E$4:$BF$4,0)),0), IF(AND($A17="COMPOSICAO",$A$8="COM DESONERAÇÃO"),_xlfn.XLOOKUP($B17,'CCD'!B:B,OFFSET('CCD'!$D:$D,0,1+MATCH($B$8,'CCD'!$E$4:$BF$4,0)),0), IF(AND($A17="COMPOSICAO",$A$8="SEM ENCARGOS SOCIAIS"),_xlfn.XLOOKUP($B17,'CSE'!B:B,OFFSET('CSE'!$D:$D,0,1+MATCH($B$8,'CSE'!$E$9:$BF$9,0)),0),"" )))))))} -> 0
F18: {=IF($A18="","", IF(AND($A18="INSUMO",$A$8="SEM DESONERAÇÃO"),_xlfn.LET(_xlpm.linha_insumo,MATCH($B18,'ISD'!$B:$B,0),_xlpm.coluna_uf,MATCH($B$8,'ISD'!$F$4:$AF$4,0),_xlpm.coluna_sp,MATCH("SP",'ISD'!$F$4:$AF$4,0),_xlpm.preco_uf,INDEX('ISD'!$F:$AF,_xlpm.linha_insumo,_xlpm.coluna_uf),_xlpm.preco_sp,INDEX('ISD'!$F:$AF,_xlpm.linha_insumo,_xlpm.coluna_sp), _xlpm.preco_regional_as,INDEX($M:$M,MATCH($B18&"_"&$B$8,$K:$K,0)), IF(ISERROR(_xlpm.linha_insumo),0,IF(_xlpm.preco_uf<>0,_xlpm.preco_uf,IF(ISNUMBER(_xlpm.preco_regional_as),_xlpm.preco_regional_as,_xlpm.preco_sp)))), IF(AND($A18="INSUMO",$A$8="COM DESONERAÇÃO"),_xlfn.LET(_xlpm.linha_insumo,MATCH($B18,'ICD'!$B:$B,0),_xlpm.coluna_uf,MATCH($B$8,'ICD'!$F$4:$AF$4,0),_xlpm.coluna_sp,MATCH("SP",'ICD'!$F$4:$AF$4,0),_xlpm.preco_uf,INDEX('ICD'!$F:$AF,_xlpm.linha_insumo,_xlpm.coluna_uf),_xlpm.preco_sp,INDEX('ICD'!$F:$AF,_xlpm.linha_insumo,_xlpm.coluna_sp), _xlpm.preco_regional_as,INDEX($N:$N,MATCH($B18&"_"&$B$8,$K:$K,0)), IF(ISERROR(_xlpm.linha_insumo),0,IF(_xlpm.preco_uf<>0,_xlpm.preco_uf,IF(ISNUMBER(_xlpm.preco_regional_as),_xlpm.preco_regional_as,_xlpm.preco_sp)))), IF(AND($A18="INSUMO",$A$8="SEM ENCARGOS SOCIAIS"),_xlfn.LET(_xlpm.linha_insumo,MATCH($B18,'ISE'!$B:$B,0),_xlpm.coluna_uf,MATCH($B$8,'ISE'!$F$10:$AF$10,0),_xlpm.coluna_sp,MATCH("SP",'ISE'!$F$10:$AF$10,0),_xlpm.preco_uf,INDEX('ISE'!$F:$AF,_xlpm.linha_insumo,_xlpm.coluna_uf),_xlpm.preco_sp,INDEX('ISE'!$F:$AF,_xlpm.linha_insumo,_xlpm.coluna_sp), _xlpm.preco_regional_as,INDEX($L:$L,MATCH($B18&"_"&$B$8,$K:$K,0)), IF(ISERROR(_xlpm.linha_insumo),0,IF(_xlpm.preco_uf<>0,_xlpm.preco_uf,IF(ISNUMBER(_xlpm.preco_regional_as),_xlpm.preco_regional_as,_xlpm.preco_sp)))), IF(AND($A18="COMPOSICAO",$A$8="SEM DESONERAÇÃO"),_xlfn.XLOOKUP($B18,'CSD'!B:B,OFFSET('CSD'!$D:$D,0,MATCH($B$8,'CSD'!$E$4:$BF$4,0)),0), IF(AND($A18="COMPOSICAO",$A$8="COM DESONERAÇÃO"),_xlfn.XLOOKUP($B18,'CCD'!B:B,OFFSET('CCD'!$D:$D,0,MATCH($B$8,'CCD'!$E$4:$BF$4,0)),0), IF(AND($A18="COMPOSICAO",$A$8="SEM ENCARGOS SOCIAIS"),_xlfn.XLOOKUP($B18,'CSE'!B:B,OFFSET('CSE'!$D:$D,0,MATCH($B$8,'CSE'!$E$9:$BF$9,0)),0),"" )))))))} -> 0 | G18: =IF($A18="","",TRUNC(E18*F18,2)) -> 0 | H18: {=IF($A18="","", IF(AND($A18="INSUMO",$A$8="SEM DESONERAÇÃO"),_xlfn.LET(_xlpm.linha_insumo,MATCH($B18,'ISD'!$B:$B,0),_xlpm.coluna_uf,MATCH($B$8,'ISD'!$F$4:$AF$4,0),_xlpm.preco_uf,INDEX('ISD'!$F:$AF,_xlpm.linha_insumo,_xlpm.coluna_uf),IF(ISERROR(_xlpm.linha_insumo),"",IF(_xlpm.preco_uf<>0,0%,100%))), IF(AND($A18="INSUMO",$A$8="COM DESONERAÇÃO"),_xlfn.LET(_xlpm.linha_insumo,MATCH($B18,'ICD'!$B:$B,0),_xlpm.coluna_uf,MATCH($B$8,'ICD'!$F$4:$AF$4,0),_xlpm.preco_uf,INDEX('ICD'!$F:$AF,_xlpm.linha_insumo,_xlpm.coluna_uf),IF(ISERROR(_xlpm.linha_insumo),"",IF(_xlpm.preco_uf<>0,0%,100%))), IF(AND($A18="INSUMO",$A$8="SEM ENCARGOS SOCIAIS"),_xlfn.LET(_xlpm.linha_insumo,MATCH($B18,'ISE'!$B:$B,0),_xlpm.coluna_uf,MATCH($B$8,'ISE'!$F$10:$AF$10,0),_xlpm.preco_uf,INDEX('ISE'!$F:$AF,_xlpm.linha_insumo,_xlpm.coluna_uf),IF(ISERROR(_xlpm.linha_insumo),"",IF(_xlpm.preco_uf<>0,0%,100%))), IF(AND($A18="COMPOSICAO",$A$8="SEM DESONERAÇÃO"),_xlfn.XLOOKUP($B18,'CSD'!B:B,OFFSET('CSD'!$D:$D,0,1+MATCH($B$8,'CSD'!$E$4:$BF$4,0)),0), IF(AND($A18="COMPOSICAO",$A$8="COM DESONERAÇÃO"),_xlfn.XLOOKUP($B18,'CCD'!B:B,OFFSET('CCD'!$D:$D,0,1+MATCH($B$8,'CCD'!$E$4:$BF$4,0)),0), IF(AND($A18="COMPOSICAO",$A$8="SEM ENCARGOS SOCIAIS"),_xlfn.XLOOKUP($B18,'CSE'!B:B,OFFSET('CSE'!$D:$D,0,1+MATCH($B$8,'CSE'!$E$9:$BF$9,0)),0),"" )))))))} -> 0
F19: {=IF($A19="","", IF(AND($A19="INSUMO",$A$8="SEM DESONERAÇÃO"),_xlfn.LET(_xlpm.linha_insumo,MATCH($B19,'ISD'!$B:$B,0),_xlpm.coluna_uf,MATCH($B$8,'ISD'!$F$4:$AF$4,0),_xlpm.coluna_sp,MATCH("SP",'ISD'!$F$4:$AF$4,0),_xlpm.preco_uf,INDEX('ISD'!$F:$AF,_xlpm.linha_insumo,_xlpm.coluna_uf),_xlpm.preco_sp,INDEX('ISD'!$F:$AF,_xlpm.linha_insumo,_xlpm.coluna_sp), _xlpm.preco_regional_as,INDEX($M:$M,MATCH($B19&"_"&$B$8,$K:$K,0)), IF(ISERROR(_xlpm.linha_insumo),0,IF(_xlpm.preco_uf<>0,_xlpm.preco_uf,IF(ISNUMBER(_xlpm.preco_regional_as),_xlpm.preco_regional_as,_xlpm.preco_sp)))), IF(AND($A19="INSUMO",$A$8="COM DESONERAÇÃO"),_xlfn.LET(_xlpm.linha_insumo,MATCH($B19,'ICD'!$B:$B,0),_xlpm.coluna_uf,MATCH($B$8,'ICD'!$F$4:$AF$4,0),_xlpm.coluna_sp,MATCH("SP",'ICD'!$F$4:$AF$4,0),_xlpm.preco_uf,INDEX('ICD'!$F:$AF,_xlpm.linha_insumo,_xlpm.coluna_uf),_xlpm.preco_sp,INDEX('ICD'!$F:$AF,_xlpm.linha_insumo,_xlpm.coluna_sp), _xlpm.preco_regional_as,INDEX($N:$N,MATCH($B19&"_"&$B$8,$K:$K,0)), IF(ISERROR(_xlpm.linha_insumo),0,IF(_xlpm.preco_uf<>0,_xlpm.preco_uf,IF(ISNUMBER(_xlpm.preco_regional_as),_xlpm.preco_regional_as,_xlpm.preco_sp)))), IF(AND($A19="INSUMO",$A$8="SEM ENCARGOS SOCIAIS"),_xlfn.LET(_xlpm.linha_insumo,MATCH($B19,'ISE'!$B:$B,0),_xlpm.coluna_uf,MATCH($B$8,'ISE'!$F$10:$AF$10,0),_xlpm.coluna_sp,MATCH("SP",'ISE'!$F$10:$AF$10,0),_xlpm.preco_uf,INDEX('ISE'!$F:$AF,_xlpm.linha_insumo,_xlpm.coluna_uf),_xlpm.preco_sp,INDEX('ISE'!$F:$AF,_xlpm.linha_insumo,_xlpm.coluna_sp), _xlpm.preco_regional_as,INDEX($L:$L,MATCH($B19&"_"&$B$8,$K:$K,0)), IF(ISERROR(_xlpm.linha_insumo),0,IF(_xlpm.preco_uf<>0,_xlpm.preco_uf,IF(ISNUMBER(_xlpm.preco_regional_as),_xlpm.preco_regional_as,_xlpm.preco_sp)))), IF(AND($A19="COMPOSICAO",$A$8="SEM DESONERAÇÃO"),_xlfn.XLOOKUP($B19,'CSD'!B:B,OFFSET('CSD'!$D:$D,0,MATCH($B$8,'CSD'!$E$4:$BF$4,0)),0), IF(AND($A19="COMPOSICAO",$A$8="COM DESONERAÇÃO"),_xlfn.XLOOKUP($B19,'CCD'!B:B,OFFSET('CCD'!$D:$D,0,MATCH($B$8,'CCD'!$E$4:$BF$4,0)),0), IF(AND($A19="COMPOSICAO",$A$8="SEM ENCARGOS SOCIAIS"),_xlfn.XLOOKUP($B19,'CSE'!B:B,OFFSET('CSE'!$D:$D,0,MATCH($B$8,'CSE'!$E$9:$BF$9,0)),0),"" )))))))} -> 0 | G19: =IF($A19="","",TRUNC(E19*F19,2)) -> 0 | H19: {=IF($A19="","", IF(AND($A19="INSUMO",$A$8="SEM DESONERAÇÃO"),_xlfn.LET(_xlpm.linha_insumo,MATCH($B19,'ISD'!$B:$B,0),_xlpm.coluna_uf,MATCH($B$8,'ISD'!$F$4:$AF$4,0),_xlpm.preco_uf,INDEX('ISD'!$F:$AF,_xlpm.linha_insumo,_xlpm.coluna_uf),IF(ISERROR(_xlpm.linha_insumo),"",IF(_xlpm.preco_uf<>0,0%,100%))), IF(AND($A19="INSUMO",$A$8="COM DESONERAÇÃO"),_xlfn.LET(_xlpm.linha_insumo,MATCH($B19,'ICD'!$B:$B,0),_xlpm.coluna_uf,MATCH($B$8,'ICD'!$F$4:$AF$4,0),_xlpm.preco_uf,INDEX('ICD'!$F:$AF,_xlpm.linha_insumo,_xlpm.coluna_uf),IF(ISERROR(_xlpm.linha_insumo),"",IF(_xlpm.preco_uf<>0,0%,100%))), IF(AND($A19="INSUMO",$A$8="SEM ENCARGOS SOCIAIS"),_xlfn.LET(_xlpm.linha_insumo,MATCH($B19,'ISE'!$B:$B,0),_xlpm.coluna_uf,MATCH($B$8,'ISE'!$F$10:$AF$10,0),_xlpm.preco_uf,INDEX('ISE'!$F:$AF,_xlpm.linha_insumo,_xlpm.coluna_uf),IF(ISERROR(_xlpm.linha_insumo),"",IF(_xlpm.preco_uf<>0,0%,100%))), IF(AND($A19="COMPOSICAO",$A$8="SEM DESONERAÇÃO"),_xlfn.XLOOKUP($B19,'CSD'!B:B,OFFSET('CSD'!$D:$D,0,1+MATCH($B$8,'CSD'!$E$4:$BF$4,0)),0), IF(AND($A19="COMPOSICAO",$A$8="COM DESONERAÇÃO"),_xlfn.XLOOKUP($B19,'CCD'!B:B,OFFSET('CCD'!$D:$D,0,1+MATCH($B$8,'CCD'!$E$4:$BF$4,0)),0), IF(AND($A19="COMPOSICAO",$A$8="SEM ENCARGOS SOCIAIS"),_xlfn.XLOOKUP($B19,'CSE'!B:B,OFFSET('CSE'!$D:$D,0,1+MATCH($B$8,'CSE'!$E$9:$BF$9,0)),0),"" )))))))} -> 0
F20: {=IF($A20="","", IF(AND($A20="INSUMO",$A$8="SEM DESONERAÇÃO"),_xlfn.LET(_xlpm.linha_insumo,MATCH($B20,'ISD'!$B:$B,0),_xlpm.coluna_uf,MATCH($B$8,'ISD'!$F$4:$AF$4,0),_xlpm.coluna_sp,MATCH("SP",'ISD'!$F$4:$AF$4,0),_xlpm.preco_uf,INDEX('ISD'!$F:$AF,_xlpm.linha_insumo,_xlpm.coluna_uf),_xlpm.preco_sp,INDEX('ISD'!$F:$AF,_xlpm.linha_insumo,_xlpm.coluna_sp), _xlpm.preco_regional_as,INDEX($M:$M,MATCH($B20&"_"&$B$8,$K:$K,0)), IF(ISERROR(_xlpm.linha_insumo),0,IF(_xlpm.preco_uf<>0,_xlpm.preco_uf,IF(ISNUMBER(_xlpm.preco_regional_as),_xlpm.preco_regional_as,_xlpm.preco_sp)))), IF(AND($A20="INSUMO",$A$8="COM DESONERAÇÃO"),_xlfn.LET(_xlpm.linha_insumo,MATCH($B20,'ICD'!$B:$B,0),_xlpm.coluna_uf,MATCH($B$8,'ICD'!$F$4:$AF$4,0),_xlpm.coluna_sp,MATCH("SP",'ICD'!$F$4:$AF$4,0),_xlpm.preco_uf,INDEX('ICD'!$F:$AF,_xlpm.linha_insumo,_xlpm.coluna_uf),_xlpm.preco_sp,INDEX('ICD'!$F:$AF,_xlpm.linha_insumo,_xlpm.coluna_sp), _xlpm.preco_regional_as,INDEX($N:$N,MATCH($B20&"_"&$B$8,$K:$K,0)), IF(ISERROR(_xlpm.linha_insumo),0,IF(_xlpm.preco_uf<>0,_xlpm.preco_uf,IF(ISNUMBER(_xlpm.preco_regional_as),_xlpm.preco_regional_as,_xlpm.preco_sp)))), IF(AND($A20="INSUMO",$A$8="SEM ENCARGOS SOCIAIS"),_xlfn.LET(_xlpm.linha_insumo,MATCH($B20,'ISE'!$B:$B,0),_xlpm.coluna_uf,MATCH($B$8,'ISE'!$F$10:$AF$10,0),_xlpm.coluna_sp,MATCH("SP",'ISE'!$F$10:$AF$10,0),_xlpm.preco_uf,INDEX('ISE'!$F:$AF,_xlpm.linha_insumo,_xlpm.coluna_uf),_xlpm.preco_sp,INDEX('ISE'!$F:$AF,_xlpm.linha_insumo,_xlpm.coluna_sp), _xlpm.preco_regional_as,INDEX($L:$L,MATCH($B20&"_"&$B$8,$K:$K,0)), IF(ISERROR(_xlpm.linha_insumo),0,IF(_xlpm.preco_uf<>0,_xlpm.preco_uf,IF(ISNUMBER(_xlpm.preco_regional_as),_xlpm.preco_regional_as,_xlpm.preco_sp)))), IF(AND($A20="COMPOSICAO",$A$8="SEM DESONERAÇÃO"),_xlfn.XLOOKUP($B20,'CSD'!B:B,OFFSET('CSD'!$D:$D,0,MATCH($B$8,'CSD'!$E$4:$BF$4,0)),0), IF(AND($A20="COMPOSICAO",$A$8="COM DESONERAÇÃO"),_xlfn.XLOOKUP($B20,'CCD'!B:B,OFFSET('CCD'!$D:$D,0,MATCH($B$8,'CCD'!$E$4:$BF$4,0)),0), IF(AND($A20="COMPOSICAO",$A$8="SEM ENCARGOS SOCIAIS"),_xlfn.XLOOKUP($B20,'CSE'!B:B,OFFSET('CSE'!$D:$D,0,MATCH($B$8,'CSE'!$E$9:$BF$9,0)),0),"" )))))))} -> 0 | G20: =IF($A20="","",TRUNC(E20*F20,2)) -> 0 | H20: {=IF($A20="","", IF(AND($A20="INSUMO",$A$8="SEM DESONERAÇÃO"),_xlfn.LET(_xlpm.linha_insumo,MATCH($B20,'ISD'!$B:$B,0),_xlpm.coluna_uf,MATCH($B$8,'ISD'!$F$4:$AF$4,0),_xlpm.preco_uf,INDEX('ISD'!$F:$AF,_xlpm.linha_insumo,_xlpm.coluna_uf),IF(ISERROR(_xlpm.linha_insumo),"",IF(_xlpm.preco_uf<>0,0%,100%))), IF(AND($A20="INSUMO",$A$8="COM DESONERAÇÃO"),_xlfn.LET(_xlpm.linha_insumo,MATCH($B20,'ICD'!$B:$B,0),_xlpm.coluna_uf,MATCH($B$8,'ICD'!$F$4:$AF$4,0),_xlpm.preco_uf,INDEX('ICD'!$F:$AF,_xlpm.linha_insumo,_xlpm.coluna_uf),IF(ISERROR(_xlpm.linha_insumo),"",IF(_xlpm.preco_uf<>0,0%,100%))), IF(AND($A20="INSUMO",$A$8="SEM ENCARGOS SOCIAIS"),_xlfn.LET(_xlpm.linha_insumo,MATCH($B20,'ISE'!$B:$B,0),_xlpm.coluna_uf,MATCH($B$8,'ISE'!$F$10:$AF$10,0),_xlpm.preco_uf,INDEX('ISE'!$F:$AF,_xlpm.linha_insumo,_xlpm.coluna_uf),IF(ISERROR(_xlpm.linha_insumo),"",IF(_xlpm.preco_uf<>0,0%,100%))), IF(AND($A20="COMPOSICAO",$A$8="SEM DESONERAÇÃO"),_xlfn.XLOOKUP($B20,'CSD'!B:B,OFFSET('CSD'!$D:$D,0,1+MATCH($B$8,'CSD'!$E$4:$BF$4,0)),0), IF(AND($A20="COMPOSICAO",$A$8="COM DESONERAÇÃO"),_xlfn.XLOOKUP($B20,'CCD'!B:B,OFFSET('CCD'!$D:$D,0,1+MATCH($B$8,'CCD'!$E$4:$BF$4,0)),0), IF(AND($A20="COMPOSICAO",$A$8="SEM ENCARGOS SOCIAIS"),_xlfn.XLOOKUP($B20,'CSE'!B:B,OFFSET('CSE'!$D:$D,0,1+MATCH($B$8,'CSE'!$E$9:$BF$9,0)),0),"" )))))))} -> 0
F21: {=IF($A21="","", IF(AND($A21="INSUMO",$A$8="SEM DESONERAÇÃO"),_xlfn.LET(_xlpm.linha_insumo,MATCH($B21,'ISD'!$B:$B,0),_xlpm.coluna_uf,MATCH($B$8,'ISD'!$F$4:$AF$4,0),_xlpm.coluna_sp,MATCH("SP",'ISD'!$F$4:$AF$4,0),_xlpm.preco_uf,INDEX('ISD'!$F:$AF,_xlpm.linha_insumo,_xlpm.coluna_uf),_xlpm.preco_sp,INDEX('ISD'!$F:$AF,_xlpm.linha_insumo,_xlpm.coluna_sp), _xlpm.preco_regional_as,INDEX($M:$M,MATCH($B21&"_"&$B$8,$K:$K,0)), IF(ISERROR(_xlpm.linha_insumo),0,IF(_xlpm.preco_uf<>0,_xlpm.preco_uf,IF(ISNUMBER(_xlpm.preco_regional_as),_xlpm.preco_regional_as,_xlpm.preco_sp)))), IF(AND($A21="INSUMO",$A$8="COM DESONERAÇÃO"),_xlfn.LET(_xlpm.linha_insumo,MATCH($B21,'ICD'!$B:$B,0),_xlpm.coluna_uf,MATCH($B$8,'ICD'!$F$4:$AF$4,0),_xlpm.coluna_sp,MATCH("SP",'ICD'!$F$4:$AF$4,0),_xlpm.preco_uf,INDEX('ICD'!$F:$AF,_xlpm.linha_insumo,_xlpm.coluna_uf),_xlpm.preco_sp,INDEX('ICD'!$F:$AF,_xlpm.linha_insumo,_xlpm.coluna_sp), _xlpm.preco_regional_as,INDEX($N:$N,MATCH($B21&"_"&$B$8,$K:$K,0)), IF(ISERROR(_xlpm.linha_insumo),0,IF(_xlpm.preco_uf<>0,_xlpm.preco_uf,IF(ISNUMBER(_xlpm.preco_regional_as),_xlpm.preco_regional_as,_xlpm.preco_sp)))), IF(AND($A21="INSUMO",$A$8="SEM ENCARGOS SOCIAIS"),_xlfn.LET(_xlpm.linha_insumo,MATCH($B21,'ISE'!$B:$B,0),_xlpm.coluna_uf,MATCH($B$8,'ISE'!$F$10:$AF$10,0),_xlpm.coluna_sp,MATCH("SP",'ISE'!$F$10:$AF$10,0),_xlpm.preco_uf,INDEX('ISE'!$F:$AF,_xlpm.linha_insumo,_xlpm.coluna_uf),_xlpm.preco_sp,INDEX('ISE'!$F:$AF,_xlpm.linha_insumo,_xlpm.coluna_sp), _xlpm.preco_regional_as,INDEX($L:$L,MATCH($B21&"_"&$B$8,$K:$K,0)), IF(ISERROR(_xlpm.linha_insumo),0,IF(_xlpm.preco_uf<>0,_xlpm.preco_uf,IF(ISNUMBER(_xlpm.preco_regional_as),_xlpm.preco_regional_as,_xlpm.preco_sp)))), IF(AND($A21="COMPOSICAO",$A$8="SEM DESONERAÇÃO"),_xlfn.XLOOKUP($B21,'CSD'!B:B,OFFSET('CSD'!$D:$D,0,MATCH($B$8,'CSD'!$E$4:$BF$4,0)),0), IF(AND($A21="COMPOSICAO",$A$8="COM DESONERAÇÃO"),_xlfn.XLOOKUP($B21,'CCD'!B:B,OFFSET('CCD'!$D:$D,0,MATCH($B$8,'CCD'!$E$4:$BF$4,0)),0), IF(AND($A21="COMPOSICAO",$A$8="SEM ENCARGOS SOCIAIS"),_xlfn.XLOOKUP($B21,'CSE'!B:B,OFFSET('CSE'!$D:$D,0,MATCH($B$8,'CSE'!$E$9:$BF$9,0)),0),"" )))))))} -> 0 | G21: =IF($A21="","",TRUNC(E21*F21,2)) -> 0 | H21: {=IF($A21="","", IF(AND($A21="INSUMO",$A$8="SEM DESONERAÇÃO"),_xlfn.LET(_xlpm.linha_insumo,MATCH($B21,'ISD'!$B:$B,0),_xlpm.coluna_uf,MATCH($B$8,'ISD'!$F$4:$AF$4,0),_xlpm.preco_uf,INDEX('ISD'!$F:$AF,_xlpm.linha_insumo,_xlpm.coluna_uf),IF(ISERROR(_xlpm.linha_insumo),"",IF(_xlpm.preco_uf<>0,0%,100%))), IF(AND($A21="INSUMO",$A$8="COM DESONERAÇÃO"),_xlfn.LET(_xlpm.linha_insumo,MATCH($B21,'ICD'!$B:$B,0),_xlpm.coluna_uf,MATCH($B$8,'ICD'!$F$4:$AF$4,0),_xlpm.preco_uf,INDEX('ICD'!$F:$AF,_xlpm.linha_insumo,_xlpm.coluna_uf),IF(ISERROR(_xlpm.linha_insumo),"",IF(_xlpm.preco_uf<>0,0%,100%))), IF(AND($A21="INSUMO",$A$8="SEM ENCARGOS SOCIAIS"),_xlfn.LET(_xlpm.linha_insumo,MATCH($B21,'ISE'!$B:$B,0),_xlpm.coluna_uf,MATCH($B$8,'ISE'!$F$10:$AF$10,0),_xlpm.preco_uf,INDEX('ISE'!$F:$AF,_xlpm.linha_insumo,_xlpm.coluna_uf),IF(ISERROR(_xlpm.linha_insumo),"",IF(_xlpm.preco_uf<>0,0%,100%))), IF(AND($A21="COMPOSICAO",$A$8="SEM DESONERAÇÃO"),_xlfn.XLOOKUP($B21,'CSD'!B:B,OFFSET('CSD'!$D:$D,0,1+MATCH($B$8,'CSD'!$E$4:$BF$4,0)),0), IF(AND($A21="COMPOSICAO",$A$8="COM DESONERAÇÃO"),_xlfn.XLOOKUP($B21,'CCD'!B:B,OFFSET('CCD'!$D:$D,0,1+MATCH($B$8,'CCD'!$E$4:$BF$4,0)),0), IF(AND($A21="COMPOSICAO",$A$8="SEM ENCARGOS SOCIAIS"),_xlfn.XLOOKUP($B21,'CSE'!B:B,OFFSET('CSE'!$D:$D,0,1+MATCH($B$8,'CSE'!$E$9:$BF$9,0)),0),"" )))))))} -> 0
F22: {=IF($A22="","", IF(AND($A22="INSUMO",$A$8="SEM DESONERAÇÃO"),_xlfn.LET(_xlpm.linha_insumo,MATCH($B22,'ISD'!$B:$B,0),_xlpm.coluna_uf,MATCH($B$8,'ISD'!$F$4:$AF$4,0),_xlpm.coluna_sp,MATCH("SP",'ISD'!$F$4:$AF$4,0),_xlpm.preco_uf,INDEX('ISD'!$F:$AF,_xlpm.linha_insumo,_xlpm.coluna_uf),_xlpm.preco_sp,INDEX('ISD'!$F:$AF,_xlpm.linha_insumo,_xlpm.coluna_sp), _xlpm.preco_regional_as,INDEX($M:$M,MATCH($B22&"_"&$B$8,$K:$K,0)), IF(ISERROR(_xlpm.linha_insumo),0,IF(_xlpm.preco_uf<>0,_xlpm.preco_uf,IF(ISNUMBER(_xlpm.preco_regional_as),_xlpm.preco_regional_as,_xlpm.preco_sp)))), IF(AND($A22="INSUMO",$A$8="COM DESONERAÇÃO"),_xlfn.LET(_xlpm.linha_insumo,MATCH($B22,'ICD'!$B:$B,0),_xlpm.coluna_uf,MATCH($B$8,'ICD'!$F$4:$AF$4,0),_xlpm.coluna_sp,MATCH("SP",'ICD'!$F$4:$AF$4,0),_xlpm.preco_uf,INDEX('ICD'!$F:$AF,_xlpm.linha_insumo,_xlpm.coluna_uf),_xlpm.preco_sp,INDEX('ICD'!$F:$AF,_xlpm.linha_insumo,_xlpm.coluna_sp), _xlpm.preco_regional_as,INDEX($N:$N,MATCH($B22&"_"&$B$8,$K:$K,0)), IF(ISERROR(_xlpm.linha_insumo),0,IF(_xlpm.preco_uf<>0,_xlpm.preco_uf,IF(ISNUMBER(_xlpm.preco_regional_as),_xlpm.preco_regional_as,_xlpm.preco_sp)))), IF(AND($A22="INSUMO",$A$8="SEM ENCARGOS SOCIAIS"),_xlfn.LET(_xlpm.linha_insumo,MATCH($B22,'ISE'!$B:$B,0),_xlpm.coluna_uf,MATCH($B$8,'ISE'!$F$10:$AF$10,0),_xlpm.coluna_sp,MATCH("SP",'ISE'!$F$10:$AF$10,0),_xlpm.preco_uf,INDEX('ISE'!$F:$AF,_xlpm.linha_insumo,_xlpm.coluna_uf),_xlpm.preco_sp,INDEX('ISE'!$F:$AF,_xlpm.linha_insumo,_xlpm.coluna_sp), _xlpm.preco_regional_as,INDEX($L:$L,MATCH($B22&"_"&$B$8,$K:$K,0)), IF(ISERROR(_xlpm.linha_insumo),0,IF(_xlpm.preco_uf<>0,_xlpm.preco_uf,IF(ISNUMBER(_xlpm.preco_regional_as),_xlpm.preco_regional_as,_xlpm.preco_sp)))), IF(AND($A22="COMPOSICAO",$A$8="SEM DESONERAÇÃO"),_xlfn.XLOOKUP($B22,'CSD'!B:B,OFFSET('CSD'!$D:$D,0,MATCH($B$8,'CSD'!$E$4:$BF$4,0)),0), IF(AND($A22="COMPOSICAO",$A$8="COM DESONERAÇÃO"),_xlfn.XLOOKUP($B22,'CCD'!B:B,OFFSET('CCD'!$D:$D,0,MATCH($B$8,'CCD'!$E$4:$BF$4,0)),0), IF(AND($A22="COMPOSICAO",$A$8="SEM ENCARGOS SOCIAIS"),_xlfn.XLOOKUP($B22,'CSE'!B:B,OFFSET('CSE'!$D:$D,0,MATCH($B$8,'CSE'!$E$9:$BF$9,0)),0),"" )))))))} -> 0 | G22: =IF($A22="","",TRUNC(E22*F22,2)) -> 0 | H22: {=IF($A22="","", IF(AND($A22="INSUMO",$A$8="SEM DESONERAÇÃO"),_xlfn.LET(_xlpm.linha_insumo,MATCH($B22,'ISD'!$B:$B,0),_xlpm.coluna_uf,MATCH($B$8,'ISD'!$F$4:$AF$4,0),_xlpm.preco_uf,INDEX('ISD'!$F:$AF,_xlpm.linha_insumo,_xlpm.coluna_uf),IF(ISERROR(_xlpm.linha_insumo),"",IF(_xlpm.preco_uf<>0,0%,100%))), IF(AND($A22="INSUMO",$A$8="COM DESONERAÇÃO"),_xlfn.LET(_xlpm.linha_insumo,MATCH($B22,'ICD'!$B:$B,0),_xlpm.coluna_uf,MATCH($B$8,'ICD'!$F$4:$AF$4,0),_xlpm.preco_uf,INDEX('ICD'!$F:$AF,_xlpm.linha_insumo,_xlpm.coluna_uf),IF(ISERROR(_xlpm.linha_insumo),"",IF(_xlpm.preco_uf<>0,0%,100%))), IF(AND($A22="INSUMO",$A$8="SEM ENCARGOS SOCIAIS"),_xlfn.LET(_xlpm.linha_insumo,MATCH($B22,'ISE'!$B:$B,0),_xlpm.coluna_uf,MATCH($B$8,'ISE'!$F$10:$AF$10,0),_xlpm.preco_uf,INDEX('ISE'!$F:$AF,_xlpm.linha_insumo,_xlpm.coluna_uf),IF(ISERROR(_xlpm.linha_insumo),"",IF(_xlpm.preco_uf<>0,0%,100%))), IF(AND($A22="COMPOSICAO",$A$8="SEM DESONERAÇÃO"),_xlfn.XLOOKUP($B22,'CSD'!B:B,OFFSET('CSD'!$D:$D,0,1+MATCH($B$8,'CSD'!$E$4:$BF$4,0)),0), IF(AND($A22="COMPOSICAO",$A$8="COM DESONERAÇÃO"),_xlfn.XLOOKUP($B22,'CCD'!B:B,OFFSET('CCD'!$D:$D,0,1+MATCH($B$8,'CCD'!$E$4:$BF$4,0)),0), IF(AND($A22="COMPOSICAO",$A$8="SEM ENCARGOS SOCIAIS"),_xlfn.XLOOKUP($B22,'CSE'!B:B,OFFSET('CSE'!$D:$D,0,1+MATCH($B$8,'CSE'!$E$9:$BF$9,0)),0),"" )))))))} -> 0
F23: {=IF($A23="","", IF(AND($A23="INSUMO",$A$8="SEM DESONERAÇÃO"),_xlfn.LET(_xlpm.linha_insumo,MATCH($B23,'ISD'!$B:$B,0),_xlpm.coluna_uf,MATCH($B$8,'ISD'!$F$4:$AF$4,0),_xlpm.coluna_sp,MATCH("SP",'ISD'!$F$4:$AF$4,0),_xlpm.preco_uf,INDEX('ISD'!$F:$AF,_xlpm.linha_insumo,_xlpm.coluna_uf),_xlpm.preco_sp,INDEX('ISD'!$F:$AF,_xlpm.linha_insumo,_xlpm.coluna_sp), _xlpm.preco_regional_as,INDEX($M:$M,MATCH($B23&"_"&$B$8,$K:$K,0)), IF(ISERROR(_xlpm.linha_insumo),0,IF(_xlpm.preco_uf<>0,_xlpm.preco_uf,IF(ISNUMBER(_xlpm.preco_regional_as),_xlpm.preco_regional_as,_xlpm.preco_sp)))), IF(AND($A23="INSUMO",$A$8="COM DESONERAÇÃO"),_xlfn.LET(_xlpm.linha_insumo,MATCH($B23,'ICD'!$B:$B,0),_xlpm.coluna_uf,MATCH($B$8,'ICD'!$F$4:$AF$4,0),_xlpm.coluna_sp,MATCH("SP",'ICD'!$F$4:$AF$4,0),_xlpm.preco_uf,INDEX('ICD'!$F:$AF,_xlpm.linha_insumo,_xlpm.coluna_uf),_xlpm.preco_sp,INDEX('ICD'!$F:$AF,_xlpm.linha_insumo,_xlpm.coluna_sp), _xlpm.preco_regional_as,INDEX($N:$N,MATCH($B23&"_"&$B$8,$K:$K,0)), IF(ISERROR(_xlpm.linha_insumo),0,IF(_xlpm.preco_uf<>0,_xlpm.preco_uf,IF(ISNUMBER(_xlpm.preco_regional_as),_xlpm.preco_regional_as,_xlpm.preco_sp)))), IF(AND($A23="INSUMO",$A$8="SEM ENCARGOS SOCIAIS"),_xlfn.LET(_xlpm.linha_insumo,MATCH($B23,'ISE'!$B:$B,0),_xlpm.coluna_uf,MATCH($B$8,'ISE'!$F$10:$AF$10,0),_xlpm.coluna_sp,MATCH("SP",'ISE'!$F$10:$AF$10,0),_xlpm.preco_uf,INDEX('ISE'!$F:$AF,_xlpm.linha_insumo,_xlpm.coluna_uf),_xlpm.preco_sp,INDEX('ISE'!$F:$AF,_xlpm.linha_insumo,_xlpm.coluna_sp), _xlpm.preco_regional_as,INDEX($L:$L,MATCH($B23&"_"&$B$8,$K:$K,0)), IF(ISERROR(_xlpm.linha_insumo),0,IF(_xlpm.preco_uf<>0,_xlpm.preco_uf,IF(ISNUMBER(_xlpm.preco_regional_as),_xlpm.preco_regional_as,_xlpm.preco_sp)))), IF(AND($A23="COMPOSICAO",$A$8="SEM DESONERAÇÃO"),_xlfn.XLOOKUP($B23,'CSD'!B:B,OFFSET('CSD'!$D:$D,0,MATCH($B$8,'CSD'!$E$4:$BF$4,0)),0), IF(AND($A23="COMPOSICAO",$A$8="COM DESONERAÇÃO"),_xlfn.XLOOKUP($B23,'CCD'!B:B,OFFSET('CCD'!$D:$D,0,MATCH($B$8,'CCD'!$E$4:$BF$4,0)),0), IF(AND($A23="COMPOSICAO",$A$8="SEM ENCARGOS SOCIAIS"),_xlfn.XLOOKUP($B23,'CSE'!B:B,OFFSET('CSE'!$D:$D,0,MATCH($B$8,'CSE'!$E$9:$BF$9,0)),0),"" )))))))} -> 0 | G23: =IF($A23="","",TRUNC(E23*F23,2)) -> 0 | H23: {=IF($A23="","", IF(AND($A23="INSUMO",$A$8="SEM DESONERAÇÃO"),_xlfn.LET(_xlpm.linha_insumo,MATCH($B23,'ISD'!$B:$B,0),_xlpm.coluna_uf,MATCH($B$8,'ISD'!$F$4:$AF$4,0),_xlpm.preco_uf,INDEX('ISD'!$F:$AF,_xlpm.linha_insumo,_xlpm.coluna_uf),IF(ISERROR(_xlpm.linha_insumo),"",IF(_xlpm.preco_uf<>0,0%,100%))), IF(AND($A23="INSUMO",$A$8="COM DESONERAÇÃO"),_xlfn.LET(_xlpm.linha_insumo,MATCH($B23,'ICD'!$B:$B,0),_xlpm.coluna_uf,MATCH($B$8,'ICD'!$F$4:$AF$4,0),_xlpm.preco_uf,INDEX('ICD'!$F:$AF,_xlpm.linha_insumo,_xlpm.coluna_uf),IF(ISERROR(_xlpm.linha_insumo),"",IF(_xlpm.preco_uf<>0,0%,100%))), IF(AND($A23="INSUMO",$A$8="SEM ENCARGOS SOCIAIS"),_xlfn.LET(_xlpm.linha_insumo,MATCH($B23,'ISE'!$B:$B,0),_xlpm.coluna_uf,MATCH($B$8,'ISE'!$F$10:$AF$10,0),_xlpm.preco_uf,INDEX('ISE'!$F:$AF,_xlpm.linha_insumo,_xlpm.coluna_uf),IF(ISERROR(_xlpm.linha_insumo),"",IF(_xlpm.preco_uf<>0,0%,100%))), IF(AND($A23="COMPOSICAO",$A$8="SEM DESONERAÇÃO"),_xlfn.XLOOKUP($B23,'CSD'!B:B,OFFSET('CSD'!$D:$D,0,1+MATCH($B$8,'CSD'!$E$4:$BF$4,0)),0), IF(AND($A23="COMPOSICAO",$A$8="COM DESONERAÇÃO"),_xlfn.XLOOKUP($B23,'CCD'!B:B,OFFSET('CCD'!$D:$D,0,1+MATCH($B$8,'CCD'!$E$4:$BF$4,0)),0), IF(AND($A23="COMPOSICAO",$A$8="SEM ENCARGOS SOCIAIS"),_xlfn.XLOOKUP($B23,'CSE'!B:B,OFFSET('CSE'!$D:$D,0,1+MATCH($B$8,'CSE'!$E$9:$BF$9,0)),0),"" )))))))} -> 0
F24: {=IF($A24="","", IF(AND($A24="INSUMO",$A$8="SEM DESONERAÇÃO"),_xlfn.LET(_xlpm.linha_insumo,MATCH($B24,'ISD'!$B:$B,0),_xlpm.coluna_uf,MATCH($B$8,'ISD'!$F$4:$AF$4,0),_xlpm.coluna_sp,MATCH("SP",'ISD'!$F$4:$AF$4,0),_xlpm.preco_uf,INDEX('ISD'!$F:$AF,_xlpm.linha_insumo,_xlpm.coluna_uf),_xlpm.preco_sp,INDEX('ISD'!$F:$AF,_xlpm.linha_insumo,_xlpm.coluna_sp), _xlpm.preco_regional_as,INDEX($M:$M,MATCH($B24&"_"&$B$8,$K:$K,0)), IF(ISERROR(_xlpm.linha_insumo),0,IF(_xlpm.preco_uf<>0,_xlpm.preco_uf,IF(ISNUMBER(_xlpm.preco_regional_as),_xlpm.preco_regional_as,_xlpm.preco_sp)))), IF(AND($A24="INSUMO",$A$8="COM DESONERAÇÃO"),_xlfn.LET(_xlpm.linha_insumo,MATCH($B24,'ICD'!$B:$B,0),_xlpm.coluna_uf,MATCH($B$8,'ICD'!$F$4:$AF$4,0),_xlpm.coluna_sp,MATCH("SP",'ICD'!$F$4:$AF$4,0),_xlpm.preco_uf,INDEX('ICD'!$F:$AF,_xlpm.linha_insumo,_xlpm.coluna_uf),_xlpm.preco_sp,INDEX('ICD'!$F:$AF,_xlpm.linha_insumo,_xlpm.coluna_sp), _xlpm.preco_regional_as,INDEX($N:$N,MATCH($B24&"_"&$B$8,$K:$K,0)), IF(ISERROR(_xlpm.linha_insumo),0,IF(_xlpm.preco_uf<>0,_xlpm.preco_uf,IF(ISNUMBER(_xlpm.preco_regional_as),_xlpm.preco_regional_as,_xlpm.preco_sp)))), IF(AND($A24="INSUMO",$A$8="SEM ENCARGOS SOCIAIS"),_xlfn.LET(_xlpm.linha_insumo,MATCH($B24,'ISE'!$B:$B,0),_xlpm.coluna_uf,MATCH($B$8,'ISE'!$F$10:$AF$10,0),_xlpm.coluna_sp,MATCH("SP",'ISE'!$F$10:$AF$10,0),_xlpm.preco_uf,INDEX('ISE'!$F:$AF,_xlpm.linha_insumo,_xlpm.coluna_uf),_xlpm.preco_sp,INDEX('ISE'!$F:$AF,_xlpm.linha_insumo,_xlpm.coluna_sp), _xlpm.preco_regional_as,INDEX($L:$L,MATCH($B24&"_"&$B$8,$K:$K,0)), IF(ISERROR(_xlpm.linha_insumo),0,IF(_xlpm.preco_uf<>0,_xlpm.preco_uf,IF(ISNUMBER(_xlpm.preco_regional_as),_xlpm.preco_regional_as,_xlpm.preco_sp)))), IF(AND($A24="COMPOSICAO",$A$8="SEM DESONERAÇÃO"),_xlfn.XLOOKUP($B24,'CSD'!B:B,OFFSET('CSD'!$D:$D,0,MATCH($B$8,'CSD'!$E$4:$BF$4,0)),0), IF(AND($A24="COMPOSICAO",$A$8="COM DESONERAÇÃO"),_xlfn.XLOOKUP($B24,'CCD'!B:B,OFFSET('CCD'!$D:$D,0,MATCH($B$8,'CCD'!$E$4:$BF$4,0)),0), IF(AND($A24="COMPOSICAO",$A$8="SEM ENCARGOS SOCIAIS"),_xlfn.XLOOKUP($B24,'CSE'!B:B,OFFSET('CSE'!$D:$D,0,MATCH($B$8,'CSE'!$E$9:$BF$9,0)),0),"" )))))))} -> 0 | G24: =IF($A24="","",TRUNC(E24*F24,2)) -> 0 | H24: {=IF($A24="","", IF(AND($A24="INSUMO",$A$8="SEM DESONERAÇÃO"),_xlfn.LET(_xlpm.linha_insumo,MATCH($B24,'ISD'!$B:$B,0),_xlpm.coluna_uf,MATCH($B$8,'ISD'!$F$4:$AF$4,0),_xlpm.preco_uf,INDEX('ISD'!$F:$AF,_xlpm.linha_insumo,_xlpm.coluna_uf),IF(ISERROR(_xlpm.linha_insumo),"",IF(_xlpm.preco_uf<>0,0%,100%))), IF(AND($A24="INSUMO",$A$8="COM DESONERAÇÃO"),_xlfn.LET(_xlpm.linha_insumo,MATCH($B24,'ICD'!$B:$B,0),_xlpm.coluna_uf,MATCH($B$8,'ICD'!$F$4:$AF$4,0),_xlpm.preco_uf,INDEX('ICD'!$F:$AF,_xlpm.linha_insumo,_xlpm.coluna_uf),IF(ISERROR(_xlpm.linha_insumo),"",IF(_xlpm.preco_uf<>0,0%,100%))), IF(AND($A24="INSUMO",$A$8="SEM ENCARGOS SOCIAIS"),_xlfn.LET(_xlpm.linha_insumo,MATCH($B24,'ISE'!$B:$B,0),_xlpm.coluna_uf,MATCH($B$8,'ISE'!$F$10:$AF$10,0),_xlpm.preco_uf,INDEX('ISE'!$F:$AF,_xlpm.linha_insumo,_xlpm.coluna_uf),IF(ISERROR(_xlpm.linha_insumo),"",IF(_xlpm.preco_uf<>0,0%,100%))), IF(AND($A24="COMPOSICAO",$A$8="SEM DESONERAÇÃO"),_xlfn.XLOOKUP($B24,'CSD'!B:B,OFFSET('CSD'!$D:$D,0,1+MATCH($B$8,'CSD'!$E$4:$BF$4,0)),0), IF(AND($A24="COMPOSICAO",$A$8="COM DESONERAÇÃO"),_xlfn.XLOOKUP($B24,'CCD'!B:B,OFFSET('CCD'!$D:$D,0,1+MATCH($B$8,'CCD'!$E$4:$BF$4,0)),0), IF(AND($A24="COMPOSICAO",$A$8="SEM ENCARGOS SOCIAIS"),_xlfn.XLOOKUP($B24,'CSE'!B:B,OFFSET('CSE'!$D:$D,0,1+MATCH($B$8,'CSE'!$E$9:$BF$9,0)),0),"" )))))))} -> 0
... F201: {=IF($A201="","", IF(AND($A201="INSUMO",$A$8="SEM DESONERAÇÃO"),_xlfn.LET(_xlpm.linha_insumo,MATCH($B201,'ISD'!$B:$B,0),_xlpm.coluna_uf,MATCH($B$8,'ISD'!$F$4:$AF$4,0),_xlpm.coluna_sp,MATCH("SP",'ISD'!$F$4:$AF$4,0),_xlpm.preco_uf,INDEX('ISD'!$F:$AF,_xlpm.linha_insumo,_xlpm.coluna_uf),_xlpm.preco_sp,INDEX('ISD'!$F:$AF,_xlpm.linha_insumo,_xlpm.coluna_sp), _xlpm.preco_regional_as,INDEX($M:$M,MATCH($B201&"_"&$B$8,$K:$K,0)), IF(ISERROR(_xlpm.linha_insumo),0,IF(_xlpm.preco_uf<>0,_xlpm.preco_uf,IF(ISNUMBER(_xlpm.preco_regional_as),_xlpm.preco_regional_as,_xlpm.preco_sp)))), IF(AND($A201="INSUMO",$A$8="COM DESONERAÇÃO"),_xlfn.LET(_xlpm.linha_insumo,MATCH($B201,'ICD'!$B:$B,0),_xlpm.coluna_uf,MATCH($B$8,'ICD'!$F$4:$AF$4,0),_xlpm.coluna_sp,MATCH("SP",'ICD'!$F$4:$AF$4,0),_xlpm.preco_uf,INDEX('ICD'!$F:$AF,_xlpm.linha_insumo,_xlpm.coluna_uf),_xlpm.preco_sp,INDEX('ICD'!$F:$AF,_xlpm.linha_insumo,_xlpm.coluna_sp), _xlpm.preco_regional_as,INDEX($N:$N,MATCH($B201&"_"&$B$8,$K:$K,0)), IF(ISERROR(_xlpm.linha_insumo),0,IF(_xlpm.preco_uf<>0,_xlpm.preco_uf,IF(ISNUMBER(_xlpm.preco_regional_as),_xlpm.preco_regional_as,_xlpm.preco_sp)))), IF(AND($A201="INSUMO",$A$8="SEM ENCARGOS SOCIAIS"),_xlfn.LET(_xlpm.linha_insumo,MATCH($B201,'ISE'!$B:$B,0),_xlpm.coluna_uf,MATCH($B$8,'ISE'!$F$10:$AF$10,0),_xlpm.coluna_sp,MATCH("SP",'ISE'!$F$10:$AF$10,0),_xlpm.preco_uf,INDEX('ISE'!$F:$AF,_xlpm.linha_insumo,_xlpm.coluna_uf),_xlpm.preco_sp,INDEX('ISE'!$F:$AF,_xlpm.linha_insumo,_xlpm.coluna_sp), _xlpm.preco_regional_as,INDEX($L:$L,MATCH($B201&"_"&$B$8,$K:$K,0)), IF(ISERROR(_xlpm.linha_insumo),0,IF(_xlpm.preco_uf<>0,_xlpm.preco_uf,IF(ISNUMBER(_xlpm.preco_regional_as),_xlpm.preco_regional_as,_xlpm.preco_sp)))), IF(AND($A201="COMPOSICAO",$A$8="SEM DESONERAÇÃO"),_xlfn.XLOOKUP($B201,'CSD'!B:B,OFFSET('CSD'!$D:$D,0,MATCH($B$8,'CSD'!$E$4:$BF$4,0)),0), IF(AND($A201="COMPOSICAO",$A$8="COM DESONERAÇÃO"),_xlfn.XLOOKUP($B201,'CCD'!B:B,OFFSET('CCD'!$D:$D,0,MATCH($B$8,'CCD'!$E$4:$BF$4,0)),0), IF(AND($A201="COMPOSICAO",$A$8="SEM ENCARGOS SOCIAIS"),_xlfn.XLOOKUP($B201,'CSE'!B:B,OFFSET('CSE'!$D:$D,0,MATCH($B$8,'CSE'!$E$9:$BF$9,0)),0),"" )))))))} -> 0 | G201: =IF($A201="","",TRUNC(E201*F201,2)) -> 0 | H201: {=IF($A201="","", IF(AND($A201="INSUMO",$A$8="SEM DESONERAÇÃO"),_xlfn.LET(_xlpm.linha_insumo,MATCH($B201,'ISD'!$B:$B,0),_xlpm.coluna_uf,MATCH($B$8,'ISD'!$F$4:$AF$4,0),_xlpm.preco_uf,INDEX('ISD'!$F:$AF,_xlpm.linha_insumo,_xlpm.coluna_uf),IF(ISERROR(_xlpm.linha_insumo),"",IF(_xlpm.preco_uf<>0,0%,100%))), IF(AND($A201="INSUMO",$A$8="COM DESONERAÇÃO"),_xlfn.LET(_xlpm.linha_insumo,MATCH($B201,'ICD'!$B:$B,0),_xlpm.coluna_uf,MATCH($B$8,'ICD'!$F$4:$AF$4,0),_xlpm.preco_uf,INDEX('ICD'!$F:$AF,_xlpm.linha_insumo,_xlpm.coluna_uf),IF(ISERROR(_xlpm.linha_insumo),"",IF(_xlpm.preco_uf<>0,0%,100%))), IF(AND($A201="INSUMO",$A$8="SEM ENCARGOS SOCIAIS"),_xlfn.LET(_xlpm.linha_insumo,MATCH($B201,'ISE'!$B:$B,0),_xlpm.coluna_uf,MATCH($B$8,'ISE'!$F$10:$AF$10,0),_xlpm.preco_uf,INDEX('ISE'!$F:$AF,_xlpm.linha_insumo,_xlpm.coluna_uf),IF(ISERROR(_xlpm.linha_insumo),"",IF(_xlpm.preco_uf<>0,0%,100%))), IF(AND($A201="COMPOSICAO",$A$8="SEM DESONERAÇÃO"),_xlfn.XLOOKUP($B201,'CSD'!B:B,OFFSET('CSD'!$D:$D,0,1+MATCH($B$8,'CSD'!$E$4:$BF$4,0)),0), IF(AND($A201="COMPOSICAO",$A$8="COM DESONERAÇÃO"),_xlfn.XLOOKUP($B201,'CCD'!B:B,OFFSET('CCD'!$D:$D,0,1+MATCH($B$8,'CCD'!$E$4:$BF$4,0)),0), IF(AND($A201="COMPOSICAO",$A$8="SEM ENCARGOS SOCIAIS"),_xlfn.XLOOKUP($B201,'CSE'!B:B,OFFSET('CSE'!$D:$D,0,1+MATCH($B$8,'CSE'!$E$9:$BF$9,0)),0),"" )))))))} -> 0
